Workbook
Name MovieRange: Data!$A$1:$N$1077
Name NativeTimeline_Release_Date: #N/A
Name Slicer_Country: #N/A

Sheet Pivot Table
A2: Slicer to filter Pivot 1 table by Country Wise | L2: Timeline to filter Pivot 2 table by Time Series
V12: Top 20 Movies with Highest Budget
A13: Pivot 1 | L13: Pivot 2
A14: Language | B14: Genre | C14: Budget | D14: Box Office | E14: Profit | F14: Oscar Wins | G14: Nominations | H14: Run Time (Min. | L14: Row Labels | M14: Budget | N14: Box Office | O14: Profit | P14: Oscar Wins | Q14: Nominations | R14: Run Time (Min. | V14: Title | W14: Budget | X14: Box Office | Y14: Profit | Z14: Oscar Wins | AA14: Nominations | AB14: Run Time (Min.
A15: Cantonese | B15: Martial Arts | C15: 110965000 | D15: 408736047 | E15: 297771047 | F15: 0 | G15: 0 | H15: 1010 | L15: 1931 | M15: 768000 | N15: 12506000 | O15: 11738000 | P15: 0 | Q15: 1 | R15: 239 | V15: Dracula | W15: 355000 | X15: 355000 | Y15: 0 | Z15: 0 | AA15: 0 | AB15: 85
B16: Action | C16: 4500000 | D16: 4500000 | E16: 0 | F16: 0 | G16: 0 | H16: 128 | L16: 11366 | M16: 355000 | N16: 355000 | O16: 0 | P16: 0 | Q16: 0 | R16: 85 | V16: Frankenstein | W16: 262000 | X16: 12000000 | Y16: 11738000 | Z16: 0 | AA16: 0 | AB16: 71
A17: Cantonese Total | C17: 115465000 | D17: 413236047 | E17: 297771047 | F17: 0 | G17: 0 | H17: 1138 | L17: 11436 | M17: 151000 | N17: 151000 | O17: 0 | P17: 0 | Q17: 1 | R17: 83 | V17: The Public Enemy | W17: 151000 | X17: 151000 | Y17: 0 | Z17: 0 | AA17: 1 | AB17: 83
A18: Mandarin | B18: War | C18: 40000000 | D18: 40000000 | E18: 0 | F18: 0 | G18: 0 | H18: 127 | L18: 11648 | M18: 262000 | N18: 12000000 | O18: 11738000 | P18: 0 | Q18: 0 | R18: 71 | V18: Grand Total | W18: 768000 | X18: 12506000 | Y18: 11738000 | Z18: 0 | AA18: 1 | AB18: 239
B19: Martial Arts | C19: 38230000 | D19: 55700000 | E19: 17470000 | F19: 0 | G19: 0 | H19: 477 | L19: Grand Total | M19: 768000 | N19: 12506000 | O19: 11738000 | P19: 0 | Q19: 1 | R19: 239
A20: Mandarin Total | C20: 78230000 | D20: 95700000 | E20: 17470000 | F20: 0 | G20: 0 | H20: 604
A21: English | B21: Martial Arts | C21: 850000 | D21: 22000000 | E21: 21150000 | F21: 0 | G21: 0 | H21: 102
A22: English Total | C22: 850000 | D22: 22000000 | E22: 21150000 | F22: 0 | G22: 0 | H22: 102
A23: Grand Total | C23: 194545000 | D23: 530936047 | E23: 336391047 | F23: 0 | G23: 0 | H23: 1844
V39: Top 20 Movies by Highest Profit
V41: Title | W41: Budget | X41: Box Office | Y41: Profit | Z41: Oscar Wins | AA41: Nominations | AB41: Run Time (Min.
V42: Frankenstein | W42: 262000 | X42: 12000000 | Y42: 11738000 | Z42: 0 | AA42: 0 | AB42: 71
V43: The Public Enemy | W43: 151000 | X43: 151000 | Y43: 0 | Z43: 0 | AA43: 1 | AB43: 83
V44: Dracula | W44: 355000 | X44: 355000 | Y44: 0 | Z44: 0 | AA44: 0 | AB44: 85
V45: Grand Total | W45: 768000 | X45: 12506000 | Y45: 11738000 | Z45: 0 | AA45: 1 | AB45: 239
V65: Year wise Movies Count
V67: Years (Release Date) | W67: Movies Releases | X67: Budget | Y67: Box Office | Z67: Profit | AA67: Oscar Wins | AB67: Nominations | AC67: Run Time (Min.
V68: 1931 | W68: 3 | X68: 768000 | Y68: 12506000 | Z68: 11738000 | AA68: 0 | AB68: 1 | AC68: 239
V69: Grand Total | W69: 3 | X69: 768000 | Y69: 12506000 | Z69: 11738000 | AA69: 0 | AB69: 1 | AC69: 239
V157: Movies With Most Oscars Wins
V159: Title | W159: Years (Release Date) | X159: Budget | Y159: Box Office | Z159: Profit | AA159: Oscar Wins | AB159: Nominations | AC159: Run Time (Min.
V160: Grand Total

Sheet Vlookup
A1: DETAILS OF MOVIES WHO WON MORE THAN 5 OSCARS
A3: Movie Name | B3: Release Date | C3: Run Time | D3: Genre | E3: Director | F3: Studio | G3: Country | H3: Language | I3: Certificate | J3: Budget | K3: Box Office | L3: Nominations | M3: Oscar Wins | U3: Title
A4: Titanic | B4: =VLOOKUP($A4,Table1[[#All],[Title]:[Oscar Wins]],COLUMNS($A$3:B3),0) -> 35818 | C4: =VLOOKUP($A4,Table1[[#All],[Title]:[Oscar Wins]],COLUMNS($A$3:C3),0) -> 194 | D4: =VLOOKUP($A4,Table1[[#All],[Title]:[Oscar Wins]],COLUMNS($A$3:D3),0) -> Romance | E4: =VLOOKUP($A4,Table1[[#All],[Title]:[Oscar Wins]],COLUMNS($A$3:E3),0) -> James Cameron | F4: =VLOOKUP($A4,Table1[[#All],[Title]:[Oscar Wins]],COLUMNS($A$3:F3),0) -> 20th Century Fox | G4: =VLOOKUP($A4,Table1[[#All],[Title]:[Oscar Wins]],COLUMNS($A$3:G3),0) -> United States | H4: =VLOOKUP($A4,Table1[[#All],[Title]:[Oscar Wins]],COLUMNS($A$3:H3),0) -> English | I4: =VLOOKUP($A4,Table1[[#All],[Title]:[Oscar Wins]],COLUMNS($A$3:I3),0) -> 12 | J4: =ROUND(VLOOKUP($A4,Table1[[#All],[Title]:[Oscar Wins]],COLUMNS($A$3:J3),0)/1000000,2)&" M" -> 200 M | K4: =ROUND(VLOOKUP($A4,Table1[[#All],[Title]:[Oscar Wins]],COLUMNS($A$3:K3),0)/1000000,2)&" M" -> 2186.77 M | L4: =VLOOKUP($A4,Table1[[#All],[Title]:[Oscar Wins]],COLUMNS($A$3:L3),0) -> 14 | M4: =VLOOKUP($A4,Table1[[#All],[Title]:[Oscar Wins]],COLUMNS($A$3:M3),0) -> 11 | U4: 10
A5: The Lord of the Rings: Return of the King | B5: =VLOOKUP($A5,Table1[[#All],[Title]:[Oscar Wins]],COLUMNS($A$3:B4),0) -> 37972 | C5: =VLOOKUP($A5,Table1[[#All],[Title]:[Oscar Wins]],COLUMNS($A$3:C4),0) -> 201 | D5: =VLOOKUP($A5,Table1[[#All],[Title]:[Oscar Wins]],COLUMNS($A$3:D4),0) -> Fantasy | E5: =VLOOKUP($A5,Table1[[#All],[Title]:[Oscar Wins]],COLUMNS($A$3:E4),0) -> Peter Jackson | F5: =VLOOKUP($A5,Table1[[#All],[Title]:[Oscar Wins]],COLUMNS($A$3:F4),0) -> WingNut Films | G5: =VLOOKUP($A5,Table1[[#All],[Title]:[Oscar Wins]],COLUMNS($A$3:G4),0) -> New Zealand | H5: =VLOOKUP($A5,Table1[[#All],[Title]:[Oscar Wins]],COLUMNS($A$3:H4),0) -> English | I5: =VLOOKUP($A5,Table1[[#All],[Title]:[Oscar Wins]],COLUMNS($A$3:I4),0) -> 12A | J5: =ROUND(VLOOKUP($A5,Table1[[#All],[Title]:[Oscar Wins]],COLUMNS($A$3:J4),0)/1000000,2)&" M" -> 94 M | K5: =ROUND(VLOOKUP($A5,Table1[[#All],[Title]:[Oscar Wins]],COLUMNS($A$3:K4),0)/1000000,2)&" M" -> 1119.93 M | L5: =VLOOKUP($A5,Table1[[#All],[Title]:[Oscar Wins]],COLUMNS($A$3:L4),0) -> 11 | M5: =VLOOKUP($A5,Table1[[#All],[Title]:[Oscar Wins]],COLUMNS($A$3:M4),0) -> 11 | U5: 300
A6: Ben-Hur | B6: =VLOOKUP($A6,Table1[[#All],[Title]:[Oscar Wins]],COLUMNS($A$3:B5),0) -> 21872 | C6: =VLOOKUP($A6,Table1[[#All],[Title]:[Oscar Wins]],COLUMNS($A$3:C5),0) -> 212 | D6: =VLOOKUP($A6,Table1[[#All],[Title]:[Oscar Wins]],COLUMNS($A$3:D5),0) -> Drama | E6: =VLOOKUP($A6,Table1[[#All],[Title]:[Oscar Wins]],COLUMNS($A$3:E5),0) -> William Wyler | F6: =VLOOKUP($A6,Table1[[#All],[Title]:[Oscar Wins]],COLUMNS($A$3:F5),0) -> Metro-Goldwyn-Mayer | G6: =VLOOKUP($A6,Table1[[#All],[Title]:[Oscar Wins]],COLUMNS($A$3:G5),0) -> United States | H6: =VLOOKUP($A6,Table1[[#All],[Title]:[Oscar Wins]],COLUMNS($A$3:H5),0) -> English | I6: =VLOOKUP($A6,Table1[[#All],[Title]:[Oscar Wins]],COLUMNS($A$3:I5),0) -> PG | J6: =ROUND(VLOOKUP($A6,Table1[[#All],[Title]:[Oscar Wins]],COLUMNS($A$3:J5),0)/1000000,2)&" M" -> 15.2 M | K6: =ROUND(VLOOKUP($A6,Table1[[#All],[Title]:[Oscar Wins]],COLUMNS($A$3:K5),0)/1000000,2)&" M" -> 146.9 M | L6: =VLOOKUP($A6,Table1[[#All],[Title]:[Oscar Wins]],COLUMNS($A$3:L5),0) -> 12 | M6: =VLOOKUP($A6,Table1[[#All],[Title]:[Oscar Wins]],COLUMNS($A$3:M5),0) -> 11 | U6: 2012
A7: West Side Story | B7: =VLOOKUP($A7,Table1[[#All],[Title]:[Oscar Wins]],COLUMNS($A$3:B6),0) -> 22572 | C7: =VLOOKUP($A7,Table1[[#All],[Title]:[Oscar Wins]],COLUMNS($A$3:C6),0) -> 152 | D7: =VLOOKUP($A7,Table1[[#All],[Title]:[Oscar Wins]],COLUMNS($A$3:D6),0) -> Musical | E7: =VLOOKUP($A7,Table1[[#All],[Title]:[Oscar Wins]],COLUMNS($A$3:E6),0) -> Robert Wise | F7: =VLOOKUP($A7,Table1[[#All],[Title]:[Oscar Wins]],COLUMNS($A$3:F6),0) -> The Mirisch Production Company | G7: =VLOOKUP($A7,Table1[[#All],[Title]:[Oscar Wins]],COLUMNS($A$3:G6),0) -> United States | H7: =VLOOKUP($A7,Table1[[#All],[Title]:[Oscar Wins]],COLUMNS($A$3:H6),0) -> English | I7: =VLOOKUP($A7,Table1[[#All],[Title]:[Oscar Wins]],COLUMNS($A$3:I6),0) -> PG | J7: =ROUND(VLOOKUP($A7,Table1[[#All],[Title]:[Oscar Wins]],COLUMNS($A$3:J6),0)/1000000,2)&" M" -> 6 M | K7: =ROUND(VLOOKUP($A7,Table1[[#All],[Title]:[Oscar Wins]],COLUMNS($A$3:K6),0)/1000000,2)&" M" -> 43.7 M | L7: =VLOOKUP($A7,Table1[[#All],[Title]:[Oscar Wins]],COLUMNS($A$3:L6),0) -> 11 | M7: =VLOOKUP($A7,Table1[[#All],[Title]:[Oscar Wins]],COLUMNS($A$3:M6),0) -> 10 | U7: 101 Dalmatians
A8: The English Patient | B8: =VLOOKUP($A8,Table1[[#All],[Title]:[Oscar Wins]],COLUMNS($A$3:B7),0) -> 35384 | C8: =VLOOKUP($A8,Table1[[#All],[Title]:[Oscar Wins]],COLUMNS($A$3:C7),0) -> 162 | D8: =VLOOKUP($A8,Table1[[#All],[Title]:[Oscar Wins]],COLUMNS($A$3:D7),0) -> Romance | E8: =VLOOKUP($A8,Table1[[#All],[Title]:[Oscar Wins]],COLUMNS($A$3:E7),0) -> Anthony Minghella | F8: =VLOOKUP($A8,Table1[[#All],[Title]:[Oscar Wins]],COLUMNS($A$3:F7),0) -> Miramax Films | G8: =VLOOKUP($A8,Table1[[#All],[Title]:[Oscar Wins]],COLUMNS($A$3:G7),0) -> United Kingdom | H8: =VLOOKUP($A8,Table1[[#All],[Title]:[Oscar Wins]],COLUMNS($A$3:H7),0) -> English | I8: =VLOOKUP($A8,Table1[[#All],[Title]:[Oscar Wins]],COLUMNS($A$3:I7),0) -> 15 | J8: =ROUND(VLOOKUP($A8,Table1[[#All],[Title]:[Oscar Wins]],COLUMNS($A$3:J7),0)/1000000,2)&" M" -> 27 M | K8: =ROUND(VLOOKUP($A8,Table1[[#All],[Title]:[Oscar Wins]],COLUMNS($A$3:K7),0)/1000000,2)&" M" -> 232 M | L8: =VLOOKUP($A8,Table1[[#All],[Title]:[Oscar Wins]],COLUMNS($A$3:L7),0) -> 12 | M8: =VLOOKUP($A8,Table1[[#All],[Title]:[Oscar Wins]],COLUMNS($A$3:M7),0) -> 9 | U8: 12 Years a Slave
A9: On the Waterfront | B9: =VLOOKUP($A9,Table1[[#All],[Title]:[Oscar Wins]],COLUMNS($A$3:B8),0) -> 19933 | C9: =VLOOKUP($A9,Table1[[#All],[Title]:[Oscar Wins]],COLUMNS($A$3:C8),0) -> 108 | D9: =VLOOKUP($A9,Table1[[#All],[Title]:[Oscar Wins]],COLUMNS($A$3:D8),0) -> Crime | E9: =VLOOKUP($A9,Table1[[#All],[Title]:[Oscar Wins]],COLUMNS($A$3:E8),0) -> Elia Kazan | F9: =VLOOKUP($A9,Table1[[#All],[Title]:[Oscar Wins]],COLUMNS($A$3:F8),0) -> Horizon Pictures | G9: =VLOOKUP($A9,Table1[[#All],[Title]:[Oscar Wins]],COLUMNS($A$3:G8),0) -> United States | H9: =VLOOKUP($A9,Table1[[#All],[Title]:[Oscar Wins]],COLUMNS($A$3:H8),0) -> English | I9: =VLOOKUP($A9,Table1[[#All],[Title]:[Oscar Wins]],COLUMNS($A$3:I8),0) -> PG | J9: =ROUND(VLOOKUP($A9,Table1[[#All],[Title]:[Oscar Wins]],COLUMNS($A$3:J8),0)/1000000,2)&" M" -> 0.91 M | K9: =ROUND(VLOOKUP($A9,Table1[[#All],[Title]:[Oscar Wins]],COLUMNS($A$3:K8),0)/1000000,2)&" M" -> 9.6 M | L9: =VLOOKUP($A9,Table1[[#All],[Title]:[Oscar Wins]],COLUMNS($A$3:L8),0) -> 12 | M9: =VLOOKUP($A9,Table1[[#All],[Title]:[Oscar Wins]],COLUMNS($A$3:M8),0) -> 8 | U9: 127 Hours
A10: Gone with the Wind | B10: =VLOOKUP($A10,Table1[[#All],[Title]:[Oscar Wins]],COLUMNS($A$3:B9),0) -> 14594 | C10: =VLOOKUP($A10,Table1[[#All],[Title]:[Oscar Wins]],COLUMNS($A$3:C9),0) -> 221 | D10: =VLOOKUP($A10,Table1[[#All],[Title]:[Oscar Wins]],COLUMNS($A$3:D9),0) -> Romance | E10: =VLOOKUP($A10,Table1[[#All],[Title]:[Oscar Wins]],COLUMNS($A$3:E9),0) -> Victor Fleming | F10: =VLOOKUP($A10,Table1[[#All],[Title]:[Oscar Wins]],COLUMNS($A$3:F9),0) -> Selznick International Pictures | G10: =VLOOKUP($A10,Table1[[#All],[Title]:[Oscar Wins]],COLUMNS($A$3:G9),0) -> United States | H10: =VLOOKUP($A10,Table1[[#All],[Title]:[Oscar Wins]],COLUMNS($A$3:H9),0) -> English | I10: =VLOOKUP($A10,Table1[[#All],[Title]:[Oscar Wins]],COLUMNS($A$3:I9),0) -> PG | J10: =ROUND(VLOOKUP($A10,Table1[[#All],[Title]:[Oscar Wins]],COLUMNS($A$3:J9),0)/1000000,2)&" M" -> 3.85 M | K10: =ROUND(VLOOKUP($A10,Table1[[#All],[Title]:[Oscar Wins]],COLUMNS($A$3:K9),0)/1000000,2)&" M" -> 198 M | L10: =VLOOKUP($A10,Table1[[#All],[Title]:[Oscar Wins]],COLUMNS($A$3:L9),0) -> 13 | M10: =VLOOKUP($A10,Table1[[#All],[Title]:[Oscar Wins]],COLUMNS($A$3:M9),0) -> 8 | U10: 13 Assassins
A11: Cabaret | B11: =VLOOKUP($A11,Table1[[#All],[Title]:[Oscar Wins]],COLUMNS($A$3:B10),0) -> 26342 | C11: =VLOOKUP($A11,Table1[[#All],[Title]:[Oscar Wins]],COLUMNS($A$3:C10),0) -> 124 | D11: =VLOOKUP($A11,Table1[[#All],[Title]:[Oscar Wins]],COLUMNS($A$3:D10),0) -> Musical | E11: =VLOOKUP($A11,Table1[[#All],[Title]:[Oscar Wins]],COLUMNS($A$3:E10),0) -> Bob Fosse | F11: =VLOOKUP($A11,Table1[[#All],[Title]:[Oscar Wins]],COLUMNS($A$3:F10),0) -> Allied Artists | G11: =VLOOKUP($A11,Table1[[#All],[Title]:[Oscar Wins]],COLUMNS($A$3:G10),0) -> United States | H11: =VLOOKUP($A11,Table1[[#All],[Title]:[Oscar Wins]],COLUMNS($A$3:H10),0) -> English | I11: =VLOOKUP($A11,Table1[[#All],[Title]:[Oscar Wins]],COLUMNS($A$3:I10),0) -> 15 | J11: =ROUND(VLOOKUP($A11,Table1[[#All],[Title]:[Oscar Wins]],COLUMNS($A$3:J10),0)/1000000,2)&" M" -> 2.29 M | K11: =ROUND(VLOOKUP($A11,Table1[[#All],[Title]:[Oscar Wins]],COLUMNS($A$3:K10),0)/1000000,2)&" M" -> 42.77 M | L11: =VLOOKUP($A11,Table1[[#All],[Title]:[Oscar Wins]],COLUMNS($A$3:L10),0) -> 10 | M11: =VLOOKUP($A11,Table1[[#All],[Title]:[Oscar Wins]],COLUMNS($A$3:M10),0) -> 8 | U11: 1492: Conquest of Paradise
A12: Slumdog Millionaire | B12: =VLOOKUP($A12,Table1[[#All],[Title]:[Oscar Wins]],COLUMNS($A$3:B11),0) -> 39690 | C12: =VLOOKUP($A12,Table1[[#All],[Title]:[Oscar Wins]],COLUMNS($A$3:C11),0) -> 120 | D12: =VLOOKUP($A12,Table1[[#All],[Title]:[Oscar Wins]],COLUMNS($A$3:D11),0) -> Drama | E12: =VLOOKUP($A12,Table1[[#All],[Title]:[Oscar Wins]],COLUMNS($A$3:E11),0) -> Danny Boyle | F12: =VLOOKUP($A12,Table1[[#All],[Title]:[Oscar Wins]],COLUMNS($A$3:F11),0) -> FilmFour Productions | G12: =VLOOKUP($A12,Table1[[#All],[Title]:[Oscar Wins]],COLUMNS($A$3:G11),0) -> United Kingdom | H12: =VLOOKUP($A12,Table1[[#All],[Title]:[Oscar Wins]],COLUMNS($A$3:H11),0) -> English | I12: =VLOOKUP($A12,Table1[[#All],[Title]:[Oscar Wins]],COLUMNS($A$3:I11),0) -> 15 | J12: =ROUND(VLOOKUP($A12,Table1[[#All],[Title]:[Oscar Wins]],COLUMNS($A$3:J11),0)/1000000,2)&" M" -> 15 M | K12: =ROUND(VLOOKUP($A12,Table1[[#All],[Title]:[Oscar Wins]],COLUMNS($A$3:K11),0)/1000000,2)&" M" -> 377.9 M | L12: =VLOOKUP($A12,Table1[[#All],[Title]:[Oscar Wins]],COLUMNS($A$3:L11),0) -> 10 | M12: =VLOOKUP($A12,Table1[[#All],[Title]:[Oscar Wins]],COLUMNS($A$3:M11),0) -> 8 | U12: 20,000 Leagues Under the Sea
A13: From Here to Eternity | B13: =VLOOKUP($A13,Table1[[#All],[Title]:[Oscar Wins]],COLUMNS($A$3:B12),0) -> 19576 | C13: =VLOOKUP($A13,Table1[[#All],[Title]:[Oscar Wins]],COLUMNS($A$3:C12),0) -> 118 | D13: =VLOOKUP($A13,Table1[[#All],[Title]:[Oscar Wins]],COLUMNS($A$3:D12),0) -> Drama | E13: =VLOOKUP($A13,Table1[[#All],[Title]:[Oscar Wins]],COLUMNS($A$3:E12),0) -> Fred Zinnemann | F13: =VLOOKUP($A13,Table1[[#All],[Title]:[Oscar Wins]],COLUMNS($A$3:F12),0) -> Columbia Pictures | G13: =VLOOKUP($A13,Table1[[#All],[Title]:[Oscar Wins]],COLUMNS($A$3:G12),0) -> United States | H13: =VLOOKUP($A13,Table1[[#All],[Title]:[Oscar Wins]],COLUMNS($A$3:H12),0) -> English | I13: =VLOOKUP($A13,Table1[[#All],[Title]:[Oscar Wins]],COLUMNS($A$3:I12),0) -> PG | J13: =ROUND(VLOOKUP($A13,Table1[[#All],[Title]:[Oscar Wins]],COLUMNS($A$3:J12),0)/1000000,2)&" M" -> 2.5 M | K13: =ROUND(VLOOKUP($A13,Table1[[#All],[Title]:[Oscar Wins]],COLUMNS($A$3:K12),0)/1000000,2)&" M" -> 30.5 M | L13: =VLOOKUP($A13,Table1[[#All],[Title]:[Oscar Wins]],COLUMNS($A$3:L12),0) -> 13 | M13: =VLOOKUP($A13,Table1[[#All],[Title]:[Oscar Wins]],COLUMNS($A$3:M12),0) -> 8 | U13: 2001: A Space Odyssey
A14: Gandhi | B14: =VLOOKUP($A14,Table1[[#All],[Title]:[Oscar Wins]],COLUMNS($A$3:B13),0) -> 30287 | C14: =VLOOKUP($A14,Table1[[#All],[Title]:[Oscar Wins]],COLUMNS($A$3:C13),0) -> 188 | D14: =VLOOKUP($A14,Table1[[#All],[Title]:[Oscar Wins]],COLUMNS($A$3:D13),0) -> Biography | E14: =VLOOKUP($A14,Table1[[#All],[Title]:[Oscar Wins]],COLUMNS($A$3:E13),0) -> Richard Attenborough | F14: =VLOOKUP($A14,Table1[[#All],[Title]:[Oscar Wins]],COLUMNS($A$3:F13),0) -> Goldcrest Films | G14: =VLOOKUP($A14,Table1[[#All],[Title]:[Oscar Wins]],COLUMNS($A$3:G13),0) -> United Kingdom | H14: =VLOOKUP($A14,Table1[[#All],[Title]:[Oscar Wins]],COLUMNS($A$3:H13),0) -> English | I14: =VLOOKUP($A14,Table1[[#All],[Title]:[Oscar Wins]],COLUMNS($A$3:I13),0) -> PG | J14: =ROUND(VLOOKUP($A14,Table1[[#All],[Title]:[Oscar Wins]],COLUMNS($A$3:J13),0)/1000000,2)&" M" -> 22 M | K14: =ROUND(VLOOKUP($A14,Table1[[#All],[Title]:[Oscar Wins]],COLUMNS($A$3:K13),0)/1000000,2)&" M" -> 52.77 M | L14: =VLOOKUP($A14,Table1[[#All],[Title]:[Oscar Wins]],COLUMNS($A$3:L13),0) -> 11 | M14: =VLOOKUP($A14,Table1[[#All],[Title]:[Oscar Wins]],COLUMNS($A$3:M13),0) -> 8 | U14: 21 Grams
A15: My Fair Lady | B15: =VLOOKUP($A15,Table1[[#All],[Title]:[Oscar Wins]],COLUMNS($A$3:B14),0) -> 23690 | C15: =VLOOKUP($A15,Table1[[#All],[Title]:[Oscar Wins]],COLUMNS($A$3:C14),0) -> 170 | D15: =VLOOKUP($A15,Table1[[#All],[Title]:[Oscar Wins]],COLUMNS($A$3:D14),0) -> Musical | E15: =VLOOKUP($A15,Table1[[#All],[Title]:[Oscar Wins]],COLUMNS($A$3:E14),0) -> George Cukor | F15: =VLOOKUP($A15,Table1[[#All],[Title]:[Oscar Wins]],COLUMNS($A$3:F14),0) -> Warner Bros. Pictures | G15: =VLOOKUP($A15,Table1[[#All],[Title]:[Oscar Wins]],COLUMNS($A$3:G14),0) -> United States | H15: =VLOOKUP($A15,Table1[[#All],[Title]:[Oscar Wins]],COLUMNS($A$3:H14),0) -> English | I15: =VLOOKUP($A15,Table1[[#All],[Title]:[Oscar Wins]],COLUMNS($A$3:I14),0) -> U | J15: =ROUND(VLOOKUP($A15,Table1[[#All],[Title]:[Oscar Wins]],COLUMNS($A$3:J14),0)/1000000,2)&" M" -> 17 M | K15: =ROUND(VLOOKUP($A15,Table1[[#All],[Title]:[Oscar Wins]],COLUMNS($A$3:K14),0)/1000000,2)&" M" -> 72 M | L15: =VLOOKUP($A15,Table1[[#All],[Title]:[Oscar Wins]],COLUMNS($A$3:L14),0) -> 12 | M15: =VLOOKUP($A15,Table1[[#All],[Title]:[Oscar Wins]],COLUMNS($A$3:M14),0) -> 8 | U15: 21 Jump Street
A16: Shakespeare in Love | B16: =VLOOKUP($A16,Table1[[#All],[Title]:[Oscar Wins]],COLUMNS($A$3:B15),0) -> 36132 | C16: =VLOOKUP($A16,Table1[[#All],[Title]:[Oscar Wins]],COLUMNS($A$3:C15),0) -> 123 | D16: =VLOOKUP($A16,Table1[[#All],[Title]:[Oscar Wins]],COLUMNS($A$3:D15),0) -> Romantic Comedy | E16: =VLOOKUP($A16,Table1[[#All],[Title]:[Oscar Wins]],COLUMNS($A$3:E15),0) -> John Madden | F16: =VLOOKUP($A16,Table1[[#All],[Title]:[Oscar Wins]],COLUMNS($A$3:F15),0) -> The Bedford Falls Company | G16: =VLOOKUP($A16,Table1[[#All],[Title]:[Oscar Wins]],COLUMNS($A$3:G15),0) -> United Kingdom | H16: =VLOOKUP($A16,Table1[[#All],[Title]:[Oscar Wins]],COLUMNS($A$3:H15),0) -> English | I16: =VLOOKUP($A16,Table1[[#All],[Title]:[Oscar Wins]],COLUMNS($A$3:I15),0) -> 15 | J16: =ROUND(VLOOKUP($A16,Table1[[#All],[Title]:[Oscar Wins]],COLUMNS($A$3:J15),0)/1000000,2)&" M" -> 25 M | K16: =ROUND(VLOOKUP($A16,Table1[[#All],[Title]:[Oscar Wins]],COLUMNS($A$3:K15),0)/1000000,2)&" M" -> 289.3 M | L16: =VLOOKUP($A16,Table1[[#All],[Title]:[Oscar Wins]],COLUMNS($A$3:L15),0) -> 13 | M16: =VLOOKUP($A16,Table1[[#All],[Title]:[Oscar Wins]],COLUMNS($A$3:M15),0) -> 7 | U16: 22 Jump Street
A17: Patton | B17: =VLOOKUP($A17,Table1[[#All],[Title]:[Oscar Wins]],COLUMNS($A$3:B16),0) -> 25660 | C17: =VLOOKUP($A17,Table1[[#All],[Title]:[Oscar Wins]],COLUMNS($A$3:C16),0) -> 170 | D17: =VLOOKUP($A17,Table1[[#All],[Title]:[Oscar Wins]],COLUMNS($A$3:D16),0) -> Biography | E17: =VLOOKUP($A17,Table1[[#All],[Title]:[Oscar Wins]],COLUMNS($A$3:E16),0) -> Franklin J. Schaffner | F17: =VLOOKUP($A17,Table1[[#All],[Title]:[Oscar Wins]],COLUMNS($A$3:F16),0) -> 20th Century Fox | G17: =VLOOKUP($A17,Table1[[#All],[Title]:[Oscar Wins]],COLUMNS($A$3:G16),0) -> United States | H17: =VLOOKUP($A17,Table1[[#All],[Title]:[Oscar Wins]],COLUMNS($A$3:H16),0) -> English | I17: =VLOOKUP($A17,Table1[[#All],[Title]:[Oscar Wins]],COLUMNS($A$3:I16),0) -> PG | J17: =ROUND(VLOOKUP($A17,Table1[[#All],[Title]:[Oscar Wins]],COLUMNS($A$3:J16),0)/1000000,2)&" M" -> 12.6 M | K17: =ROUND(VLOOKUP($A17,Table1[[#All],[Title]:[Oscar Wins]],COLUMNS($A$3:K16),0)/1000000,2)&" M" -> 61.8 M | L17: =VLOOKUP($A17,Table1[[#All],[Title]:[Oscar Wins]],COLUMNS($A$3:L16),0) -> 10 | M17: =VLOOKUP($A17,Table1[[#All],[Title]:[Oscar Wins]],COLUMNS($A$3:M16),0) -> 7 | U17: 28 Days Later
A18: The Bridge on the River Kwai | B18: =VLOOKUP($A18,Table1[[#All],[Title]:[Oscar Wins]],COLUMNS($A$3:B17),0) -> 21095 | C18: =VLOOKUP($A18,Table1[[#All],[Title]:[Oscar Wins]],COLUMNS($A$3:C17),0) -> 161 | D18: =VLOOKUP($A18,Table1[[#All],[Title]:[Oscar Wins]],COLUMNS($A$3:D17),0) -> War | E18: =VLOOKUP($A18,Table1[[#All],[Title]:[Oscar Wins]],COLUMNS($A$3:E17),0) -> David Lean | F18: =VLOOKUP($A18,Table1[[#All],[Title]:[Oscar Wins]],COLUMNS($A$3:F17),0) -> Horizon Pictures | G18: =VLOOKUP($A18,Table1[[#All],[Title]:[Oscar Wins]],COLUMNS($A$3:G17),0) -> United Kingdom | H18: =VLOOKUP($A18,Table1[[#All],[Title]:[Oscar Wins]],COLUMNS($A$3:H17),0) -> English | I18: =VLOOKUP($A18,Table1[[#All],[Title]:[Oscar Wins]],COLUMNS($A$3:I17),0) -> U | J18: =ROUND(VLOOKUP($A18,Table1[[#All],[Title]:[Oscar Wins]],COLUMNS($A$3:J17),0)/1000000,2)&" M" -> 2.8 M | K18: =ROUND(VLOOKUP($A18,Table1[[#All],[Title]:[Oscar Wins]],COLUMNS($A$3:K17),0)/1000000,2)&" M" -> 30.6 M | L18: =VLOOKUP($A18,Table1[[#All],[Title]:[Oscar Wins]],COLUMNS($A$3:L17),0) -> 8 | M18: =VLOOKUP($A18,Table1[[#All],[Title]:[Oscar Wins]],COLUMNS($A$3:M17),0) -> 7 | U18: 28 Weeks Later
... A30: Terminator 2: Judgement Day | B30: =VLOOKUP($A30,Table1[[#All],[Title]:[Oscar Wins]],COLUMNS($A$3:B29),0) -> 33466 | C30: =VLOOKUP($A30,Table1[[#All],[Title]:[Oscar Wins]],COLUMNS($A$3:C29),0) -> 136 | D30: =VLOOKUP($A30,Table1[[#All],[Title]:[Oscar Wins]],COLUMNS($A$3:D29),0) -> Science Fiction | E30: =VLOOKUP($A30,Table1[[#All],[Title]:[Oscar Wins]],COLUMNS($A$3:E29),0) -> James Cameron | F30: =VLOOKUP($A30,Table1[[#All],[Title]:[Oscar Wins]],COLUMNS($A$3:F29),0) -> Carolco Pictures | G30: =VLOOKUP($A30,Table1[[#All],[Title]:[Oscar Wins]],COLUMNS($A$3:G29),0) -> United States | H30: =VLOOKUP($A30,Table1[[#All],[Title]:[Oscar Wins]],COLUMNS($A$3:H29),0) -> English | I30: =VLOOKUP($A30,Table1[[#All],[Title]:[Oscar Wins]],COLUMNS($A$3:I29),0) -> 15 | J30: =ROUND(VLOOKUP($A30,Table1[[#All],[Title]:[Oscar Wins]],COLUMNS($A$3:J29),0)/1000000,2)&" M" -> 100 M | K30: =ROUND(VLOOKUP($A30,Table1[[#All],[Title]:[Oscar Wins]],COLUMNS($A$3:K29),0)/1000000,2)&" M" -> 516.82 M | L30: =VLOOKUP($A30,Table1[[#All],[Title]:[Oscar Wins]],COLUMNS($A$3:L29),0) -> 4 | M30: =VLOOKUP($A30,Table1[[#All],[Title]:[Oscar Wins]],COLUMNS($A$3:M29),0) -> 6 | U30: A Field in England
U31: A Fistful of Dollars
U32: A Hard Day's Night
U33: A History of Violence
U34: A Knight's Tale
U35: A Life Less Ordinary
U36: A Million Ways to Die in the West
U37: A Place in the Sun
U38: A Prophet
U39: A Streetcar Named Desire
U40: A.I. Artificial Intelligence
U41: Abraham Lincoln: Vampire Hunter
U42: Air Force One
... U1053: Zulu

Sheet Hlookup
A1: Movie Name | B1: Release Date | C1: Run Time | D1: Genre | E1: Director | F1: Studio | G1: Country | H1: Language | I1: Certificate | J1: Budget | K1: Box Office | L1: Nominations | M1: Oscar Wins
A2: Titanic | B2: =HLOOKUP($A2,'Raw Data for Hlookup'!$2:$14,COLUMNS($A$1:B1),0) -> 35818 | C2: =HLOOKUP($A2,'Raw Data for Hlookup'!$2:$14,COLUMNS($A$1:C1),0) -> 194 | D2: =HLOOKUP($A2,'Raw Data for Hlookup'!$2:$14,COLUMNS($A$1:D1),0) -> Romance | E2: =HLOOKUP($A2,'Raw Data for Hlookup'!$2:$14,COLUMNS($A$1:E1),0) -> James Cameron | F2: =HLOOKUP($A2,'Raw Data for Hlookup'!$2:$14,COLUMNS($A$1:F1),0) -> 20th Century Fox | G2: =HLOOKUP($A2,'Raw Data for Hlookup'!$2:$14,COLUMNS($A$1:G1),0) -> United States | H2: =HLOOKUP($A2,'Raw Data for Hlookup'!$2:$14,COLUMNS($A$1:H1),0) -> English | I2: =HLOOKUP($A2,'Raw Data for Hlookup'!$2:$14,COLUMNS($A$1:I1),0) -> 12 | ... M2: =HLOOKUP($A2,'Raw Data for Hlookup'!$2:$14,COLUMNS($A$1:M1),0) -> 11
A3: The Lord of the Rings: Return of the King | B3: =HLOOKUP($A3,'Raw Data for Hlookup'!$2:$14,COLUMNS($A$1:B2),0) -> 37972 | C3: =HLOOKUP($A3,'Raw Data for Hlookup'!$2:$14,COLUMNS($A$1:C2),0) -> 201 | D3: =HLOOKUP($A3,'Raw Data for Hlookup'!$2:$14,COLUMNS($A$1:D2),0) -> Fantasy | E3: =HLOOKUP($A3,'Raw Data for Hlookup'!$2:$14,COLUMNS($A$1:E2),0) -> Peter Jackson | F3: =HLOOKUP($A3,'Raw Data for Hlookup'!$2:$14,COLUMNS($A$1:F2),0) -> WingNut Films | G3: =HLOOKUP($A3,'Raw Data for Hlookup'!$2:$14,COLUMNS($A$1:G2),0) -> New Zealand | H3: =HLOOKUP($A3,'Raw Data for Hlookup'!$2:$14,COLUMNS($A$1:H2),0) -> English | I3: =HLOOKUP($A3,'Raw Data for Hlookup'!$2:$14,COLUMNS($A$1:I2),0) -> 12A | ... M3: =HLOOKUP($A3,'Raw Data for Hlookup'!$2:$14,COLUMNS($A$1:M2),0) -> 11
A4: Ben-Hur | B4: =HLOOKUP($A4,'Raw Data for Hlookup'!$2:$14,COLUMNS($A$1:B3),0) -> 21872 | C4: =HLOOKUP($A4,'Raw Data for Hlookup'!$2:$14,COLUMNS($A$1:C3),0) -> 212 | D4: =HLOOKUP($A4,'Raw Data for Hlookup'!$2:$14,COLUMNS($A$1:D3),0) -> Drama | E4: =HLOOKUP($A4,'Raw Data for Hlookup'!$2:$14,COLUMNS($A$1:E3),0) -> William Wyler | F4: =HLOOKUP($A4,'Raw Data for Hlookup'!$2:$14,COLUMNS($A$1:F3),0) -> Metro-Goldwyn-Mayer | G4: =HLOOKUP($A4,'Raw Data for Hlookup'!$2:$14,COLUMNS($A$1:G3),0) -> United States | H4: =HLOOKUP($A4,'Raw Data for Hlookup'!$2:$14,COLUMNS($A$1:H3),0) -> English | I4: =HLOOKUP($A4,'Raw Data for Hlookup'!$2:$14,COLUMNS($A$1:I3),0) -> PG | ... M4: =HLOOKUP($A4,'Raw Data for Hlookup'!$2:$14,COLUMNS($A$1:M3),0) -> 11
A5: West Side Story | B5: =HLOOKUP($A5,'Raw Data for Hlookup'!$2:$14,COLUMNS($A$1:B4),0) -> 22572 | C5: =HLOOKUP($A5,'Raw Data for Hlookup'!$2:$14,COLUMNS($A$1:C4),0) -> 152 | D5: =HLOOKUP($A5,'Raw Data for Hlookup'!$2:$14,COLUMNS($A$1:D4),0) -> Musical | E5: =HLOOKUP($A5,'Raw Data for Hlookup'!$2:$14,COLUMNS($A$1:E4),0) -> Robert Wise | F5: =HLOOKUP($A5,'Raw Data for Hlookup'!$2:$14,COLUMNS($A$1:F4),0) -> The Mirisch Production Company | G5: =HLOOKUP($A5,'Raw Data for Hlookup'!$2:$14,COLUMNS($A$1:G4),0) -> United States | H5: =HLOOKUP($A5,'Raw Data for Hlookup'!$2:$14,COLUMNS($A$1:H4),0) -> English | I5: =HLOOKUP($A5,'Raw Data for Hlookup'!$2:$14,COLUMNS($A$1:I4),0) -> PG | ... M5: =HLOOKUP($A5,'Raw Data for Hlookup'!$2:$14,COLUMNS($A$1:M4),0) -> 10
A6: The English Patient | B6: =HLOOKUP($A6,'Raw Data for Hlookup'!$2:$14,COLUMNS($A$1:B5),0) -> 35384 | C6: =HLOOKUP($A6,'Raw Data for Hlookup'!$2:$14,COLUMNS($A$1:C5),0) -> 162 | D6: =HLOOKUP($A6,'Raw Data for Hlookup'!$2:$14,COLUMNS($A$1:D5),0) -> Romance | E6: =HLOOKUP($A6,'Raw Data for Hlookup'!$2:$14,COLUMNS($A$1:E5),0) -> Anthony Minghella | F6: =HLOOKUP($A6,'Raw Data for Hlookup'!$2:$14,COLUMNS($A$1:F5),0) -> Miramax Films | G6: =HLOOKUP($A6,'Raw Data for Hlookup'!$2:$14,COLUMNS($A$1:G5),0) -> United Kingdom | H6: =HLOOKUP($A6,'Raw Data for Hlookup'!$2:$14,COLUMNS($A$1:H5),0) -> English | I6: =HLOOKUP($A6,'Raw Data for Hlookup'!$2:$14,COLUMNS($A$1:I5),0) -> 15 | ... M6: =HLOOKUP($A6,'Raw Data for Hlookup'!$2:$14,COLUMNS($A$1:M5),0) -> 9
A7: On the Waterfront | B7: =HLOOKUP($A7,'Raw Data for Hlookup'!$2:$14,COLUMNS($A$1:B6),0) -> 19933 | C7: =HLOOKUP($A7,'Raw Data for Hlookup'!$2:$14,COLUMNS($A$1:C6),0) -> 108 | D7: =HLOOKUP($A7,'Raw Data for Hlookup'!$2:$14,COLUMNS($A$1:D6),0) -> Crime | E7: =HLOOKUP($A7,'Raw Data for Hlookup'!$2:$14,COLUMNS($A$1:E6),0) -> Elia Kazan | F7: =HLOOKUP($A7,'Raw Data for Hlookup'!$2:$14,COLUMNS($A$1:F6),0) -> Horizon Pictures | G7: =HLOOKUP($A7,'Raw Data for Hlookup'!$2:$14,COLUMNS($A$1:G6),0) -> United States | H7: =HLOOKUP($A7,'Raw Data for Hlookup'!$2:$14,COLUMNS($A$1:H6),0) -> English | I7: =HLOOKUP($A7,'Raw Data for Hlookup'!$2:$14,COLUMNS($A$1:I6),0) -> PG | ... M7: =HLOOKUP($A7,'Raw Data for Hlookup'!$2:$14,COLUMNS($A$1:M6),0) -> 8
A8: Gone with the Wind | B8: =HLOOKUP($A8,'Raw Data for Hlookup'!$2:$14,COLUMNS($A$1:B7),0) -> 14594 | C8: =HLOOKUP($A8,'Raw Data for Hlookup'!$2:$14,COLUMNS($A$1:C7),0) -> 221 | D8: =HLOOKUP($A8,'Raw Data for Hlookup'!$2:$14,COLUMNS($A$1:D7),0) -> Romance | E8: =HLOOKUP($A8,'Raw Data for Hlookup'!$2:$14,COLUMNS($A$1:E7),0) -> Victor Fleming | F8: =HLOOKUP($A8,'Raw Data for Hlookup'!$2:$14,COLUMNS($A$1:F7),0) -> Selznick International Pictures | G8: =HLOOKUP($A8,'Raw Data for Hlookup'!$2:$14,COLUMNS($A$1:G7),0) -> United States | H8: =HLOOKUP($A8,'Raw Data for Hlookup'!$2:$14,COLUMNS($A$1:H7),0) -> English | I8: =HLOOKUP($A8,'Raw Data for Hlookup'!$2:$14,COLUMNS($A$1:I7),0) -> PG | ... M8: =HLOOKUP($A8,'Raw Data for Hlookup'!$2:$14,COLUMNS($A$1:M7),0) -> 8
A9: Cabaret | B9: =HLOOKUP($A9,'Raw Data for Hlookup'!$2:$14,COLUMNS($A$1:B8),0) -> 26342 | C9: =HLOOKUP($A9,'Raw Data for Hlookup'!$2:$14,COLUMNS($A$1:C8),0) -> 124 | D9: =HLOOKUP($A9,'Raw Data for Hlookup'!$2:$14,COLUMNS($A$1:D8),0) -> Musical | E9: =HLOOKUP($A9,'Raw Data for Hlookup'!$2:$14,COLUMNS($A$1:E8),0) -> Bob Fosse | F9: =HLOOKUP($A9,'Raw Data for Hlookup'!$2:$14,COLUMNS($A$1:F8),0) -> Allied Artists | G9: =HLOOKUP($A9,'Raw Data for Hlookup'!$2:$14,COLUMNS($A$1:G8),0) -> United States | H9: =HLOOKUP($A9,'Raw Data for Hlookup'!$2:$14,COLUMNS($A$1:H8),0) -> English | I9: =HLOOKUP($A9,'Raw Data for Hlookup'!$2:$14,COLUMNS($A$1:I8),0) -> 15 | ... M9: =HLOOKUP($A9,'Raw Data for Hlookup'!$2:$14,COLUMNS($A$1:M8),0) -> 8
A10: Slumdog Millionaire | B10: =HLOOKUP($A10,'Raw Data for Hlookup'!$2:$14,COLUMNS($A$1:B9),0) -> 39690 | C10: =HLOOKUP($A10,'Raw Data for Hlookup'!$2:$14,COLUMNS($A$1:C9),0) -> 120 | D10: =HLOOKUP($A10,'Raw Data for Hlookup'!$2:$14,COLUMNS($A$1:D9),0) -> Drama | E10: =HLOOKUP($A10,'Raw Data for Hlookup'!$2:$14,COLUMNS($A$1:E9),0) -> Danny Boyle | F10: =HLOOKUP($A10,'Raw Data for Hlookup'!$2:$14,COLUMNS($A$1:F9),0) -> FilmFour Productions | G10: =HLOOKUP($A10,'Raw Data for Hlookup'!$2:$14,COLUMNS($A$1:G9),0) -> United Kingdom | H10: =HLOOKUP($A10,'Raw Data for Hlookup'!$2:$14,COLUMNS($A$1:H9),0) -> English | I10: =HLOOKUP($A10,'Raw Data for Hlookup'!$2:$14,COLUMNS($A$1:I9),0) -> 15 | ... M10: =HLOOKUP($A10,'Raw Data for Hlookup'!$2:$14,COLUMNS($A$1:M9),0) -> 8
A11: From Here to Eternity | B11: =HLOOKUP($A11,'Raw Data for Hlookup'!$2:$14,COLUMNS($A$1:B10),0) -> 19576 | C11: =HLOOKUP($A11,'Raw Data for Hlookup'!$2:$14,COLUMNS($A$1:C10),0) -> 118 | D11: =HLOOKUP($A11,'Raw Data for Hlookup'!$2:$14,COLUMNS($A$1:D10),0) -> Drama | E11: =HLOOKUP($A11,'Raw Data for Hlookup'!$2:$14,COLUMNS($A$1:E10),0) -> Fred Zinnemann | F11: =HLOOKUP($A11,'Raw Data for Hlookup'!$2:$14,COLUMNS($A$1:F10),0) -> Columbia Pictures | G11: =HLOOKUP($A11,'Raw Data for Hlookup'!$2:$14,COLUMNS($A$1:G10),0) -> United States | H11: =HLOOKUP($A11,'Raw Data for Hlookup'!$2:$14,COLUMNS($A$1:H10),0) -> English | I11: =HLOOKUP($A11,'Raw Data for Hlookup'!$2:$14,COLUMNS($A$1:I10),0) -> PG | ... M11: =HLOOKUP($A11,'Raw Data for Hlookup'!$2:$14,COLUMNS($A$1:M10),0) -> 8
A12: Gandhi | B12: =HLOOKUP($A12,'Raw Data for Hlookup'!$2:$14,COLUMNS($A$1:B11),0) -> 30287 | C12: =HLOOKUP($A12,'Raw Data for Hlookup'!$2:$14,COLUMNS($A$1:C11),0) -> 188 | D12: =HLOOKUP($A12,'Raw Data for Hlookup'!$2:$14,COLUMNS($A$1:D11),0) -> Biography | E12: =HLOOKUP($A12,'Raw Data for Hlookup'!$2:$14,COLUMNS($A$1:E11),0) -> Richard Attenborough | F12: =HLOOKUP($A12,'Raw Data for Hlookup'!$2:$14,COLUMNS($A$1:F11),0) -> Goldcrest Films | G12: =HLOOKUP($A12,'Raw Data for Hlookup'!$2:$14,COLUMNS($A$1:G11),0) -> United Kingdom | H12: =HLOOKUP($A12,'Raw Data for Hlookup'!$2:$14,COLUMNS($A$1:H11),0) -> English | I12: =HLOOKUP($A12,'Raw Data for Hlookup'!$2:$14,COLUMNS($A$1:I11),0) -> PG | ... M12: =HLOOKUP($A12,'Raw Data for Hlookup'!$2:$14,COLUMNS($A$1:M11),0) -> 8
A13: My Fair Lady | B13: =HLOOKUP($A13,'Raw Data for Hlookup'!$2:$14,COLUMNS($A$1:B12),0) -> 23690 | C13: =HLOOKUP($A13,'Raw Data for Hlookup'!$2:$14,COLUMNS($A$1:C12),0) -> 170 | D13: =HLOOKUP($A13,'Raw Data for Hlookup'!$2:$14,COLUMNS($A$1:D12),0) -> Musical | E13: =HLOOKUP($A13,'Raw Data for Hlookup'!$2:$14,COLUMNS($A$1:E12),0) -> George Cukor | F13: =HLOOKUP($A13,'Raw Data for Hlookup'!$2:$14,COLUMNS($A$1:F12),0) -> Warner Bros. Pictures | G13: =HLOOKUP($A13,'Raw Data for Hlookup'!$2:$14,COLUMNS($A$1:G12),0) -> United States | H13: =HLOOKUP($A13,'Raw Data for Hlookup'!$2:$14,COLUMNS($A$1:H12),0) -> English | I13: =HLOOKUP($A13,'Raw Data for Hlookup'!$2:$14,COLUMNS($A$1:I12),0) -> U | ... M13: =HLOOKUP($A13,'Raw Data for Hlookup'!$2:$14,COLUMNS($A$1:M12),0) -> 8
... A28: Terminator 2: Judgement Day | B28: =HLOOKUP($A28,'Raw Data for Hlookup'!$2:$14,COLUMNS($A$1:B27),0) -> 33466 | C28: =HLOOKUP($A28,'Raw Data for Hlookup'!$2:$14,COLUMNS($A$1:C27),0) -> 136 | D28: =HLOOKUP($A28,'Raw Data for Hlookup'!$2:$14,COLUMNS($A$1:D27),0) -> Science Fiction | E28: =HLOOKUP($A28,'Raw Data for Hlookup'!$2:$14,COLUMNS($A$1:E27),0) -> James Cameron | F28: =HLOOKUP($A28,'Raw Data for Hlookup'!$2:$14,COLUMNS($A$1:F27),0) -> Carolco Pictures | G28: =HLOOKUP($A28,'Raw Data for Hlookup'!$2:$14,COLUMNS($A$1:G27),0) -> United States | H28: =HLOOKUP($A28,'Raw Data for Hlookup'!$2:$14,COLUMNS($A$1:H27),0) -> English | I28: =HLOOKUP($A28,'Raw Data for Hlookup'!$2:$14,COLUMNS($A$1:I27),0) -> 15 | ... M28: =HLOOKUP($A28,'Raw Data for Hlookup'!$2:$14,COLUMNS($A$1:M27),0) -> 6

Sheet Raw Data for Hlookup
A1: ID | B1: 345 | C1: 441 | D1: 454 | E1: 1490 | F1: 1491 | G1: 1492 | H1: 1493 | I1: 1141 | J1: 357 | K1: 488 | L1: 205 | M1: 213 | N1: 226 | O1: 1138 | P1: 1229 | Q1: 1230 | R1: 1237 | S1: 1238 | T1: 1474 | U1: 72 | V1: 207 | W1: 231 | X1: 1205 | Y1: 1207 | Z1: 1220 | AA1: 1221 | AB1: 1301 | AC1: 1302 | AD1: 1303 | AE1: 1304 | AF1: 1309 | AG1: 1331 | AH1: 1365 | AI1: 223 | AJ1: 227 | AK1: 255 | AL1: 1462 | AM1: 1675 | AN1: 238 | AO1: 1167 | AP1: 1168 | AQ1: 1169 | AR1: 1170 | AS1: 1171 | AT1: 1195 | AU1: 1197 | AV1: 1209 | AW1: 1210 | AX1: 1228 | AY1: 1232 | AZ1: 1247 | BA1: 1248 | BB1: 1249 | BC1: 1250 | BD1: 1310 | BE1: 1239 | BF1: 1241 | BG1: 633 | BH1: 650 | BI1: 1377 | BJ1: 1378 | BK1: 260 | BL1: 262 | BM1: 263 | BN1: 598 | BO1: 1253 | BP1: 1269 | BQ1: 1270 | BR1: 1281 | BS1: 1287 | BT1: 1289 | BU1: 1298 | BV1: 1299 | BW1: 1359 | BX1: 3 | BY1: 59 | BZ1: 73 | CA1: 74 | CB1: 265 | CC1: 271 | CD1: 283 | CE1: 293 | CF1: 1399 | CG1: 253 | CH1: 1395 | CI1: 1322 | CJ1: 1323 | CK1: 1575 | CL1: 1579 | CM1: 1582 | CN1: 1242 | CO1: 1243 | CP1: 1245 | CQ1: 1246 | CR1: 11 | CS1: 18 | CT1: 22 | CU1: 31 | CV1: 35 | CW1: 38 | CX1: 51 | CY1: 61 | CZ1: 65 | DA1: 120 | DB1: 156 | DC1: 157 | DD1: 167 | DE1: 178 | DF1: 194 | DG1: 202 | DH1: 206 | DI1: 216 | DJ1: 219 | DK1: 220 | DL1: 221 | DM1: 222 | DN1: 228 | DO1: 233 | DP1: 236 | DQ1: 239 | DR1: 241 | DS1: 242 | DT1: 251 | DU1: 252 | DV1: 256 | DW1: 258 | DX1: 264 | DY1: 266 | DZ1: 291 | EA1: 300 | EB1: 311 | EC1: 312 | ED1: 321 | EE1: 327 | EF1: 334 | EG1: 336 | EH1: 339 | EI1: 346 | EJ1: 369 | EK1: 376 | EL1: 382 | EM1: 494 | EN1: 498 | EO1: 500 | EP1: 524 | EQ1: 531 | ER1: 544 | ES1: 548 | ET1: 588 | EU1: 589 | EV1: 609 | EW1: 614 | EX1: 615 | EY1: 639 | EZ1: 653 | FA1: 664 | FB1: 675 | FC1: 714 | FD1: 766 | FE1: 769 | FF1: 899 | FG1: 1125 | FH1: 1150 | FI1: 1151 | FJ1: 1154 | FK1: 1159 | FL1: 1161 | FM1: 1162 | FN1: 1164 | FO1: 1172 | FP1: 1173 | FQ1: 1219 | FR1: 1311 | FS1: 1314 | FT1: 1315 | FU1: 1316 | FV1: 1317 | FW1: 1319 | FX1: 1320 | FY1: 1326 | FZ1: 1327 | GA1: 1328 | GB1: 1330 | GC1: 1333 | GD1: 1334 | GE1: 1335 | GF1: 1336 | GG1: 1337 | GH1: 1371 | GI1: 1372 | GJ1: 1373 | GK1: 1374 | GL1: 1375 | GM1: 1376 | GN1: 1404 | GO1: 1415 | GP1: 1416 | GQ1: 1417 | GR1: 1418 | GS1: 1427 | GT1: 1429 | GU1: 1433 | GV1: 1456 | GW1: 1461 | GX1: 1472 | GY1: 1485 | GZ1: 1488 | HA1: 1505 | HB1: 1535 | HC1: 1542 | HD1: 1543 | HE1: 1546 | HF1: 1547 | HG1: 1557 | HH1: 1558 | HI1: 1560 | HJ1: 1561 | HK1: 1572 | HL1: 1599 | HM1: 1605 | HN1: 1606 | HO1: 1609 | HP1: 1610 | HQ1: 1612 | HR1: 1613 | HS1: 1620 | HT1: 1625 | HU1: 1644 | HV1: 1645 | HW1: 1646 | HX1: 1647 | HY1: 1650 | HZ1: 1653 | IA1: 1 | IB1: 2 | IC1: 5 | ID1: 6 | IE1: 7 | IF1: 8 | IG1: 9 | IH1: 10 | II1: 12 | IJ1: 13 | IK1: 14 | IL1: 15 | IM1: 16 | IN1: 17 | IO1: 19 | IP1: 20 | IQ1: 21 | IR1: 23 | IS1: 24 | IT1: 25 | IU1: 26 | IV1: 27 | IW1: 28 | IX1: 29 | IY1: 30 | IZ1: 32 | JA1: 33 | JB1: 34 | JC1: 36 | JD1: 37 | JE1: 39 | JF1: 40 | JG1: 41 | JH1: 42 | JI1: 43 | JJ1: 44 | JK1: 45 | JL1: 46 | JM1: 47 | JN1: 48 | JO1: 49 | JP1: 50 | JQ1: 52 | JR1: 53 | JS1: 54 | JT1: 55 | JU1: 56 | JV1: 57 | JW1: 58 | JX1: 60 | JY1: 62 | JZ1: 63 | KA1: 64 | KB1: 66 | KC1: 67 | KD1: 68 | KE1: 69 | KF1: 70 | KG1: 71 | KH1: 75 | KI1: 76 | KJ1: 77 | KK1: 78 | KL1: 79 | KM1: 80 | KN1: 81 | KO1: 82 | KP1: 83 | KQ1: 84 | KR1: 85 | KS1: 86 | KT1: 87 | KU1: 88 | KV1: 89 | KW1: 90 | KX1: 91 | KY1: 92 | KZ1: 93 | LA1: 94 | LB1: 95 | LC1: 96 | LD1: 97 | LE1: 98 | LF1: 99 | LG1: 100 | LH1: 101 | LI1: 102 | LJ1: 103 | LK1: 104 | LL1: 105 | LM1: 106 | LN1: 107 | LO1: 108 | LP1: 109 | LQ1: 110 | LR1: 111 | LS1: 112 | LT1: 113 | LU1: 114 | LV1: 115 | LW1: 116 | LX1: 117 | LY1: 118 | LZ1: 119 | MA1: 121 | MB1: 122 | MC1: 123 | MD1: 124 | ME1: 125 | MF1: 126 | MG1: 127 | MH1: 128 | MI1: 129 | MJ1: 130 | MK1: 131 | ML1: 132 | MM1: 133 | MN1: 134 | MO1: 135 | MP1: 136 | MQ1: 137 | MR1: 138 | MS1: 139 | MT1: 140 | MU1: 141 | MV1: 142 | MW1: 143 | MX1: 144 | MY1: 145 | MZ1: 146 | NA1: 147 | NB1: 148 | NC1: 149 | ND1: 150 | NE1: 151 | NF1: 152 | NG1: 153 | NH1: 154 | NI1: 155 | NJ1: 158 | NK1: 159 | NL1: 160 | NM1: 161 | NN1: 162 | NO1: 163 | NP1: 164 | NQ1: 165 | NR1: 166 | NS1: 168 | NT1: 169 | NU1: 170 | NV1: 171 | NW1: 172 | NX1: 173 | NY1: 174 | NZ1: 175 | OA1: 176 | OB1: 177 | OC1: 179 | OD1: 180 | OE1: 181 | OF1: 182 | OG1: 183 | OH1: 184 | OI1: 185 | OJ1: 186 | OK1: 187 | OL1: 188 | OM1: 189 | ON1: 190 | OO1: 191 | OP1: 192 | OQ1: 193 | OR1: 195 | OS1: 196 | OT1: 197 | OU1: 199 | OV1: 200 | OW1: 201 | OX1: 203 | OY1: 204 | OZ1: 208 | PA1: 209 | PB1: 210 | PC1: 211 | PD1: 212 | PE1: 214 | PF1: 215 | PG1: 217 | PH1: 218 | PI1: 224 | PJ1: 225 | PK1: 229 | PL1: 230 | PM1: 232 | PN1: 234 | PO1: 237 | PP1: 240 | PQ1: 243 | PR1: 244 | PS1: 245 | PT1: 246 | PU1: 249 | PV1: 250 | PW1: 254 | PX1: 257 | PY1: 259 | PZ1: 261 | QA1: 267 | QB1: 270 | QC1: 272 | QD1: 273 | QE1: 274 | QF1: 275 | QG1: 276 | QH1: 277 | QI1: 278 | QJ1: 279 | QK1: 280 | QL1: 281 | QM1: 282 | QN1: 284 | QO1: 285 | QP1: 286 | QQ1: 287 | QR1: 288 | QS1: 289 | QT1: 290 | QU1: 292 | QV1: 294 | QW1: 295 | QX1: 296 | QY1: 297 | QZ1: 298 | RA1: 299 | RB1: 301 | RC1: 302 | RD1: 303 | RE1: 304 | RF1: 305 | RG1: 306 | RH1: 307 | RI1: 308 | RJ1: 309 | RK1: 310 | RL1: 313 | RM1: 314 | RN1: 315 | RO1: 316 | RP1: 317 | RQ1: 318 | RR1: 319 | RS1: 320 | RT1: 322 | RU1: 323 | RV1: 324 | RW1: 325 | RX1: 326 | RY1: 328 | RZ1: 329 | SA1: 330 | SB1: 332 | SC1: 333 | SD1: 335 | SE1: 337 | SF1: 338 | SG1: 340 | SH1: 341 | SI1: 342 | SJ1: 343 | SK1: 344 | SL1: 347 | SM1: 348 | SN1: 349 | SO1: 350 | SP1: 351 | SQ1: 352 | SR1: 353 | SS1: 354 | ST1: 355 | SU1: 356 | SV1: 358 | SW1: 359 | SX1: 360 | SY1: 361 | SZ1: 362 | TA1: 363 | TB1: 364 | TC1: 365 | TD1: 366 | TE1: 367 | TF1: 368 | TG1: 370 | TH1: 371 | TI1: 372 | TJ1: 373 | TK1: 374 | TL1: 375 | TM1: 377 | TN1: 378 | TO1: 380 | TP1: 381 | TQ1: 383 | TR1: 384 | TS1: 385 | TT1: 386 | TU1: 387 | TV1: 388 | TW1: 389 | TX1: 390 | TY1: 391 | TZ1: 392 | UA1: 393 | UB1: 394 | UC1: 395 | UD1: 396 | UE1: 397 | UF1: 398 | UG1: 399 | UH1: 400 | UI1: 401 | UJ1: 403 | UK1: 404 | UL1: 405 | UM1: 406 | UN1: 407 | UO1: 408 | UP1: 409 | UQ1: 410 | UR1: 411 | US1: 412 | UT1: 413 | UU1: 414 | UV1: 415 | UW1: 416 | UX1: 417 | UY1: 418 | UZ1: 419 | VA1: 420 | VB1: 421 | VC1: 422 | VD1: 423 | VE1: 424 | VF1: 425 | VG1: 426 | VH1: 427 | VI1: 428 | VJ1: 430 | VK1: 431 | VL1: 432 | VM1: 433 | VN1: 434 | VO1: 435 | VP1: 436 | VQ1: 437 | VR1: 438 | VS1: 439 | VT1: 440 | VU1: 442 | VV1: 443 | VW1: 444 | VX1: 445 | VY1: 446 | VZ1: 447 | WA1: 448 | WB1: 449 | WC1: 450 | WD1: 451 | WE1: 452 | WF1: 453 | WG1: 455 | WH1: 456 | WI1: 458 | WJ1: 460 | WK1: 461 | WL1: 462 | WM1: 463 | WN1: 464 | WO1: 465 | WP1: 466 | WQ1: 468 | WR1: 469 | WS1: 470 | WT1: 472 | WU1: 473 | WV1: 474 | WW1: 475 | WX1: 476 | WY1: 477 | WZ1: 478 | XA1: 479 | XB1: 480 | XC1: 481 | XD1: 482 | XE1: 485 | XF1: 486 | XG1: 487 | XH1: 489 | XI1: 490 | XJ1: 492 | XK1: 495 | XL1: 497 | XM1: 501 | XN1: 502 | XO1: 503 | XP1: 504 | XQ1: 505 | XR1: 507 | XS1: 509 | XT1: 510 | XU1: 511 | XV1: 512 | XW1: 513 | XX1: 514 | XY1: 515 | XZ1: 516 | YA1: 517 | YB1: 518 | YC1: 519 | YD1: 522 | YE1: 523 | YF1: 525 | YG1: 526 | YH1: 527 | YI1: 529 | YJ1: 532 | YK1: 533 | YL1: 534 | YM1: 537 | YN1: 538 | YO1: 540 | YP1: 541 | YQ1: 542 | YR1: 543 | YS1: 545 | YT1: 546 | YU1: 547 | YV1: 553 | YW1: 554 | YX1: 556 | YY1: 557 | YZ1: 558 | ZA1: 559 | ZB1: 561 | ZC1: 563 | ZD1: 564 | ZE1: 565 | ZF1: 566 | ZG1: 570 | ZH1: 572 | ZI1: 573 | ZJ1: 576 | ZK1: 578 | ZL1: 582 | ZM1: 583 | ZN1: 584 | ZO1: 590 | ZP1: 591 | ZQ1: 593 | ZR1: 600 | ZS1: 601 | ZT1: 602 | ZU1: 605 | ZV1: 611 | ZW1: 612 | ZX1: 613 | ZY1: 617 | ZZ1: 618 | AAA1: 619 | AAB1: 621 | AAC1: 622 | AAD1: 627 | AAE1: 636 | AAF1: 638 | AAG1: 646 | AAH1: 648 | AAI1: 655 | AAJ1: 656 | AAK1: 657 | AAL1: 660 | AAM1: 662 | AAN1: 665 | AAO1: 669 | AAP1: 670 | AAQ1: 674 | AAR1: 676 | AAS1: 682 | AAT1: 684 | AAU1: 685 | AAV1: 687 | AAW1: 688 | AAX1: 691 | AAY1: 694 | AAZ1: 695 | ABA1: 696 | ABB1: 697 | ABC1: 704 | ABD1: 709 | ABE1: 710 | ABF1: 721 | ABG1: 722 | ABH1: 724 | ABI1: 726 | ABJ1: 727 | ABK1: 728 | ABL1: 731 | ABM1: 736 | ABN1: 737 | ABO1: 738 | ABP1: 744 | ABQ1: 753 | ABR1: 754 | ABS1: 755 | ABT1: 757 | ABU1: 761 | ABV1: 767 | ABW1: 774 | ABX1: 776 | ABY1: 779 | ABZ1: 781 | ACA1: 783 | ACB1: 784 | ACC1: 785 | ACD1: 796 | ACE1: 853 | ACF1: 858 | ACG1: 885 | ACH1: 887 | ACI1: 893 | ACJ1: 900 | ACK1: 913 | ACL1: 941 | ACM1: 972 | ACN1: 977 | ACO1: 982 | ACP1: 1063 | ACQ1: 1120 | ACR1: 1121 | ACS1: 1122 | ACT1: 1123 | ACU1: 1124 | ACV1: 1126 | ACW1: 1127 | ACX1: 1128 | ACY1: 1129 | ACZ1: 1130 | ADA1: 1131 | ADB1: 1132 | ADC1: 1133 | ADD1: 1134 | ADE1: 1135 | ADF1: 1136 | ADG1: 1137 | ADH1: 1139 | ADI1: 1140 | ADJ1: 1142 | ADK1: 1143 | ADL1: 1144 | ADM1: 1145 | ADN1: 1148 | ADO1: 1149 | ADP1: 1152 | ADQ1: 1156 | ADR1: 1157 | ADS1: 1158 | ADT1: 1163 | ADU1: 1165 | ADV1: 1166 | ADW1: 1185 | ADX1: 1203 | ADY1: 1204 | ADZ1: 1206 | AEA1: 1211 | AEB1: 1212 | AEC1: 1213 | AED1: 1214 | AEE1: 1215 | AEF1: 1216 | AEG1: 1217 | AEH1: 1218 | AEI1: 1233 | AEJ1: 1234 | AEK1: 1235 | AEL1: 1236 | AEM1: 1251 | AEN1: 1261 | AEO1: 1273 | AEP1: 1274 | AEQ1: 1275 | AER1: 1276 | AES1: 1277 | AET1: 1285 | AEU1: 1305 | AEV1: 1308 | AEW1: 1324 | AEX1: 1325 | AEY1: 1329 | AEZ1: 1332 | AFA1: 1338 | AFB1: 1339 | AFC1: 1340 | AFD1: 1341 | AFE1: 1342 | AFF1: 1343 | AFG1: 1344 | AFH1: 1345 | AFI1: 1346 | AFJ1: 1347 | AFK1: 1348 | AFL1: 1349 | AFM1: 1350 | AFN1: 1351 | AFO1: 1352 | AFP1: 1353 | AFQ1: 1354 | AFR1: 1355 | AFS1: 1356 | AFT1: 1357 | AFU1: 1358 | AFV1: 1360 | AFW1: 1361 | AFX1: 1362 | AFY1: 1363 | AFZ1: 1366 | AGA1: 1367 | AGB1: 1368 | AGC1: 1369 | AGD1: 1370 | AGE1: 1379 | AGF1: 1380 | AGG1: 1381 | AGH1: 1383 | AGI1: 1384 | AGJ1: 1385 | AGK1: 1386 | AGL1: 1387 | AGM1: 1388 | AGN1: 1389 | AGO1: 1390 | AGP1: 1391 | AGQ1: 1392 | AGR1: 1393 | AGS1: 1394 | AGT1: 1396 | AGU1: 1397 | AGV1: 1400 | AGW1: 1402 | AGX1: 1403 | AGY1: 1405 | AGZ1: 1406 | AHA1: 1407 | AHB1: 1408 | AHC1: 1409 | AHD1: 1410 | AHE1: 1411 | AHF1: 1412 | AHG1: 1413 | AHH1: 1414 | AHI1: 1419 | AHJ1: 1420 | AHK1: 1422 | AHL1: 1423 | AHM1: 1431 | AHN1: 1432 | AHO1: 1434 | AHP1: 1436 | AHQ1: 1437 | AHR1: 1438 | AHS1: 1439 | AHT1: 1440 | AHU1: 1441 | AHV1: 1442 | AHW1: 1443 | AHX1: 1444 | AHY1: 1445 | AHZ1: 1446 | AIA1: 1447 | AIB1: 1448 | AIC1: 1449 | AID1: 1450 | AIE1: 1451 | AIF1: 1452 | AIG1: 1453 | AIH1: 1454 | AII1: 1455 | AIJ1: 1457 | AIK1: 1458 | AIL1: 1459 | AIM1: 1460 | AIN1: 1463 | AIO1: 1464 | AIP1: 1465 | AIQ1: 1466 | AIR1: 1467 | AIS1: 1468 | AIT1: 1469 | AIU1: 1470 | AIV1: 1471 | AIW1: 1473 | AIX1: 1475 | AIY1: 1476 | AIZ1: 1478 | AJA1: 1479 | AJB1: 1480 | AJC1: 1481 | AJD1: 1482 | AJE1: 1483 | AJF1: 1484 | AJG1: 1486 | AJH1: 1487 | AJI1: 1489 | AJJ1: 1494 | AJK1: 1495 | AJL1: 1496 | AJM1: 1498 | AJN1: 1499 | AJO1: 1500 | AJP1: 1501 | AJQ1: 1503 | AJR1: 1504 | AJS1: 1507 | AJT1: 1508 | AJU1: 1509 | AJV1: 1510 | AJW1: 1511 | AJX1: 1512 | AJY1: 1513 | AJZ1: 1514 | AKA1: 1515 | AKB1: 1516 | AKC1: 1517 | AKD1: 1518 | AKE1: 1519 | AKF1: 1520 | AKG1: 1521 | AKH1: 1522 | AKI1: 1523 | AKJ1: 1524 | AKK1: 1525 | AKL1: 1526 | AKM1: 1527 | AKN1: 1528 | AKO1: 1529 | AKP1: 1530 | AKQ1: 1531 | AKR1: 1532 | AKS1: 1533 | AKT1: 1534 | AKU1: 1536 | AKV1: 1537 | AKW1: 1538 | AKX1: 1539 | AKY1: 1540 | AKZ1: 1541 | ALA1: 1545 | ALB1: 1548 | ALC1: 1550 | ALD1: 1551 | ALE1: 1552 | ALF1: 1553 | ALG1: 1554 | ALH1: 1555 | ALI1: 1556 | ALJ1: 1562 | ALK1: 1563 | ALL1: 1564 | ALM1: 1565 | ALN1: 1566 | ALO1: 1567 | ALP1: 1568 | ALQ1: 1569 | ALR1: 1570 | ALS1: 1571 | ALT1: 1573 | ALU1: 1574 | ALV1: 1577 | ALW1: 1580 | ALX1: 1581 | ALY1: 1583 | ALZ1: 1584 | AMA1: 1585 | AMB1: 1586 | AMC1: 1587 | AMD1: 1588 | AME1: 1589 | AMF1: 1590 | AMG1: 1591 | AMH1: 1592 | AMI1: 1593 | AMJ1: 1594 | AMK1: 1596 | AML1: 1597 | AMM1: 1600 | AMN1: 1601 | AMO1: 1602 | AMP1: 1603 | AMQ1: 1604 | AMR1: 1607 | AMS1: 1614 | AMT1: 1615 | AMU1: 1616 | AMV1: 1617 | AMW1: 1618 | AMX1: 1619 | AMY1: 1621 | AMZ1: 1622 | ANA1: 1624 | ANB1: 1626 | ANC1: 1627 | AND1: 1628 | ANE1: 1629 | ANF1: 1630 | ANG1: 1631 | ANH1: 1632 | ANI1: 1633 | ANJ1: 1634 | ANK1: 1635 | ANL1: 1636 | ANM1: 1637 | ANN1: 1638 | ANO1: 1639 | ANP1: 1640 | ANQ1: 1641 | ANR1: 1642 | ANS1: 1643 | ANT1: 1648 | ANU1: 1649 | ANV1: 1655 | ANW1: 1658 | ANX1: 1660 | ANY1: 1663 | ANZ1: 1664 | AOA1: 1666 | AOB1: 1667 | AOC1: 1668 | AOD1: 1670 | AOE1: 1671 | AOF1: 1672 | AOG1: 1673 | AOH1: 1674 | AOI1: 1676 | AOJ1: 1677
A2: Title | B2: Happy Feet | C2: Crocodile Dundee II | D2: Crocodile Dundee | E2: Mad Max | F2: Mad Max 2 | G2: Mad Max Beyond Thunderdome | H2: Mad Max: Fury Road | I2: City of God | J2: My Big Fat Greek Wedding | K2: Porky's | L2: Hero | M2: Crouching Tiger, Hidden Dragon | N2: House of Flying Daggers | O2: The Mermaid | P2: Detective Dee and the Mystery of the Phantom Flame | Q2: Flying Swords of Dragon Gate | R2: Red Cliff | S2: Red Cliff II | T2: Only God Forgives | U2: The Fifth Element | V2: Leon | W2: Amelie | X2: Kiss of the Dragon | Y2: Unleashed | Z2: The Transporter | AA2: Transporter 2 | AB2: District 13 | AC2: District 13: Ultimatum | AD2: Taken | AE2: From Paris with Love | AF2: A Prophet | AG2: Solomon Kane | AH2: 3 Days to Kill | AI2: Downfall | AJ2: Das Boot | AK2: The Lives of Others | AL2: Lucky Number Slevin | AM2: The NeverEnding Story | AN2: Rumble in the Bronx | AO2: The Big Boss | AP2: Fist of Fury | AQ2: Way of the Dragon | AR2: Game of Death | AS2: Enter the Dragon | AT2: Police Story 3: Super Cop | AU2: Twin Dragons | AV2: The Warlords | AW2: Dragon | AX2: Seven Swords | AY2: Hard Boiled | AZ2: Ip Man | BA2: Ip Man 2 | BB2: Ip Man 3 | BC2: Iron Monkey | BD2: Kung Fu Hustle | BE2: The Raid | BF2: The Raid 2 | BG2: The Good, the Bad and the Ugly | BH2: A Fistful of Dollars | BI2: For a Few Dollars More | BJ2: Once Upon a Time in the West | BK2: Seven Samurai | BL2: Kagemusha | BM2: Ran | BN2: Tora! Tora! Tora! | BO2: Rashomon | BP2: Ichi the Killer | BQ2: 13 Assassins | BR2: Battle Royale | BS2: When the Last Sword Is Drawn | BT2: The Twilight Samurai | BU2: Godzilla | BV2: King Kong vs. Godzilla | BW2: Red Sonja | BX2: King Kong | BY2: The Lord of the Rings: Fellowship of the Ring | BZ2: The Lord of the Rings: Return of the King | CA2: The Lord of the Rings: The Two Towers | CB2: Once Were Warriors | CC2: The Hobbit: The Battle of the Five Armies | CD2: The Hobbit: The Desolation of Smaug | CE2: The Hobbit: An Unexpected Journey | CF2: No Country for Old Men | CG2: Night Watch | CH2: Day Watch | CI2: Momentum | CJ2: District 9 | CK2: The Girl with the Dragon Tattoo | CL2: The Girl Who Kicked the Hornets' Nest | CM2: The Seventh Seal | CN2: Ong-Bak | CO2: Ong-Bak 2 | CP2: Warrior King | CQ2: Warrior King 2 | CR2: Harry Potter and the Order of the Phoenix | CS2: Harry Potter and the Goblet of Fire | CT2: Die Another Day | CU2: The World Is Not Enough | CV2: Harry Potter and the Prisoner of Azkaban | CW2: Harry Potter and the Philosopher's Stone | CX2: Tomorrow Never Dies | CY2: Casino Royale | CZ2: Harry Potter and the Chamber of Secrets | DA2: GoldenEye | DB2: Licence to Kill | DC2: The Living Daylights | DD2: Moonraker | DE2: For Your Eyes Only | DF2: Gandhi | DG2: Borat: Cultural Learnings of America for Make Benefit Glorious Nation of Kazakhstan | DH2: Hot Fuzz | DI2: Sense and Sensibility | DJ2: 28 Days Later | DK2: The Beach | DL2: Trainspotting | DM2: The Spy Who Loved Me | DN2: Casino Royale | DO2: Thunderball | DP2: On Her Majesty's Secret Service | DQ2: Diamonds are Forever | DR2: Live and Let Die | DS2: The Man with the Golden Gun | DT2: Shaun of the Dead | DU2: Four Weddings and a Funeral | DV2: From Russia with Love | DW2: Dr. No | DX2: Sunshine | DY2: Flushed Away | DZ2: Skyfall | EA2: Harry Potter and the Deathly Hallows - Part 2 | EB2: Alice in Wonderland | EC2: Harry Potter and the Deathly Hallows - Part 1 | ED2: Harry Potter and the Half-Blood Prince | EE2: Sherlock Holmes | EF2: Mamma Mia! | EG2: Quantum of Solace | EH2: The Chronicles of Narnia: Prince Caspian | EI2: The Chronicles of Narnia: The Lion, the Witch and the Wardrobe | EJ2: Notting Hill | EK2: Shakespeare in Love | EL2: The Full Monty | EM2: Superman II | EN2: Chariots of Fire | EO2: Time Bandits | EP2: Revenge of the Pink Panther | EQ2: A Bridge Too Far | ER2: The Rocky Horror Picture Show | ES2: The Return of the Pink Panther | ET2: A Clockwork Orange | EU2: Bedknobs and Broomsticks | EV2: 2001: A Space Odyssey | EW2: Romeo and Juliet | EX2: Oliver! | EY2: Doctor Zhivago | EZ2: A Hard Day's Night | FA2: Lawrence of Arabia | FB2: The Guns of Navarone | FC2: The Bridge on the River Kwai | FD2: Ivanhoe | FE2: Moulin Rouge | FF2: Goodbye, Mr. Chips | FG2: Spectre | FH2: Lolita | FI2: The 39 Steps | FJ2: Anna Karenina | FK2: Brief Encounter | FL2: The Seventh Veil | FM2: Great Expectations | FN2: Hamlet | FO2: Monty Python and the Holy Grail | FP2: Monty Python's Life of Brian | FQ2: Clash of the Titans | FR2: This Is England | FS2: Dead Man's Shoes | FT2: The League of Gentlemen's Apocalypse | FU2: Down Terrace | FV2: Kill List | FW2: A Field in England | FX2: High-Rise | FY2: Slumdog Millionaire | FZ2: The Best Exotic Marigold Hotel | GA2: The Second Best Exotic Marigold Hotel | GB2: Ironclad | GC2: Shallow Grave | GD2: A Life Less Ordinary | GE2: 28 Weeks Later | GF2: 127 Hours | GG2: Trance | GH2: Kingsman: The Secret Service | GI2: Kick-Ass | GJ2: Stardust | GK2: Layer Cake | GL2: Underworld | GM2: Underworld: Evolution | GN2: Outland | GO2: Full Metal Jacket | GP2: Eyes Wide Shut | GQ2: The Shining | GR2: Dr. Strangelove or: How I Learned to Stop Worrying and Love the Bomb | GS2: Murder on the Orient Express | GT2: Flash Gordon | GU2: Where Eagles Dare | GV2: Cross of Iron | GW2: Zulu | GX2: Bronson | GY2: Hugo | GZ2: Labyrinth | HA2: Scott Pilgrim vs. the World | HB2: Fantastic Beasts and Where to Find Them | HC2: Ex Machina | HD2: Anna Karenina | HE2: Chocolat | HF2: The English Patient | HG2: Lock, Stock and Two Smoking Barrels | HH2: Snatch | HI2: RocknRolla | HJ2: Sherlock Holmes: A Game of Shadows | HK2: The Counsellor | HL2: The Theory of Everything | HM2: Man on Wire | HN2: The Danish Girl | HO2: The Other Boleyn Girl | HP2: Mandela: Long Walk to Freedom | HQ2: Les Misérables | HR2: The King's Speech | HS2: Shame | HT2: Rush | HU2: The Eagle | HV2: The Last King of Scotland | HW2: Centurion | HX2: Jason and the Argonauts | HY2: One Million Years B.C. | HZ2: Superman III | IA2: Jurassic Park | IB2: Spider-Man | IC2: Superman Returns | ID2: Titanic | IE2: Evan Almighty | IF2: Waterworld | IG2: Pearl Harbor | IH2: Transformers | II2: Beowulf | IJ2: Bee Movie | IK2: Pirates of the Caribbean: At World's End | IL2: I Am Legend | IM2: Ratatouille | IN2: Troy | IO2: Batman Begins | IP2: Charlie and the Chocolate Factory | IQ2: Pirates of the Caribbean: Dead Man's Chest | IR2: Lethal Weapon 4 | IS2: Armageddon | IT2: Men in Black II | IU2: Spider-Man 3 | IV2: Spider-Man 2 | IW2: Stealth | IX2: Final Fantasy: The Spirits Within | IY2: Miami Vice | IZ2: Master and Commander: The Far Side of the World | JA2: War of the Worlds | JB2: The Bourne Ultimatum | JC2: The Matrix Reloaded | JD2: The Da Vinci Code | JE2: The Day After Tomorrow | JF2: Pirates of the Caribbean: Curse of the Black Pearl | JG2: The Last Samurai | JH2: The Perfect Storm | JI2: Mission: Impossible III | JJ2: Mission: Impossible II | JK2: Windtalkers | JL2: Star Wars: Episode II - Attack of the Clones | JM2: Monsters, Inc. | JN2: Star Wars: Episode I - The Phantom Menace | JO2: Star Wars: Episode III - Revenge of the Sith | JP2: The Matrix Revolutions | JQ2: Ocean's Eleven | JR2: Live Free or Die Hard | JS2: Around the World in 80 Days | JT2: Kingdom of Heaven | JU2: Mr. & Mrs. Smith | JV2: The Aviator | JW2: Ali | JX2: I, Robot | JY2: Minority Report | JZ2: Terminator 2: Judgement Day | KA2: Catwoman | KB2: American Gangster | KC2: Blood Diamond | KD2: Gladiator | KE2: True Lies | KF2: Gangs of New York | KG2: Black Hawk Down | KH2: Rush Hour 3 | KI2: Rush Hour 2 | KJ2: Men in Black | KK2: The Departed | KL2: Die Hard: With A Vengeance | KM2: Cinderella Man | KN2: The Bourne Supremacy | KO2: Last Action Hero | KP2: Cast Away | KQ2: Ocean's Twelve | KR2: Click | KS2: Bruce Almighty | KT2: Mission: Impossible | KU2: Deep Impact | KV2: Road to Perdition | KW2: A Beautiful Mind | KX2: Children of Men | KY2: Munich | KZ2: Independence Day | LA2: X-Men | LB2: X2 | LC2: The Rock | LD2: Constantine | LE2: Unbreakable | LF2: Talladega Nights: The Ballad of Ricky Bobby | LG2: The Simpsons Movie | LH2: Braveheart | LI2: Jarhead | LJ2: The Village | LK2: Shrek the Third | LL2: Shrek 2 | LM2: The Abyss | LN2: Star Trek: Insurrection | LO2: Who Framed Roger Rabbit? | LP2: Sleepy Hollow | LQ2: xXx | LR2: Die Hard 2 | LS2: The Long Kiss Goodnight | LT2: Apollo 13 | LU2: Saving Private Ryan | LV2: Fight Club | LW2: The Matrix | LX2: Total Recall | LY2: Cliffhanger | LZ2: Clear and Present Danger | MA2: The Black Dahlia | MB2: The Truman Show | MC2: Event Horizon | MD2: The Bourne Identity | ME2: Hellboy | MF2: Starsky & Hutch | MG2: Intolerable Cruelty | MH2: 300 | MI2: Star Trek: Nemesis | MJ2: Superman | MK2: Crimson Tide | ML2: Deja Vu | MM2: Man On Fire | MN2: Enemy of the State | MO2: Kill Bill: Vol. 1 | MP2: Alien 3 | MQ2: Shanghai Noon | MR2: Kill Bill: Vol. 2 | MS2: Blade II | MT2: Flags of our Fathers | MU2: Casino | MV2: Robin Hood: Prince of Thieves | MW2: Shrek | MX2: Shanghai Knights | MY2: Indiana Jones and the Last Crusade | MZ2: Star Trek: First Contact | NA2: Blade | NB2: Patriot Games | NC2: The Fugitive | ND2: The Prestige | NE2: The Last of the Mohicans | NF2: Apocalypto | NG2: Wedding Crashers | NH2: Back to the Future Part III | NI2: Back to the Future Part II | NJ2: Sin City | NK2: Serenity | NL2: Star Trek: Generations | NM2: Never Say Never Again | NN2: Star Trek: The Motion Picture | NO2: Rush Hour | NP2: Lethal Weapon 3 | NQ2: Star Wars: Episode VI - Return of the Jedi | NR2: A History of Violence | NS2: Get Shorty | NT2: The Assassination of Jesse James by the Coward Robert Ford | NU2: Million Dollar Baby | NV2: Seven | NW2: The Hunt For Red October | NX2: Ghostbusters | NY2: Star Trek V: The Final Frontier | NZ2: Indiana Jones and the Temple of Doom | OA2: Blade Runner | OB2: Die Hard | OC2: Octopussy | OD2: Star Trek VI: The Undiscovered Country | OE2: The Running Man | OF2: Open Range | OG2: Kindergarten Cop | OH2: O Brother, Where Art Thou? | OI2: Goodfellas | OJ2: The Passion of the Christ | OK2: The Untouchables | OL2: Schindler's List | OM2: Anchorman: The Legend of Ron Burgundy | ON2: Scarface | OO2: Star Trek IV: The Voyage Home | OP2: King Kong | OQ2: Star Wars: Episode V - The Empire Strikes Back | OR2: Equilibrium | OS2: From Dusk Till Dawn | OT2: Raiders of the Lost Ark | OU2: Back to the Future | OV2: Dances with Wolves | OW2: Star Trek III: The Search For Spock | OX2: Raging Bull | OY2: Aliens | OZ2: High Plains Drifter | PA2: Collateral | PB2: American Beauty | PC2: Lethal Weapon | PD2: Lethal Weapon 2 | PE2: Brokeback Mountain | PF2: Hulk | PG2: Ride with the Devil | PH2: Twins | PI2: Letters from Iwo Jima | PJ2: Star Trek II: The Wrath of Khan | PK2: Star Wars: Episode IV: A New Hope | PL2: E.T.: The Extra-Terrestrial | PM2: You Only Live Twice | PN2: Alien | PO2: Pulp Fiction | PP2: Fargo | PQ2: Good Night, and Good Luck | PR2: Pale Rider | PS2: The Terminator | PT2: Around the World in 80 Days | PU2: The Usual Suspects | PV2: Memento | PW2: Goldfinger | PX2: Reservoir Dogs | PY2: King Kong | PZ2: Super Size Me | QA2: Indiana Jones and the Kingdom of the Crystal Skull | QB2: Transformers: Age of Extinction | QC2: Guardians of the Galaxy | QD2: Maleficent | QE2: X-Men: Days of Future Past | QF2: Captain America: The Winter Soldier | QG2: The Hunger Games: Mockingjay Part 1 | QH2: The Amazing Spider-Man 2 | QI2: Dawn of the Planet of the Apes | QJ2: Interstellar | QK2: Frozen | QL2: Iron Man 3 | QM2: Despicable Me 2 | QN2: The Hunger Games: Catching Fire | QO2: Fast & Furious 6 | QP2: Monsters University | QQ2: Gravity | QR2: Man of Steel | QS2: Thor: The Dark World | QT2: The Avengers | QU2: The Dark Knight Rises | QV2: Ice Age: Continental Drift | QW2: The Twilight Saga: Breaking Dawn - Part 2 | QX2: The Amazing Spider-Man | QY2: Madagascar 3: Europe's Most Wanted | QZ2: The Hunger Games | RA2: Men in Black 3 | RB2: Transformers: Dark of the Moon | RC2: Pirates of the Caribbean: On Stranger Tides | RD2: The Twilight Saga: Breaking Dawn - Part 1 | RE2: Mission: Impossible - Ghost Protocol | RF2: Kung Fu Panda 2 | RG2: Fast Five | RH2: The Hangover Part II | RI2: The Smurfs | RJ2: Cars 2 | RK2: Toy Story 3 | RL2: Inception | RM2: Shrek Forever After | RN2: The Twilight Saga: Eclipse | RO2: Iron Man 2 | RP2: Tangled | RQ2: Despicable Me | RR2: How to Train Your Dragon | RS2: Avatar | RT2: Ice Age: Dawn of the Dinosaurs | RU2: Transformers: Revenge of the Fallen | RV2: 2012 | RW2: Up | RX2: The Twilight Saga: New Moon | RY2: Angels & Demons | RZ2: The Hangover | SA2: The Dark Knight | SB2: Kung Fu Panda | SC2: Hancock | SD2: Madagascar: Escape 2 Africa | SE2: Iron Man | SF2: WALL-E | SG2: National Treasure: Book of Secrets | SH2: Frost/Nixon | SI2: Ice Age: The Meltdown | SJ2: Night at the Museum | SK2: Cars | SL2: Madagascar | SM2: Hitch | SN2: The Incredibles | SO2: Meet the Fockers | SP2: Shark Tale | SQ2: Finding Nemo | SR2: Terminator 3: Rise of the Machines | SS2: Bad Boys II | ST2: Signs | SU2: Ice Age | SV2: The Mummy Returns | SW2: Jurassic Park III | SX2: Hannibal | SY2: What Women Want | SZ2: Dinosaur | TA2: How the Grinch Stole Christmas | TB2: Meet the Parents | TC2: What Lies Beneath | TD2: Toy Story 2 | TE2: Tarzan | TF2: The Mummy | TG2: Austin Powers: The Spy Who Shagged Me | TH2: Godzilla | TI2: There's Something About Mary | TJ2: A Bug's Life | TK2: Mulan | TL2: Dr. Dolittle | TM2: The Lost World: Jurassic Park | TN2: Air Force One | TO2: Liar Liar | TP2: My Best Friend's Wedding | TQ2: Twister | TR2: The Hunchback of Notre Dame | TS2: 101 Dalmatians | TT2: Ransom | TU2: The Nutty Professor | TV2: Jerry Maguire | TW2: Eraser | TX2: Toy Story | TY2: Pocahontas | TZ2: Batman Forever | UA2: Casper | UB2: Jumanji | UC2: The Lion King | UD2: The Mask | UE2: Speed | UF2: The Flintstones | UG2: Dumb and Dumber | UH2: Donnie Brasco | UI2: Interview with the Vampire: The Vampire Chronicles | UJ2: Mrs. Doubtfire | UK2: The Firm | UL2: Indecent Proposal | UM2: Sleepless in Seattle | UN2: Philadelphia | UO2: The Pelican Brief | UP2: Aladdin | UQ2: The Bodyguard | UR2: Home Alone 2: Lost in New York | US2: Basic Instinct | UT2: Batman Returns | UU2: A Few Good Men | UV2: Sister Act | UW2: Bram Stoker's Dracula | UX2: Wayne's World | UY2: Beauty and the Beast | UZ2: Hook | VA2: The Silence of the Lambs | VB2: JFK | VC2: The Addams Family | VD2: Cape Fear | VE2: Hot Shots! | VF2: City Slickers | VG2: Ghost | VH2: Home Alone | VI2: Pretty Woman | VJ2: Teenage Mutant Ninja Turtles | VK2: Batman | VL2: Look Who's Talking | VM2: Dead Poets Society | VN2: Honey, I Shrunk the Kids | VO2: Ghostbusters II | VP2: The Little Mermaid | VQ2: Born on the Fourth of July | VR2: Rain Man | VS2: Coming to America | VT2: Big | VU2: The Naked Gun: From the Files of Police Squad! | VV2: Cocktail | VW2: Beetlejuice | VX2: Three Men and a Baby | VY2: Fatal Attraction | VZ2: Beverly Hills Cop II | WA2: Good Morning, Vietnam | WB2: Moonstruck | WC2: The Secret of My Success | WD2: Stakeout | WE2: The Witches of Eastwick | WF2: Top Gun | WG2: Platoon | WH2: The Karate Kid, Part II | WI2: The Golden Child | WJ2: Ferris Bueller's Day Off | WK2: Rambo: First Blood Part II | WL2: Rocky IV | WM2: The Color Purple | WN2: Out Of Africa | WO2: Cocoon | WP2: The Jewel of the Nile | WQ2: The Goonies | WR2: Spies Like Us | WS2: Beverly Hills Cop | WT2: Gremlins | WU2: The Karate Kid | WV2: Police Academy | WW2: Footloose | WX2: Romancing the Stone | WY2: Terms of Endearment | WZ2: Flashdance | XA2: Trading Places | XB2: WarGames | XC2: Sudden Impact | XD2: Staying Alive | XE2: Tootsie | XF2: An Officer and a Gentleman | XG2: Rocky III | XH2: 48 Hrs. | XI2: Poltergeist | XJ2: Annie | XK2: Arthur | XL2: The Cannonball Run | XM2: 9 to 5 | XN2: Stir Crazy | XO2: Airplane! | XP2: Any Which Way You Can | XQ2: Private Benjamin | XR2: Smokey and the Bandit II | XS2: The Blues Brothers | XT2: Kramer vs. Kramer | XU2: The Amityville Horror | XV2: Rocky II | XW2: Apocalypse Now | XX2: 10 | XY2: The Jerk | XZ2: The Muppet Movie | YA2: Grease | YB2: National Lampoon's Animal House | YC2: Every Which Way but Loose | YD2: Jaws 2 | YE2: Dawn of the Dead | YF2: The Deer Hunter | YG2: Smokey and the Bandit | YH2: Close Encounters of the Third Kind | YI2: Saturday Night Fever | YJ2: The Deep | YK2: Annie Hall | YL2: Rocky | YM2: All the President's Men | YN2: The Omen | YO2: Silver Streak | YP2: The Enforcer | YQ2: Midway | YR2: Jaws | YS2: One Flew Over the Cuckoo's Nest | YT2: Dog Day Afternoon | YU2: Shampoo | YV2: Blazing Saddles | YW2: The Towering Inferno | YX2: Young Frankenstein | YY2: Earthquake | YZ2: The Godfather Part II | ZA2: Airport 1975 | ZB2: The Longest Yard | ZC2: The Sting | ZD2: The Exorcist | ZE2: American Graffiti | ZF2: Papillon | ZG2: Robin Hood | ZH2: The Godfather | ZI2: The Poseidon Adventure | ZJ2: Deliverance | ZK2: Cabaret | ZL2: Fiddler on the Roof | ZM2: The French Connection | ZN2: Dirty Harry | ZO2: Love Story | ZP2: Airport | ZQ2: Patton | ZR2: Butch Cassidy and the Sundance Kid | ZS2: Midnight Cowboy | ZT2: Easy Rider | ZU2: Paint Your Wagon | ZV2: The Love Bug | ZW2: The Odd Couple | ZX2: Bullitt | ZY2: Planet of the Apes | ZZ2: The Graduate | AAA2: The Jungle Book | AAB2: Bonnie and Clyde | AAC2: The Dirty Dozen | AAD2: Night of the Living Dead | AAE2: Grand Prix | AAF2: The Sound of Music | AAG2: Von Ryan's Express | AAH2: My Fair Lady | AAI2: Cleopatra | AAJ2: How the West Was Won | AAK2: It's a Mad, Mad, Mad, Mad World | AAL2: The Sword in the Stone | AAM2: The Birds | AAN2: The Longest Day | AAO2: Mutiny on the Bounty | AAP2: To Kill a Mockingbird | AAQ2: West Side Story | AAR2: El Cid | AAS2: One Hundred and One Dalmatians | AAT2: Spartacus | AAU2: Psycho | AAV2: Swiss Family Robinson | AAW2: The Alamo | AAX2: Ocean's 11 | AAY2: Ben-Hur | AAZ2: Sleeping Beauty | ABA2: North by Northwest | ABB2: Some Like It Hot | ABC2: South Pacific | ABD2: The Vikings | ABE2: Vertigo | ABF2: A Farewell to Arms | ABG2: Gunfight at the O.K. Corral | ABH2: The Ten Commandments | ABI2: War and Peace | ABJ2: The King and I | ABK2: The Searchers | ABL2: High Society | ABM2: Oklahoma! | ABN2: Guys and Dolls | ABO2: Lady and the Tramp | ABP2: 20,000 Leagues Under the Sea | ABQ2: The Robe | ABR2: From Here to Eternity | ABS2: Shane | ABT2: Peter Pan | ABU2: Gentlemen Prefer Blondes | ABV2: Singin' in the Rain | ABW2: Alice in Wonderland | ABX2: A Streetcar Named Desire | ABY2: The African Queen | ABZ2: Strangers on a Train | ACA2: Cinderella | ACB2: King Solomon's Mines | ACC2: Annie Get Your Gun | ACD2: Sands of Iwo Jima | ACE2: For Whom the Bell Tolls | ACF2: Casablanca | ACG2: The Great Dictator | ACH2: The Grapes of Wrath | ACI2: Gone with the Wind | ACJ2: The Wizard of Oz | ACK2: Snow White and the Seven Dwarfs | ACL2: Anna Karenina | ACM2: Frankenstein | ACN2: Dracula | ACO2: All Quiet on the Western Front | ACP2: The Kid | ACQ2: Star Wars: The Force Awakens | ACR2: Jurassic World | ACS2: Furious 7 | ACT2: Avengers: Age of Ultron | ACU2: Minions | ACV2: Inside Out | ACW2: Mission: Impossible - Rogue Nation | ACX2: The Hunger Games: Mockingjay - Part 2 | ACY2: The Martian | ACZ2: Captain America: Civil War | ADA2: Finding Dory | ADB2: Zootopia | ADC2: The Jungle Book | ADD2: Batman v Superman: Dawn of Justice | ADE2: The Secret Life of Pets | ADF2: Deadpool | ADG2: Suicide Squad | ADH2: X-Men: Apocalypse | ADI2: Doctor Strange | ADJ2: The Parent Trap | ADK2: Captain Blood | ADL2: The Adventures of Robin Hood | ADM2: The Charge of the Light Brigade | ADN2: Mutiny on the Bounty | ADO2: The Misfits | ADP2: Citizen Kane | ADQ2: The Public Enemy | ADR2: It's a Wonderful Life | ADS2: Mr. Smith Goes to Washington | ADT2: Miracle on 34th Street | ADU2: Joan of Arc | ADV2: The Three Musketeers | ADW2: Cannonball Run II | ADX2: Romeo Must Die | ADY2: The One | ADZ2: Cradle 2 the Grave | AEA2: The Forbidden Kingdom | AEB2: The Mummy: Tomb of the Dragon Emperor | AEC2: The Expendables | AED2: The Expendables 2 | AEE2: The Expendables 3 | AEF2: The Incredible Hulk | AEG2: Now You See Me | AEH2: Clash of the Titans | AEI2: Hard Target | AEJ2: Broken Arrow | AEK2: Face/Off | AEL2: Paycheck | AEM2: Crouching Tiger, Hidden Dragon: Sword of Destiny | AEN2: 47 Ronin | AEO2: Thor | AEP2: Battleship | AEQ2: The Kingdom | AER2: Lone Survivor | AES2: Deepwater Horizon | AET2: The Fast and the Furious: Tokyo Drift | AEU2: The Gunman | AEV2: Assault on Precinct 13 | AEW2: Elysium | AEX2: Chappie | AEY2: John Carter | AEZ2: A Knight's Tale | AFA2: Steve Jobs | AFB2: Life of Pi | AFC2: Terminator Genisys | AFD2: Maggie | AFE2: Sabotage | AFF2: Escape Plan | AFG2: The Last Stand | AFH2: Terminator Salvation | AFI2: Collateral Damage | AFJ2: The 6th Day | AFK2: End of Days | AFL2: Batman & Robin | AFM2: Jingle All the Way | AFN2: Junior | AFO2: Total Recall | AFP2: True Grit | AFQ2: Red Heat | AFR2: Predator | AFS2: Raw Deal | AFT2: Commando | AFU2: X-Men: The Last Stand | AFV2: Conan the Destroyer | AFW2: Conan the Barbarian | AFX2: Conan the Barbarian | AFY2: Pumping Iron | AFZ2: This Means War | AGA2: We Are Marshall | AGB2: X-Men: First Class | AGC2: Charlie's Angels | AGD2: Charlie's Angels: Full Throttle | AGE2: Once Upon a Time in America | AGF2: Underworld: Rise of the Lycans | AGG2: Underworld: Awakening | AGH2: Stargate | AGI2: Under Siege | AGJ2: Bridge of Spies | AGK2: Duel | AGL2: Empire of the Sun | AGM2: Amistad | AGN2: A.I. Artificial Intelligence | AGO2: Catch Me If You Can | AGP2: The Terminal | AGQ2: Lincoln | AGR2: Abraham Lincoln: Vampire Hunter | AGS2: The BFG | AGT2: Unbroken | AGU2: Inside Llewyn Davis | AGV2: The Ladykillers | AGW2: The Big Lebowski | AGX2: Miller's Crossing | AGY2: Outlander | AGZ2: Timecop | AHA2: Kung Fu Panda 3 | AHB2: Universal Soldier | AHC2: Double Impact | AHD2: Death Warrant | AHE2: Kickboxer | AHF2: Cyborg | AHG2: Bloodsport | AHH2: Brooklyn's Finest | AHI2: Paths of Glory | AHJ2: The Treasure of the Sierra Madre | AHK2: The Unforgiven | AHL2: Unforgiven | AHM2: Hang 'Em High | AHN2: Coogan's Bluff | AHO2: Kelly's Heroes | AHP2: The Outlaw Josey Wales | AHQ2: Heartbreak Ridge | AHR2: The Dead Pool | AHS2: Space Cowboys | AHT2: Gran Torino | AHU2: Invictus | AHV2: American Sniper | AHW2: Sully | AHX2: J. Edgar | AHY2: Changeling | AHZ2: Blade: Trinity | AIA2: U.S. Marshals | AIB2: Drop Zone | AIC2: Demolition Man | AID2: Passenger 57 | AIE2: The Princess Bride | AIF2: The Long Riders | AIG2: The Wild Bunch | AIH2: American History X | AII2: Convoy | AIJ2: The Getaway | AIK2: Straw Dogs | AIL2: Judgment at Nuremberg | AIM2: The Great Escape | AIN2: Star Trek Beyond | AIO2: Star Trek Into Darkness | AIP2: Star Trek | AIQ2: RoboCop | AIR2: RoboCop | AIS2: Clerks | AIT2: Mallrats | AIU2: Chasing Amy | AIV2: Dogma | AIW2: Drive | AIX2: Taxi Driver | AIY2: Mean Streets | AIZ2: New York, New York | AJA2: The King of Comedy | AJB2: The Color of Money | AJC2: The Last Temptation of Christ | AJD2: The Age of Innocence | AJE2: Silence | AJF2: The Wolf of Wall Street | AJG2: Shutter Island | AJH2: Zoolander | AJI2: Willow | AJJ2: Happy Feet Two | AJK2: Zoolander 2 | AJL2: Dune | AJM2: The Nice Guys | AJN2: Kiss Kiss Bang Bang | AJO2: Independence Day: Resurgence | AJP2: Ghostbusters | AJQ2: Jason Bourne | AJR2: Sausage Party | AJS2: Jackie Brown | AJT2: Inglourious Basterds | AJU2: Django Unchained | AJV2: The Hateful Eight | AJW2: Bill & Ted's Excellent Adventure | AJX2: Bill & Ted's Bogus Journey | AJY2: The Magnificent Seven | AJZ2: The Magnificent Seven | AKA2: The Replacement Killers | AKB2: Training Day | AKC2: Tears of the Sun | AKD2: King Arthur | AKE2: Shooter | AKF2: Olympus Has Fallen | AKG2: The Equalizer | AKH2: Southpaw | AKI2: Miss Peregrine's Home for Peculiar Children | AKJ2: Mars Attacks! | AKK2: Planet of the Apes | AKL2: Big Fish | AKM2: Dark Shadows | AKN2: Watchmen | AKO2: Man of Steel | AKP2: Sucker Punch | AKQ2: Dawn of the Dead | AKR2: Jack Reacher: Never Go Back | AKS2: Jack Reacher | AKT2: The Way of the Gun | AKU2: Moana | AKV2: Bad Santa | AKW2: Bad Santa 2 | AKX2: Rogue One: A Star Wars Story | AKY2: Passengers | AKZ2: The Imitation Game | ALA2: Godzilla | ALB2: Near Dark | ALC2: Point Break | ALD2: Point Break | ALE2: Invincible | ALF2: Strange Days | ALG2: K-19: The Widowmaker | ALH2: The Hurt Locker | ALI2: Zero Dark Thirty | ALJ2: The Man from U.N.C.L.E. | ALK2: Prometheus | ALL2: Legend | ALM2: Black Rain | ALN2: Thelma & Louise | ALO2: 1492: Conquest of Paradise | ALP2: G.I. Jane | ALQ2: Matchstick Men | ALR2: Body of Lies | ALS2: Robin Hood | ALT2: Exodus: Gods and Kings | ALU2: Twilight | ALV2: Dead Man Down | ALW2: The Girl with the Dragon Tattoo | ALX2: John Wick | ALY2: The Revenant | ALZ2: Birdman | AMA2: 21 Grams | AMB2: Ted | AMC2: Ted 2 | AMD2: A Million Ways to Die in the West | AME2: Hansel & Gretel: Witch Hunters | AMF2: There Will Be Blood | AMG2: Punch-Drunk Love | AMH2: The Master | AMI2: Inherent Vice | AMJ2: Boogie Nights | AMK2: Gremlins 2: The New Batch | AML2: The Punisher | AMM2: Looper | AMN2: 12 Years a Slave | AMO2: Prisoners | AMP2: Cowboys & Aliens | AMQ2: Knight and Day | AMR2: Jupiter Ascending | AMS2: Sicario | AMT2: Edge of Tomorrow | AMU2: The Adjustment Bureau | AMV2: The Wolfman | AMW2: Charlie Wilson's War | AMX2: Sin City: A Dame to Kill For | AMY2: Ant-Man | AMZ2: 3:10 to Yuma | ANA2: The Wolverine | ANB2: Solaris | ANC2: Magic Mike | AND2: The Three Musketeers | ANE2: Mr. Holland's Opus | ANF2: The Mighty Ducks | ANG2: Young Guns | ANH2: Young Guns II: Blaze of Glory | ANI2: The Lost Boys | ANJ2: Flatliners | ANK2: 21 Jump Street | ANL2: Cloudy with a Chance of Meatballs | ANM2: Anastasia | ANN2: Hot Rod | ANO2: Cloudy with a Chance of Meatballs 2 | ANP2: The Lego Movie | ANQ2: Bad Boys | ANR2: 22 Jump Street | ANS2: Ice Age: Collision Course | ANT2: Pete's Dragon | ANU2: Pete's Dragon | ANV2: Fantastic Voyage | ANW2: Julius Caesar | ANX2: King Solomon's Mines | ANY2: Giant | ANZ2: Rebel Without a Cause | AOA2: Gentleman's Agreement | AOB2: Viva Zapata! | AOC2: On the Waterfront | AOD2: The Diary of Anne Frank | AOE2: The Greatest Story Ever Told | AOF2: A Place in the Sun | AOG2: The Talk of the Town | AOH2: Samson and Delilah | AOI2: Enemy Mine | AOJ2: In the Line of Fire
A3: Release Date | B3: 39038 | C3: 32288 | D3: 31681 | E3: 28957 | F3: 29944 | G3: 31238 | H3: 42131 | I3: 37498 | J3: 37365 | K3: 30057 | L3: 37553 | M3: 36713 | N3: 38126 | O3: 42408 | P3: 40450 | Q3: 40892 | R3: 39639 | S3: 39820 | T3: 41416 | U3: 35557 | V3: 34591 | W3: 37006 | X3: 37078 | Y3: 38385 | Z3: 37531 | AA3: 38567 | AB3: 38301 | AC3: 39862 | AD3: 39505 | AE3: 40214 | AF3: 39949 | AG3: 40170 | AH3: 41682 | AI3: 38246 | AJ3: 29846 | AK3: 38799 | AL3: 38772 | AM3: 30778 | AN3: 34720 | AO3: 26209 | AP3: 26380 | AQ3: 26663 | AR3: 28572 | AS3: 26871 | AT3: 33789 | AU3: 33618 | AV3: 39428 | AW3: 40676 | AX3: 38562 | AY3: 33710 | AZ3: 39800 | BA3: 40297 | BB3: 42354 | BC3: 34215 | BD3: 38244 | BE3: 40794 | BF3: 41660 | BG3: 24456 | BH3: 23632 | BI3: 24064 | BJ3: 25193 | BK3: 19840 | BL3: 29337 | BM3: 31198 | BN3: 25834 | BO3: 18500 | BP3: 37148 | BQ3: 40446 | BR3: 36876 | BS3: 37564 | BT3: 37562 | BU3: 20031 | BV3: 22869 | BW3: 31231 | BX3: 38700 | BY3: 37244 | BZ3: 37972 | CA3: 37608 | CB3: 34803 | CC3: 41974 | CD3: 41621 | CE3: 41257 | CF3: 39221 | CG3: 38176 | CH3: 38718 | CI3: 42293 | CJ3: 40038 | CK3: 39871 | CL3: 40144 | CM3: 20867 | CN3: 37642 | CO3: 39786 | CP3: 38575 | CQ3: 41570 | CR3: 39274 | CS3: 38662 | CT3: 37580 | CU3: 36490 | CV3: 38138 | CW3: 37211 | CX3: 35776 | CY3: 39035 | CZ3: 37575 | DA3: 35027 | DB3: 32672 | DC3: 31955 | DD3: 29035 | DE3: 29761 | DF3: 30287 | DG3: 39023 | DH3: 39127 | DI3: 35046 | DJ3: 37561 | DK3: 36567 | DL3: 35118 | DM3: 28313 | DN3: 24590 | DO3: 24085 | DP3: 25555 | DQ3: 26281 | DR3: 26842 | DS3: 27382 | DT3: 38086 | DU3: 34467 | DV3: 23294 | DW3: 22924 | DX3: 39178 | DY3: 39024 | DZ3: 41208 | EA3: 40739 | EB3: 40234 | EC3: 40501 | ED3: 40009 | EE3: 40173 | EF3: 39629 | EG3: 39752 | EH3: 39584 | EI3: 38694 | EJ3: 36301 | EK3: 36132 | EL3: 35671 | EM3: 29685 | EN3: 29675 | EO3: 29777 | EP3: 28690 | EQ3: 28291 | ER3: 27620 | ES3: 27535 | ET3: 26286 | EU3: 26213 | EV3: 24931 | EW3: 25119 | EX3: 25107 | EY3: 24098 | EZ3: 23564 | FA3: 22990 | FB3: 22398 | FC3: 21095 | FD3: 19206 | FE3: 19351 | FF3: 14380 | FG3: 42303 | FH3: 22810 | FI3: 12941 | FJ3: 17554 | FK3: 16767 | FL3: 16728 | FM3: 17162 | FN3: 17657 | FO3: 27493 | FP3: 29084 | FQ3: 29749 | FR3: 38972 | FS3: 38261 | FT3: 38506 | FU3: 40077 | FV3: 40614 | FW3: 41460 | FX3: 42260 | FY3: 39690 | FZ3: 40877 | GA3: 42061 | GB3: 40606 | GC3: 34471 | GD3: 35727 | GE3: 39198 | GF3: 40425 | GG3: 41352 | GH3: 41986 | GI3: 40263 | GJ3: 39304 | GK3: 38261 | GL3: 37883 | GM3: 38737 | GN3: 29728 | GO3: 31945 | GP3: 36357 | GQ3: 29364 | GR3: 23405 | GS3: 27357 | GT3: 29560 | GU3: 25176 | GV3: 28153 | GW3: 23398 | GX3: 39738 | GY3: 40826 | GZ3: 31590 | HA3: 40386 | HB3: 42684 | HC3: 42025 | HD3: 41159 | HE3: 36875 | HF3: 35384 | HG3: 36035 | HH3: 36761 | HI3: 39695 | HJ3: 40893 | HK3: 41550 | HL3: 41889 | HM3: 39469 | HN3: 42252 | HO3: 39493 | HP3: 41524 | HQ3: 41248 | HR3: 40427 | HS3: 40790 | HT3: 41519 | HU3: 40627 | HV3: 39094 | HW3: 40291 | HX3: 23181 | HY3: 24471 | HZ3: 30484 | IA3: 34131 | IB3: 37379 | IC3: 38912 | ID3: 35818 | IE3: 39255 | IF3: 34908 | IG3: 37032 | IH3: 39266 | II3: 39402 | IJ3: 39388 | IK3: 39227 | IL3: 39430 | IM3: 39255 | IN3: 38121 | IO3: 38518 | IP3: 38548 | IQ3: 38904 | IR3: 35986 | IS3: 35977 | IT3: 37440 | IU3: 39206 | IV3: 38168 | IW3: 38569 | IX3: 37106 | IY3: 38926 | IZ3: 37939 | JA3: 38532 | JB3: 39311 | JC3: 37756 | JD3: 38856 | JE3: 38133 | JF3: 37811 | JG3: 37960 | JH3: 36707 | JI3: 38841 | JJ3: 36670 | JK3: 37498 | JL3: 37392 | JM3: 37295 | JN3: 36299 | JO3: 38491 | JP3: 37930 | JQ3: 37302 | JR3: 39260 | JS3: 38154 | JT3: 38478 | JU3: 38513 | JV3: 38346 | JW3: 37250 | JX3: 38183 | JY3: 37441 | JZ3: 33466 | KA3: 38212 | KB3: 39402 | KC3: 39059 | KD3: 36651 | KE3: 34530 | KF3: 37610 | KG3: 37274 | KH3: 39304 | KI3: 37106 | KJ3: 35613 | KK3: 38996 | KL3: 34929 | KM3: 38604 | KN3: 38191 | KO3: 34180 | KP3: 36903 | KQ3: 38387 | KR3: 38989 | KS3: 37764 | KT3: 35207 | KU3: 35923 | KV3: 37449 | KW3: 37246 | KX3: 38982 | KY3: 38709 | KZ3: 35248 | LA3: 36756 | LB3: 37743 | LC3: 35223 | LD3: 38401 | LE3: 36889 | LF3: 38975 | LG3: 39288 | LH3: 34843 | LI3: 38730 | LJ3: 38219 | LK3: 39220 | LL3: 38126 | LM3: 32729 | LN3: 36140 | LO3: 32316 | LP3: 36483 | LQ3: 37477 | LR3: 33058 | LS3: 35398 | LT3: 34880 | LU3: 36000 | LV3: 36448 | LW3: 36322 | LX3: 33025 | LY3: 34145 | LZ3: 34549 | MA3: 38975 | MB3: 35951 | MC3: 35657 | MD3: 37421 | ME3: 38079 | MF3: 38065 | MG3: 37904 | MH3: 39164 | MI3: 37624 | MJ3: 28834 | MK3: 34831 | ML3: 39043 | MM3: 38098 | MN3: 36155 | MO3: 37911 | MP3: 33746 | MQ3: 36672 | MR3: 38100 | MS3: 37337 | MT3: 39010 | MU3: 35118 | MV3: 33403 | MW3: 37029 | MX3: 37659 | MY3: 32652 | MZ3: 35391 | NA3: 36028 | NB3: 33760 | NC3: 34187 | ND3: 39010 | NE3: 33872 | NF3: 39059 | NG3: 38548 | NH3: 33018 | NI3: 32834 | NJ3: 38443 | NK3: 38632 | NL3: 34656 | NM3: 30596 | NN3: 29196 | NO3: 36133 | NP3: 33830 | NQ3: 30461 | NR3: 38618 | NS3: 34992 | NT3: 39346 | NU3: 38366 | NV3: 34964 | NW3: 32934 | NX3: 30840 | NY3: 32668 | NZ3: 30825 | OA3: 30127 | OB3: 32339 | OC3: 30473 | OD3: 33578 | OE3: 32094 | OF3: 37848 | OG3: 33270 | OH3: 36784 | OI3: 33135 | OJ3: 38072 | OK3: 31931 | OL3: 34318 | OM3: 38240 | ON3: 30659 | OO3: 31742 | OP3: 28111 | OQ3: 29362 | OR3: 37596 | OS3: 35083 | OT3: 29749 | OU3: 31231 | OV3: 33165 | OW3: 30834 | OX3: 29539 | OY3: 31611 | OZ3: 26898 | PA3: 38205 | PB3: 36411 | PC3: 31842 | PD3: 32696 | PE3: 38695 | PF3: 37792 | PG3: 36490 | PH3: 32486 | PI3: 39060 | PJ3: 30106 | PK3: 28270 | PL3: 30113 | PM3: 24635 | PN3: 29000 | PO3: 34621 | PP3: 35132 | PQ3: 38632 | PR3: 31224 | PS3: 30981 | PT3: 20745 | PU3: 34936 | PV3: 36774 | PW3: 23637 | PX3: 33900 | PY3: 12151 | PZ3: 38240 | QA3: 39590 | QB3: 41817 | QC3: 41852 | QD3: 41787 | QE3: 41781 | QF3: 41733 | QG3: 41953 | QH3: 41739 | QI3: 41831 | QJ3: 41950 | QK3: 41605 | QL3: 41397 | QM3: 41458 | QN3: 41589 | QO3: 41401 | QP3: 41446 | QQ3: 41551 | QR3: 41439 | QS3: 41569 | QT3: 41033 | QU3: 41110 | QV3: 41087 | QW3: 41229 | QX3: 41093 | QY3: 41068 | QZ3: 40991 | RA3: 41054 | RB3: 40723 | RC3: 40683 | RD3: 40865 | RE3: 40893 | RF3: 40689 | RG3: 40662 | RH3: 40689 | RI3: 40753 | RJ3: 40718 | RK3: 40347 | RL3: 40375 | RM3: 40319 | RN3: 40359 | RO3: 40305 | RP3: 40506 | RQ3: 40368 | RR3: 40263 | RS3: 40164 | RT3: 39995 | RU3: 39983 | RV3: 40130 | RW3: 39962 | RX3: 40137 | RY3: 39948 | RZ3: 39969 | SA3: 39653 | SB3: 39605 | SC3: 39631 | SD3: 39759 | SE3: 39570 | SF3: 39626 | SG3: 39437 | SH3: 39736 | SI3: 38807 | SJ3: 39073 | SK3: 38877 | SL3: 38499 | SM3: 38394 | SN3: 38296 | SO3: 38343 | SP3: 38261 | SQ3: 37771 | SR3: 37804 | SS3: 37820 | ST3: 37470 | SU3: 37330 | SV3: 37015 | SW3: 37090 | SX3: 36931 | SY3: 36875 | SZ3: 36665 | TA3: 36847 | TB3: 36805 | TC3: 36728 | TD3: 36488 | TE3: 36327 | TF3: 36287 | TG3: 36322 | TH3: 35935 | TI3: 35991 | TJ3: 36124 | TK3: 35965 | TL3: 35972 | TM3: 35573 | TN3: 35636 | TO3: 35510 | TP3: 35601 | TQ3: 35202 | TR3: 35237 | TS3: 35396 | TT3: 35377 | TU3: 35244 | TV3: 35412 | TW3: 35237 | TX3: 35025 | TY3: 34873 | TZ3: 34866 | UA3: 34845 | UB3: 35048 | UC3: 34500 | UD3: 34544 | UE3: 34495 | UF3: 34481 | UG3: 34684 | UH3: 35489 | UI3: 34649 | UJ3: 34297 | UK3: 34150 | UL3: 34066 | UM3: 34145 | UN3: 34325 | UO3: 34320 | UP3: 33933 | UQ3: 33933 | UR3: 33928 | US3: 33732 | UT3: 33774 | UU3: 33949 | UV3: 33753 | UW3: 33921 | UX3: 33648 | UY3: 33564 | UZ3: 33583 | VA3: 33283 | VB3: 33592 | VC3: 33564 | VD3: 33555 | VE3: 33450 | VF3: 33396 | VG3: 33067 | VH3: 33193 | VI3: 32955 | VJ3: 32962 | VK3: 32682 | VL3: 32794 | VM3: 32661 | VN3: 32682 | VO3: 32675 | VP3: 32829 | VQ3: 32862 | VR3: 32493 | VS3: 32323 | VT3: 32480 | VU3: 32479 | VV3: 32353 | VW3: 32232 | VX3: 32106 | VY3: 32038 | VZ3: 31917 | WA3: 32134 | WB3: 32129 | WC3: 31877 | WD3: 31994 | WE3: 31940 | WF3: 31548 | WG3: 31765 | WH3: 31583 | WI3: 31758 | WJ3: 31574 | WK3: 31189 | WL3: 31378 | WM3: 31399 | WN3: 31399 | WO3: 31219 | WP3: 31392 | WQ3: 31205 | WR3: 31387 | WS3: 31021 | WT3: 30841 | WU3: 30855 | WV3: 30764 | WW3: 30729 | WX3: 30771 | WY3: 30659 | WZ3: 30421 | XA3: 30477 | XB3: 30470 | XC3: 30659 | XD3: 30512 | XE3: 30302 | XF3: 30176 | XG3: 30099 | XH3: 30293 | XI3: 30106 | XJ3: 30120 | XK3: 29784 | XL3: 29756 | XM3: 29574 | XN3: 29567 | XO3: 29404 | XP3: 29572 | XQ3: 29504 | XR3: 29448 | XS3: 29392 | XT3: 29208 | XU3: 29063 | XV3: 29021 | XW3: 29082 | XX3: 29133 | XY3: 29203 | XZ3: 29006 | YA3: 28657 | YB3: 28699 | YC3: 28844 | YD3: 28657 | YE3: 28734 | YF3: 28832 | YG3: 28272 | YH3: 28445 | YI3: 28473 | YJ3: 28293 | YK3: 28235 | YL3: 28085 | YM3: 27859 | YN3: 27917 | YO3: 28102 | YP3: 28116 | YQ3: 27929 | YR3: 27565 | YS3: 27717 | YT3: 27658 | YU3: 27436 | YV3: 27067 | YW3: 27377 | YX3: 27378 | YY3: 27348 | YZ3: 27375 | ZA3: 27320 | ZB3: 27262 | ZC3: 27024 | ZD3: 27024 | ZE3: 26878 | ZF3: 27014 | ZG3: 26976 | ZH3: 26382 | ZI3: 26645 | ZJ3: 26510 | ZK3: 26342 | ZL3: 26240 | ZM3: 26215 | ZN3: 26290 | ZO3: 25918 | ZP3: 25632 | ZQ3: 25660 | ZR3: 25500 | ZS3: 25348 | ZT3: 25398 | ZU3: 25491 | ZV3: 25196 | ZW3: 24960 | ZX3: 25128 | ZY3: 24931 | ZZ3: 24827 | AAA3: 24763 | AAB3: 24697 | AAC3: 24638 | AAD3: 25112 | AAE3: 24462 | AAF3: 23803 | AAG3: 23916 | AAH3: 23690 | AAI3: 23174 | AAJ3: 23062 | AAK3: 23322 | AAL3: 23370 | AAM3: 23098 | AAN3: 22914 | AAO3: 22958 | AAP3: 23005 | AAQ3: 22572 | AAR3: 22621 | AAS3: 22306 | AAT3: 22196 | AAU3: 22083 | AAV3: 22271 | AAW3: 22213 | AAX3: 22138 | AAY3: 21872 | AAZ3: 21579 | ABA3: 21759 | ABB3: 21638 | ABC3: 21263 | ABD3: 21364 | ABE3: 21314 | ABF3: 21168 | ABG3: 20970 | ABH3: 20733 | ABI3: 20688 | ABJ3: 20634 | ABK3: 20527 | ABL3: 20653 | ABM3: 20373 | ABN3: 20396 | ABO3: 20262 | ABP3: 20081 | ABQ3: 19618 | ABR3: 19576 | ABS3: 19472 | ABT3: 19395 | ABU3: 19555 | ABV3: 19095 | ABW3: 18805 | ABX3: 18889 | ABY3: 18985 | ABZ3: 18809 | ACA3: 18326 | ACB3: 18591 | ACC3: 18400 | ACD3: 18246 | ACE3: 15901 | ACF3: 15671 | ACG3: 14899 | ACH3: 14634 | ACI3: 14594 | ACJ3: 14482 | ACK3: 13870 | ACL3: 13026 | ACM3: 11648 | ACN3: 11366 | ACO3: 11069 | ACP3: 7692 | ACQ3: 42355 | ACR3: 42167 | ACS3: 42097 | ACT3: 42125 | ACU3: 42166 | ACV3: 42174 | ACW3: 42216 | ACX3: 42328 | ACY3: 42279 | ACZ3: 42496 | ADA3: 42538 | ADB3: 42464 | ADC3: 42475 | ADD3: 42454 | ADE3: 42559 | ADF3: 42412 | ADG3: 42587 | ADH3: 42499 | ADI3: 42678 | ADJ3: 36005 | ADK3: 13146 | ADL3: 14014 | ADM3: 13443 | ADN3: 13096 | ADO3: 22313 | ADP3: 15097 | ADQ3: 11436 | ADR3: 17156 | ADS3: 14535 | ADT3: 17289 | ADU3: 17848 | ADV3: 17826 | ADW3: 30862 | ADX3: 36607 | ADY3: 37197 | ADZ3: 37680 | AEA3: 39556 | AEB3: 39661 | AEC3: 40393 | AED3: 41134 | AEE3: 41855 | AEF3: 39607 | AEG3: 41415 | AEH3: 40270 | AEI3: 34201 | AEJ3: 35104 | AEK3: 35608 | AEL3: 37980 | AEM3: 42418 | AEN3: 41614 | AEO3: 40650 | AEP3: 41002 | AEQ3: 39316 | AER3: 41590 | AES3: 42626 | AET3: 38872 | AEU3: 42083 | AEV3: 38371 | AEW3: 41493 | AEX3: 42067 | AEY3: 40975 | AEZ3: 37022 | AFA3: 42252 | AFB3: 41180 | AFC3: 42177 | AFD3: 42116 | AFE3: 41717 | AFF3: 41556 | AFG3: 41292 | AFH3: 39954 | AFI3: 37291 | AFJ3: 36827 | AFK3: 36480 | AFL3: 35601 | AFM3: 35385 | AFN3: 34661 | AFO3: 41124 | AFP3: 40534 | AFQ3: 32308 | AFR3: 31940 | AFS3: 31569 | AFT3: 31324 | AFU3: 38862 | AFV3: 30862 | AFW3: 30026 | AFX3: 40766 | AFY3: 28143 | AFZ3: 40956 | AGA3: 39073 | AGB3: 40688 | AGC3: 36833 | AGD3: 37799 | AGE3: 30825 | AGF3: 39836 | AGG3: 40928 | AGH3: 34635 | AGI3: 33886 | AGJ3: 42281 | AGK3: 26250 | AGL3: 32122 | AGM3: 35774 | AGN3: 37071 | AGO3: 37615 | AGP3: 38156 | AGQ3: 41190 | AGR3: 41078 | AGS3: 42504 | AGT3: 41960 | AGU3: 41413 | AGV3: 38072 | AGW3: 35860 | AGX3: 33137 | AGY3: 39640 | AGZ3: 34593 | AHA3: 42392 | AHB3: 33795 | AHC3: 33459 | AHD3: 33130 | AHE3: 32759 | AHF3: 32605 | AHG3: 32199 | AHH3: 39829 | AHI3: 21179 | AHJ3: 17538 | AHK3: 22012 | AHL3: 33819 | AHM3: 25053 | AHN3: 25113 | AHO3: 25742 | AHP3: 27941 | AHQ3: 31751 | AHR3: 32337 | AHS3: 36739 | AHT3: 39794 | AHU3: 40158 | AHV3: 41954 | AHW3: 42615 | AHX3: 40850 | AHY3: 39745 | AHZ3: 38329 | AIA3: 35860 | AIB3: 34677 | AIC3: 34250 | AID3: 33914 | AIE3: 32045 | AIF3: 29357 | AIG3: 25372 | AIH3: 36098 | AII3: 28669 | AIJ3: 26646 | AIK3: 26296 | AIL3: 22634 | AIM3: 23182 | AIN3: 42558 | AIO3: 41387 | AIP3: 39910 | AIQ3: 31975 | AIR3: 41682 | AIS3: 34626 | AIT3: 34992 | AIU3: 35524 | AIV3: 36301 | AIW3: 40683 | AIX3: 27798 | AIY3: 26939 | AIZ3: 28297 | AJA3: 30303 | AJB3: 31702 | AJC3: 32367 | AJD3: 34229 | AJE3: 42703 | AJF3: 41625 | AJG3: 40228 | AJH3: 37162 | AJI3: 32283 | AJJ3: 40865 | AJK3: 42404 | AJL3: 31030 | AJM3: 42505 | AJN3: 38486 | AJO3: 42541 | AJP3: 42560 | AJQ3: 42562 | AJR3: 42443 | AJS3: 35789 | AJT3: 39953 | AJU3: 41254 | AJV3: 42345 | AJW3: 32556 | AJX3: 33438 | AJY3: 22212 | AJZ3: 42621 | AKA3: 35832 | AKB3: 37169 | AKC3: 37687 | AKD3: 38175 | AKE3: 39164 | AKF3: 41353 | AKG3: 41889 | AKH3: 42170 | AKI3: 42638 | AKJ3: 35412 | AKK3: 37099 | AKL3: 37965 | AKM3: 41040 | AKN3: 39867 | AKO3: 41435 | AKP3: 40627 | AKQ3: 38065 | AKR3: 42659 | AKS3: 41264 | AKT3: 36777 | AKU3: 42688 | AKV3: 37951 | AKW3: 42689 | AKX3: 42714 | AKY3: 42725 | AKZ3: 41880 | ALA3: 41767 | ALB3: 32052 | ALC3: 33431 | ALD3: 42342 | ALE3: 38954 | ALF3: 34985 | ALG3: 37456 | ALH3: 39695 | ALI3: 41262 | ALJ3: 42218 | ALK3: 41059 | ALL3: 31394 | ALM3: 32773 | ALN3: 33382 | ALO3: 33886 | ALP3: 35664 | ALQ3: 37876 | ALR3: 39731 | ALS3: 40310 | ALT3: 41985 | ALU3: 39769 | ALV3: 41341 | ALW3: 40889 | ALX3: 41925 | ALY3: 42354 | ALZ3: 41878 | AMA3: 37981 | AMB3: 41089 | AMC3: 42179 | AMD3: 41789 | AME3: 41291 | AMF3: 39352 | AMG3: 37395 | AMH3: 41153 | AMI3: 41916 | AMJ3: 35713 | AMK3: 33039 | AML3: 38093 | AMM3: 41158 | AMN3: 41516 | AMO3: 41516 | AMP3: 40753 | AMQ3: 40345 | AMR3: 42031 | AMS3: 42143 | AMT3: 41787 | AMU3: 40588 | AMV3: 40205 | AMW3: 39437 | AMX3: 41870 | AMY3: 42184 | AMZ3: 39316 | ANA3: 41471 | ANB3: 37589 | ANC3: 41084 | AND3: 34285 | ANE3: 35062 | ANF3: 33879 | ANG3: 32367 | ANH3: 33086 | ANI3: 31989 | ANJ3: 33095 | ANK3: 40984 | ANL3: 40074 | ANM3: 20802 | ANN3: 39297 | ANO3: 41544 | ANP3: 41677 | ANQ3: 34796 | ANR3: 41803 | ANS3: 42573 | ANT3: 28432 | ANU3: 42594 | ANV3: 24343 | ANW3: 19514 | ANX3: 31373 | ANY3: 20783 | ANZ3: 20389 | AOA3: 17482 | AOB3: 19031 | AOC3: 19933 | AOD3: 21627 | AOE3: 23841 | AOF3: 18854 | AOG3: 15573 | AOH3: 18253 | AOI3: 31401 | AOJ3: 34159
A4: Run Time | B4: 108 | C4: 112 | D4: 98 | E4: 93 | F4: 96 | G4: 107 | H4: 120 | I4: 130 | J4: 95 | K4: 98 | L4: 99 | M4: 120 | N4: 119 | O4: 94 | P4: 122 | Q4: 125 | R4: 146 | S4: 142 | T4: 90 | U4: 127 | V4: 110 | W4: 123 | X4: 98 | Y4: 102 | Z4: 92 | AA4: 88 | AB4: 86 | AC4: 106 | AD4: 90 | AE4: 92 | AF4: 155 | AG4: 104 | AH4: 117 | AI4: 155 | AJ4: 149 | AK4: 137 | AL4: 110 | AM4: 93 | AN4: 106 | AO4: 110 | AP4: 108 | AQ4: 100 | AR4: 85 | AS4: 102 | AT4: 95 | AU4: 104 | AV4: 127 | AW4: 116 | AX4: 153 | AY4: 128 | AZ4: 108 | BA4: 109 | BB4: 105 | BC4: 90 | BD4: 98 | BE4: 101 | BF4: 150 | BG4: 177 | BH4: 99 | BI4: 132 | BJ4: 165 | BK4: 207 | BL4: 180 | BM4: 162 | BN4: 144 | BO4: 88 | BP4: 128 | BQ4: 125 | BR4: 113 | BS4: 137 | BT4: 129 | BU4: 96 | BV4: 97 | BW4: 89 | BX4: 187 | BY4: 178 | BZ4: 201 | CA4: 179 | CB4: 102 | CC4: 174 | CD4: 161 | CE4: 169 | CF4: 122 | CG4: 114 | CH4: 131 | CI4: 96 | CJ4: 112 | CK4: 153 | CL4: 147 | CM4: 96 | CN4: 108 | CO4: 98 | CP4: 110 | CQ4: 103 | CR4: 138 | CS4: 156 | CT4: 133 | CU4: 128 | CV4: 141 | CW4: 152 | CX4: 119 | CY4: 144 | CZ4: 155 | DA4: 130 | DB4: 133 | DC4: 131 | DD4: 126 | DE4: 127 | DF4: 188 | DG4: 84 | DH4: 121 | DI4: 136 | DJ4: 113 | DK4: 115 | DL4: 93 | DM4: 125 | DN4: 131 | DO4: 130 | DP4: 140 | DQ4: 120 | DR4: 121 | DS4: 125 | DT4: 99 | DU4: 117 | DV4: 115 | DW4: 109 | DX4: 107 | DY4: 85 | DZ4: 143 | EA4: 130 | EB4: 108 | EC4: 146 | ED4: 153 | EE4: 128 | EF4: 109 | EG4: 106 | EH4: 150 | EI4: 145 | EJ4: 124 | EK4: 123 | EL4: 91 | EM4: 127 | EN4: 124 | EO4: 113 | EP4: 98 | EQ4: 176 | ER4: 100 | ES4: 114 | ET4: 136 | EU4: 117 | EV4: 142 | EW4: 138 | EX4: 153 | EY4: 193 | EZ4: 87 | FA4: 222 | FB4: 158 | FC4: 161 | FD4: 106 | FE4: 119 | FF4: 114 | FG4: 148 | FH4: 152 | FI4: 86 | FJ4: 139 | FK4: 86 | FL4: 94 | FM4: 113 | FN4: 155 | FO4: 92 | FP4: 93 | FQ4: 118 | FR4: 102 | FS4: 90 | FT4: 92 | FU4: 93 | FV4: 95 | FW4: 91 | FX4: 119 | FY4: 120 | FZ4: 124 | GA4: 122 | GB4: 121 | GC4: 92 | GD4: 103 | GE4: 100 | GF4: 93 | GG4: 101 | GH4: 129 | GI4: 117 | GJ4: 127 | GK4: 105 | GL4: 121 | GM4: 106 | GN4: 109 | GO4: 116 | GP4: 159 | GQ4: 146 | GR4: 94 | GS4: 131 | GT4: 114 | GU4: 155 | GV4: 133 | GW4: 139 | GX4: 92 | GY4: 126 | GZ4: 101 | HA4: 112 | HB4: 133 | HC4: 108 | HD4: 130 | HE4: 121 | HF4: 162 | HG4: 106 | HH4: 102 | HI4: 114 | HJ4: 129 | HK4: 118 | HL4: 123 | HM4: 94 | HN4: 119 | HO4: 115 | HP4: 146 | HQ4: 158 | HR4: 119 | HS4: 101 | HT4: 122 | HU4: 114 | HV4: 123 | HW4: 97 | HX4: 101 | HY4: 100 | HZ4: 125 | IA4: 126 | IB4: 121 | IC4: 154 | ID4: 194 | IE4: 96 | IF4: 135 | IG4: 183 | IH4: 144 | II4: 115 | IJ4: 91 | IK4: 168 | IL4: 100 | IM4: 111 | IN4: 162 | IO4: 141 | IP4: 115 | IQ4: 151 | IR4: 127 | IS4: 151 | IT4: 89 | IU4: 139 | IV4: 127 | IW4: 121 | IX4: 106 | IY4: 134 | IZ4: 138 | JA4: 116 | JB4: 115 | JC4: 138 | JD4: 146 | JE4: 124 | JF4: 135 | JG4: 154 | JH4: 130 | JI4: 125 | JJ4: 123 | JK4: 134 | JL4: 142 | JM4: 92 | JN4: 133 | JO4: 140 | JP4: 129 | JQ4: 117 | JR4: 130 | JS4: 120 | JT4: 144 | JU4: 120 | JV4: 170 | JW4: 157 | JX4: 115 | JY4: 145 | JZ4: 136 | KA4: 104 | KB4: 158 | KC4: 143 | KD4: 155 | KE4: 141 | KF4: 160 | KG4: 144 | KH4: 91 | KI4: 90 | KJ4: 98 | KK4: 151 | KL4: 131 | KM4: 144 | KN4: 108 | KO4: 130 | KP4: 143 | KQ4: 125 | KR4: 107 | KS4: 101 | KT4: 110 | KU4: 121 | KV4: 117 | KW4: 135 | KX4: 109 | KY4: 163 | KZ4: 145 | LA4: 104 | LB4: 134 | LC4: 136 | LD4: 121 | LE4: 106 | LF4: 108 | LG4: 87 | LH4: 177 | LI4: 125 | LJ4: 108 | LK4: 93 | LL4: 93 | LM4: 140 | LN4: 103 | LO4: 103 | LP4: 105 | LQ4: 124 | LR4: 124 | LS4: 120 | LT4: 140 | LU4: 170 | LV4: 139 | LW4: 136 | LX4: 113 | LY4: 113 | LZ4: 141 | MA4: 122 | MB4: 103 | MC4: 96 | MD4: 118 | ME4: 122 | MF4: 101 | MG4: 100 | MH4: 117 | MI4: 116 | MJ4: 143 | MK4: 116 | ML4: 126 | MM4: 146 | MN4: 132 | MO4: 111 | MP4: 115 | MQ4: 110 | MR4: 136 | MS4: 116 | MT4: 132 | MU4: 178 | MV4: 155 | MW4: 90 | MX4: 114 | MY4: 127 | MZ4: 111 | NA4: 120 | NB4: 117 | NC4: 130 | ND4: 130 | NE4: 112 | NF4: 138 | NG4: 119 | NH4: 118 | NI4: 108 | NJ4: 124 | NK4: 119 | NL4: 118 | NM4: 134 | NN4: 132 | NO4: 97 | NP4: 118 | NQ4: 132 | NR4: 96 | NS4: 105 | NT4: 159 | NU4: 132 | NV4: 127 | NW4: 134 | NX4: 107 | NY4: 106 | NZ4: 118 | OA4: 116 | OB4: 132 | OC4: 131 | OD4: 113 | OE4: 101 | OF4: 139 | OG4: 111 | OH4: 107 | OI4: 146 | OJ4: 126 | OK4: 119 | OL4: 197 | OM4: 95 | ON4: 170 | OO4: 122 | OP4: 134 | OQ4: 124 | OR4: 107 | OS4: 108 | OT4: 115 | OU4: 116 | OV4: 180 | OW4: 105 | OX4: 129 | OY4: 137 | OZ4: 105 | PA4: 120 | PB4: 122 | PC4: 110 | PD4: 114 | PE4: 134 | PF4: 138 | PG4: 138 | PH4: 105 | PI4: 141 | PJ4: 113 | PK4: 121 | PL4: 115 | PM4: 117 | PN4: 117 | PO4: 154 | PP4: 98 | PQ4: 93 | PR4: 116 | PS4: 108 | PT4: 183 | PU4: 106 | PV4: 113 | PW4: 110 | PX4: 99 | PY4: 100 | PZ4: 98 | QA4: 122 | QB4: 165 | QC4: 122 | QD4: 98 | QE4: 131 | QF4: 136 | QG4: 123 | QH4: 141 | QI4: 130 | QJ4: 169 | QK4: 102 | QL4: 130 | QM4: 98 | QN4: 146 | QO4: 130 | QP4: 104 | QQ4: 91 | QR4: 143 | QS4: 112 | QT4: 143 | QU4: 165 | QV4: 88 | QW4: 115 | QX4: 136 | QY4: 93 | QZ4: 142 | RA4: 106 | RB4: 157 | RC4: 137 | RD4: 117 | RE4: 133 | RF4: 90 | RG4: 130 | RH4: 102 | RI4: 103 | RJ4: 106 | RK4: 103 | RL4: 148 | RM4: 93 | RN4: 123 | RO4: 125 | RP4: 100 | RQ4: 95 | RR4: 98 | RS4: 161 | RT4: 94 | RU4: 150 | RV4: 158 | RW4: 96 | RX4: 130 | RY4: 138 | RZ4: 100 | SA4: 152 | SB4: 92 | SC4: 92 | SD4: 89 | SE4: 126 | SF4: 98 | SG4: 124 | SH4: 122 | SI4: 91 | SJ4: 108 | SK4: 116 | SL4: 86 | SM4: 118 | SN4: 115 | SO4: 115 | SP4: 90 | SQ4: 100 | SR4: 109 | SS4: 147 | ST4: 107 | SU4: 81 | SV4: 130 | SW4: 92 | SX4: 132 | SY4: 127 | SZ4: 82 | TA4: 104 | TB4: 108 | TC4: 130 | TD4: 95 | TE4: 88 | TF4: 125 | TG4: 96 | TH4: 139 | TI4: 119 | TJ4: 95 | TK4: 87 | TL4: 85 | TM4: 129 | TN4: 124 | TO4: 88 | TP4: 104 | TQ4: 113 | TR4: 91 | TS4: 103 | TT4: 121 | TU4: 95 | TV4: 139 | TW4: 114 | TX4: 81 | TY4: 82 | TZ4: 122 | UA4: 101 | UB4: 104 | UC4: 88 | UD4: 101 | UE4: 115 | UF4: 91 | UG4: 107 | UH4: 126 | UI4: 122 | UJ4: 125 | UK4: 154 | UL4: 118 | UM4: 105 | UN4: 126 | UO4: 141 | UP4: 90 | UQ4: 129 | UR4: 120 | US4: 128 | UT4: 126 | UU4: 138 | UV4: 100 | UW4: 128 | UX4: 95 | UY4: 84 | UZ4: 144 | VA4: 118 | VB4: 188 | VC4: 99 | VD4: 128 | VE4: 84 | VF4: 112 | VG4: 127 | VH4: 102 | VI4: 119 | VJ4: 93 | VK4: 126 | VL4: 96 | VM4: 128 | VN4: 94 | VO4: 108 | VP4: 82 | VQ4: 145 | VR4: 133 | VS4: 117 | VT4: 104 | VU4: 85 | VV4: 103 | VW4: 92 | VX4: 104 | VY4: 119 | VZ4: 103 | WA4: 120 | WB4: 102 | WC4: 111 | WD4: 117 | WE4: 118 | WF4: 110 | WG4: 120 | WH4: 113 | WI4: 94 | WJ4: 103 | WK4: 96 | WL4: 91 | WM4: 153 | WN4: 161 | WO4: 117 | WP4: 107 | WQ4: 114 | WR4: 102 | WS4: 105 | WT4: 106 | WU4: 127 | WV4: 96 | WW4: 110 | WX4: 106 | WY4: 132 | WZ4: 98 | XA4: 116 | XB4: 114 | XC4: 117 | XD4: 93 | XE4: 116 | XF4: 122 | XG4: 100 | XH4: 96 | XI4: 114 | XJ4: 128 | XK4: 97 | XL4: 95 | XM4: 110 | XN4: 111 | XO4: 87 | XP4: 116 | XQ4: 109 | XR4: 100 | XS4: 132 | XT4: 105 | XU4: 118 | XV4: 119 | XW4: 153 | XX4: 122 | XY4: 94 | XZ4: 97 | YA4: 110 | YB4: 109 | YC4: 114 | YD4: 116 | YE4: 127 | YF4: 183 | YG4: 96 | YH4: 135 | YI4: 118 | YJ4: 124 | YK4: 93 | YL4: 119 | YM4: 138 | YN4: 111 | YO4: 114 | YP4: 96 | YQ4: 131 | YR4: 124 | YS4: 133 | YT4: 125 | YU4: 110 | YV4: 92 | YW4: 165 | YX4: 105 | YY4: 121 | YZ4: 202 | ZA4: 106 | ZB4: 121 | ZC4: 129 | ZD4: 121 | ZE4: 112 | ZF4: 150 | ZG4: 83 | ZH4: 177 | ZI4: 117 | ZJ4: 110 | ZK4: 124 | ZL4: 179 | ZM4: 104 | ZN4: 102 | ZO4: 100 | ZP4: 137 | ZQ4: 170 | ZR4: 110 | ZS4: 113 | ZT4: 95 | ZU4: 154 | ZV4: 108 | ZW4: 105 | ZX4: 113 | ZY4: 112 | ZZ4: 105 | AAA4: 78 | AAB4: 111 | AAC4: 150 | AAD4: 96 | AAE4: 179 | AAF4: 174 | AAG4: 117 | AAH4: 170 | AAI4: 248 | AAJ4: 164 | AAK4: 210 | AAL4: 79 | AAM4: 119 | AAN4: 178 | AAO4: 185 | AAP4: 129 | AAQ4: 152 | AAR4: 184 | AAS4: 79 | AAT4: 184 | AAU4: 109 | AAV4: 126 | AAW4: 167 | AAX4: 127 | AAY4: 212 | AAZ4: 75 | ABA4: 136 | ABB4: 121 | ABC4: 171 | ABD4: 116 | ABE4: 128 | ABF4: 152 | ABG4: 122 | ABH4: 220 | ABI4: 208 | ABJ4: 133 | ABK4: 119 | ABL4: 111 | ABM4: 145 | ABN4: 150 | ABO4: 75 | ABP4: 127 | ABQ4: 135 | ABR4: 118 | ABS4: 118 | ABT4: 76 | ABU4: 91 | ABV4: 103 | ABW4: 75 | ABX4: 122 | ABY4: 105 | ABZ4: 101 | ACA4: 75 | ACB4: 103 | ACC4: 107 | ACD4: 100 | ACE4: 170 | ACF4: 102 | ACG4: 124 | ACH4: 129 | ACI4: 221 | ACJ4: 101 | ACK4: 83 | ACL4: 95 | ACM4: 71 | ACN4: 85 | ACO4: 152 | ACP4: 68 | ACQ4: 136 | ACR4: 124 | ACS4: 137 | ACT4: 141 | ACU4: 91 | ACV4: 94 | ACW4: 131 | ACX4: 137 | ACY4: 141 | ACZ4: 147 | ADA4: 97 | ADB4: 108 | ADC4: 105 | ADD4: 151 | ADE4: 87 | ADF4: 108 | ADG4: 123 | ADH4: 144 | ADI4: 115 | ADJ4: 128 | ADK4: 119 | ADL4: 102 | ADM4: 115 | ADN4: 132 | ADO4: 125 | ADP4: 119 | ADQ4: 83 | ADR4: 130 | ADS4: 129 | ADT4: 96 | ADU4: 145 | ADV4: 125 | ADW4: 108 | ADX4: 115 | ADY4: 87 | ADZ4: 101 | AEA4: 104 | AEB4: 111 | AEC4: 103 | AED4: 103 | AEE4: 126 | AEF4: 112 | AEG4: 115 | AEH4: 106 | AEI4: 97 | AEJ4: 108 | AEK4: 139 | AEL4: 119 | AEM4: 105 | AEN4: 127 | AEO4: 114 | AEP4: 131 | AEQ4: 109 | AER4: 121 | AES4: 107 | AET4: 104 | AEU4: 115 | AEV4: 109 | AEW4: 109 | AEX4: 120 | AEY4: 132 | AEZ4: 132 | AFA4: 122 | AFB4: 127 | AFC4: 126 | AFD4: 95 | AFE4: 109 | AFF4: 115 | AFG4: 107 | AFH4: 115 | AFI4: 108 | AFJ4: 124 | AFK4: 123 | AFL4: 125 | AFM4: 89 | AFN4: 109 | AFO4: 118 | AFP4: 110 | AFQ4: 103 | AFR4: 107 | AFS4: 107 | AFT4: 90 | AFU4: 104 | AFV4: 101 | AFW4: 129 | AFX4: 113 | AFY4: 85 | AFZ4: 97 | AGA4: 131 | AGB4: 132 | AGC4: 98 | AGD4: 106 | AGE4: 229 | AGF4: 92 | AGG4: 89 | AGH4: 128 | AGI4: 103 | AGJ4: 141 | AGK4: 89 | AGL4: 154 | AGM4: 154 | AGN4: 146 | AGO4: 141 | AGP4: 128 | AGQ4: 150 | AGR4: 105 | AGS4: 117 | AGT4: 137 | AGU4: 105 | AGV4: 104 | AGW4: 117 | AGX4: 115 | AGY4: 115 | AGZ4: 98 | AHA4: 95 | AHB4: 102 | AHC4: 107 | AHD4: 89 | AHE4: 103 | AHF4: 82 | AHG4: 92 | AHH4: 132 | AHI4: 88 | AHJ4: 126 | AHK4: 125 | AHL4: 131 | AHM4: 114 | AHN4: 93 | AHO4: 146 | AHP4: 135 | AHQ4: 130 | AHR4: 91 | AHS4: 130 | AHT4: 116 | AHU4: 133 | AHV4: 132 | AHW4: 96 | AHX4: 137 | AHY4: 141 | AHZ4: 113 | AIA4: 131 | AIB4: 101 | AIC4: 115 | AID4: 84 | AIE4: 98 | AIF4: 99 | AIG4: 143 | AIH4: 119 | AII4: 112 | AIJ4: 122 | AIK4: 117 | AIL4: 179 | AIM4: 172 | AIN4: 122 | AIO4: 133 | AIP4: 127 | AIQ4: 101 | AIR4: 118 | AIS4: 92 | AIT4: 94 | AIU4: 113 | AIV4: 128 | AIW4: 100 | AIX4: 113 | AIY4: 112 | AIZ4: 163 | AJA4: 109 | AJB4: 120 | AJC4: 162 | AJD4: 139 | AJE4: 159 | AJF4: 179 | AJG4: 138 | AJH4: 89 | AJI4: 126 | AJJ4: 100 | AJK4: 102 | AJL4: 136 | AJM4: 116 | AJN4: 103 | AJO4: 120 | AJP4: 116 | AJQ4: 123 | AJR4: 88 | AJS4: 154 | AJT4: 153 | AJU4: 165 | AJV4: 168 | AJW4: 89 | AJX4: 93 | AJY4: 128 | AJZ4: 133 | AKA4: 87 | AKB4: 122 | AKC4: 121 | AKD4: 142 | AKE4: 125 | AKF4: 119 | AKG4: 132 | AKH4: 123 | AKI4: 127 | AKJ4: 106 | AKK4: 120 | AKL4: 125 | AKM4: 113 | AKN4: 163 | AKO4: 143 | AKP4: 109 | AKQ4: 100 | AKR4: 118 | AKS4: 130 | AKT4: 119 | AKU4: 107 | AKV4: 91 | AKW4: 92 | AKX4: 133 | AKY4: 116 | AKZ4: 114 | ALA4: 123 | ALB4: 95 | ALC4: 122 | ALD4: 114 | ALE4: 104 | ALF4: 145 | ALG4: 138 | ALH4: 131 | ALI4: 157 | ALJ4: 116 | ALK4: 124 | ALL4: 125 | ALM4: 125 | ALN4: 129 | ALO4: 142 | ALP4: 124 | ALQ4: 116 | ALR4: 128 | ALS4: 140 | ALT4: 150 | ALU4: 121 | ALV4: 117 | ALW4: 158 | ALX4: 101 | ALY4: 156 | ALZ4: 119 | AMA4: 124 | AMB4: 106 | AMC4: 115 | AMD4: 116 | AME4: 88 | AMF4: 158 | AMG4: 95 | AMH4: 137 | AMI4: 149 | AMJ4: 155 | AMK4: 106 | AML4: 123 | AMM4: 118 | AMN4: 134 | AMO4: 153 | AMP4: 118 | AMQ4: 110 | AMR4: 127 | AMS4: 121 | AMT4: 113 | AMU4: 106 | AMV4: 103 | AMW4: 100 | AMX4: 102 | AMY4: 117 | AMZ4: 122 | ANA4: 126 | ANB4: 98 | ANC4: 110 | AND4: 105 | ANE4: 143 | ANF4: 101 | ANG4: 103 | ANH4: 104 | ANI4: 98 | ANJ4: 115 | ANK4: 109 | ANL4: 90 | ANM4: 105 | ANN4: 88 | ANO4: 95 | ANP4: 100 | ANQ4: 119 | ANR4: 112 | ANS4: 94 | ANT4: 134 | ANU4: 102 | ANV4: 100 | ANW4: 121 | ANX4: 100 | ANY4: 201 | ANZ4: 111 | AOA4: 118 | AOB4: 113 | AOC4: 108 | AOD4: 180 | AOE4: 260 | AOF4: 122 | AOG4: 118 | AOH4: 128 | AOI4: 108 | AOJ4: 128
A5: Genre | B5: Animation | C5: Adventure | D5: Comedy | E5: Action | F5: Action | G5: Action | H5: Action | I5: Crime | J5: Comedy | K5: Comedy | L5: Martial Arts | M5: Martial Arts | N5: Martial Arts | O5: Fantasy | P5: Adventure | Q5: Martial Arts | R5: War | S5: War | T5: Thriller | U5: Science Fiction | V5: Thriller | W5: Comedy | X5: Action | Y5: Martial Arts | Z5: Action | AA5: Action | AB5: Action | AC5: Action | AD5: Thriller | AE5: Thriller | AF5: Crime | AG5: Adventure | AH5: Thriller | AI5: War | AJ5: War | AK5: Drama | AL5: Crime | AM5: Fantasy | AN5: Martial Arts | AO5: Martial Arts | AP5: Martial Arts | AQ5: Martial Arts | AR5: Martial Arts | AS5: Martial Arts | AT5: Martial Arts | AU5: Martial Arts | AV5: War | AW5: Martial Arts | AX5: Martial Arts | AY5: Action | AZ5: Martial Arts | BA5: Martial Arts | BB5: Martial Arts | BC5: Martial Arts | BD5: Martial Arts | BE5: Martial Arts | BF5: Martial Arts | BG5: Western | BH5: Western | BI5: Western | BJ5: Western | BK5: Action | BL5: Drama | BM5: Drama | BN5: War | BO5: Drama | BP5: Crime | BQ5: Action | BR5: Action | BS5: Drama | BT5: Drama | BU5: Action | BV5: Action | BW5: Fantasy | BX5: Adventure | BY5: Fantasy | BZ5: Fantasy | CA5: Fantasy | CB5: Drama | CC5: Fantasy | CD5: Fantasy | CE5: Fantasy | CF5: Crime | CG5: Fantasy | CH5: Fantasy | CI5: Thriller | CJ5: Science Fiction | CK5: Thriller | CL5: Thriller | CM5: Drama | CN5: Martial Arts | CO5: Martial Arts | CP5: Martial Arts | CQ5: Martial Arts | CR5: Fantasy | CS5: Fantasy | CT5: Thriller | CU5: Thriller | CV5: Fantasy | CW5: Fantasy | CX5: Thriller | CY5: Thriller | CZ5: Fantasy | DA5: Thriller | DB5: Thriller | DC5: Thriller | DD5: Thriller | DE5: Thriller | DF5: Biography | DG5: Comedy | DH5: Comedy | DI5: Romance | DJ5: Horror | DK5: Drama | DL5: Drama | DM5: Thriller | DN5: Thriller | DO5: Thriller | DP5: Thriller | DQ5: Thriller | DR5: Thriller | DS5: Thriller | DT5: Comedy | DU5: Romance | DV5: Thriller | DW5: Thriller | DX5: Science Fiction | DY5: Animation | DZ5: Thriller | EA5: Fantasy | EB5: Fantasy | EC5: Fantasy | ED5: Fantasy | EE5: Mystery | EF5: Musical | EG5: Thriller | EH5: Fantasy | EI5: Fantasy | EJ5: Romantic Comedy | EK5: Romantic Comedy | EL5: Comedy | EM5: Action | EN5: Sport | EO5: Fantasy | EP5: Comedy | EQ5: War | ER5: Musical | ES5: Comedy | ET5: Drama | EU5: Adventure | EV5: Science Fiction | EW5: Romance | EX5: Musical | EY5: Romance | EZ5: Musical | FA5: Biography | FB5: War | FC5: War | FD5: Adventure | FE5: Drama | FF5: Drama | FG5: Thriller | FH5: Drama | FI5: Thriller | FJ5: Drama | FK5: Romance | FL5: Crime | FM5: Drama | FN5: Drama | FO5: Comedy | FP5: Comedy | FQ5: Adventure | FR5: Drama | FS5: Thriller | FT5: Comedy | FU5: Crime | FV5: Thriller | FW5: Thriller | FX5: Science Fiction | FY5: Drama | FZ5: Comedy | GA5: Comedy | GB5: History | GC5: Crime | GD5: Comedy | GE5: Horror | GF5: Biography | GG5: Crime | GH5: Action | GI5: Action | GJ5: Fantasy | GK5: Crime | GL5: Action | GM5: Action | GN5: Science Fiction | GO5: War | GP5: Drama | GQ5: Horror | GR5: Comedy | GS5: Crime | GT5: Science Fiction | GU5: War | GV5: War | GW5: History | GX5: Crime | GY5: Adventure | GZ5: Fantasy | HA5: Comedy | HB5: Fantasy | HC5: Science Fiction | HD5: Romance | HE5: Romance | HF5: Romance | HG5: Crime | HH5: Crime | HI5: Crime | HJ5: Action | HK5: Thriller | HL5: Biography | HM5: Documentary | HN5: Biography | HO5: Drama | HP5: Biography | HQ5: Musical | HR5: Biography | HS5: Drama | HT5: Sport | HU5: Adventure | HV5: Drama | HW5: Adventure | HX5: Fantasy | HY5: Adventure | HZ5: Action | IA5: Adventure | IB5: Action | IC5: Action | ID5: Romance | IE5: Comedy | IF5: Adventure | IG5: War | IH5: Science Fiction | II5: Fantasy | IJ5: Animation | IK5: Adventure | IL5: Horror | IM5: Animation | IN5: Adventure | IO5: Action | IP5: Fantasy | IQ5: Adventure | IR5: Action | IS5: Science Fiction | IT5: Science Fiction | IU5: Action | IV5: Action | IW5: Action | IX5: Animation | IY5: Thriller | IZ5: Adventure | JA5: Science Fiction | JB5: Thriller | JC5: Science Fiction | JD5: Mystery | JE5: Thriller | JF5: Adventure | JG5: Adventure | JH5: Adventure | JI5: Thriller | JJ5: Thriller | JK5: War | JL5: Science Fiction | JM5: Animation | JN5: Science Fiction | JO5: Science Fiction | JP5: Science Fiction | JQ5: Crime | JR5: Action | JS5: Adventure | JT5: Adventure | JU5: Action | JV5: Biography | JW5: Biography | JX5: Science Fiction | JY5: Science Fiction | JZ5: Science Fiction | KA5: Action | KB5: Biography | KC5: Adventure | KD5: Adventure | KE5: Thriller | KF5: Drama | KG5: War | KH5: Martial Arts | KI5: Martial Arts | KJ5: Science Fiction | KK5: Thriller | KL5: Action | KM5: Drama | KN5: Thriller | KO5: Action | KP5: Drama | KQ5: Crime | KR5: Comedy | KS5: Comedy | KT5: Thriller | KU5: Science Fiction | KV5: Crime | KW5: Drama | KX5: Science Fiction | KY5: Drama | KZ5: Science Fiction | LA5: Action | LB5: Action | LC5: Thriller | LD5: Thriller | LE5: Drama | LF5: Comedy | LG5: Animation | LH5: History | LI5: War | LJ5: Thriller | LK5: Animation | LL5: Animation | LM5: Science Fiction | LN5: Science Fiction | LO5: Comedy | LP5: Horror | LQ5: Action | LR5: Action | LS5: Action | LT5: History | LU5: War | LV5: Thriller | LW5: Science Fiction | LX5: Science Fiction | LY5: Action | LZ5: Thriller | MA5: Crime | MB5: Drama | MC5: Science Fiction | MD5: Thriller | ME5: Action | MF5: Comedy | MG5: Comedy | MH5: Adventure | MI5: Science Fiction | MJ5: Adventure | MK5: Thriller | ML5: Thriller | MM5: Thriller | MN5: Thriller | MO5: Martial Arts | MP5: Science Fiction | MQ5: Martial Arts | MR5: Martial Arts | MS5: Action | MT5: War | MU5: Crime | MV5: Adventure | MW5: Animation | MX5: Martial Arts | MY5: Adventure | MZ5: Science Fiction | NA5: Fantasy | NB5: Thriller | NC5: Thriller | ND5: Mystery | NE5: Adventure | NF5: Adventure | NG5: Comedy | NH5: Science Fiction | NI5: Science Fiction | NJ5: Crime | NK5: Science Fiction | NL5: Science Fiction | NM5: Thriller | NN5: Science Fiction | NO5: Action | NP5: Action | NQ5: Science Fiction | NR5: Drama | NS5: Crime | NT5: Western | NU5: Sport | NV5: Thriller | NW5: Thriller | NX5: Comedy | NY5: Science Fiction | NZ5: Adventure | OA5: Science Fiction | OB5: Action | OC5: Thriller | OD5: Science Fiction | OE5: Science Fiction | OF5: Western | OG5: Comedy | OH5: Comedy | OI5: Crime | OJ5: Drama | OK5: Crime | OL5: History | OM5: Comedy | ON5: Crime | OO5: Science Fiction | OP5: Adventure | OQ5: Science Fiction | OR5: Science Fiction | OS5: Horror | OT5: Adventure | OU5: Science Fiction | OV5: Western | OW5: Science Fiction | OX5: Sport | OY5: Science Fiction | OZ5: Western | PA5: Thriller | PB5: Drama | PC5: Action | PD5: Action | PE5: Drama | PF5: Action | PG5: Western | PH5: Comedy | PI5: War | PJ5: Science Fiction | PK5: Science Fiction | PL5: Science Fiction | PM5: Thriller | PN5: Science Fiction | PO5: Crime | PP5: Crime | PQ5: Drama | PR5: Western | PS5: Science Fiction | PT5: Adventure | PU5: Crime | PV5: Thriller | PW5: Thriller | PX5: Crime | PY5: Adventure | PZ5: Documentary | QA5: Adventure | QB5: Science Fiction | QC5: Science Fiction | QD5: Fantasy | QE5: Action | QF5: Action | QG5: Adventure | QH5: Action | QI5: Action | QJ5: Science Fiction | QK5: Animation | QL5: Action | QM5: Animation | QN5: Adventure | QO5: Action | QP5: Animation | QQ5: Science Fiction | QR5: Action | QS5: Action | QT5: Action | QU5: Action | QV5: Animation | QW5: Awful | QX5: Action | QY5: Animation | QZ5: Science Fiction | RA5: Science Fiction | RB5: Science Fiction | RC5: Adventure | RD5: Awful | RE5: Thriller | RF5: Animation | RG5: Action | RH5: Comedy | RI5: Animation | RJ5: Animation | RK5: Animation | RL5: Science Fiction | RM5: Animation | RN5: Awful | RO5: Action | RP5: Animation | RQ5: Animation | RR5: Animation | RS5: Science Fiction | RT5: Animation | RU5: Science Fiction | RV5: Disaster | RW5: Animation | RX5: Awful | RY5: Mystery | RZ5: Comedy | SA5: Action | SB5: Animation | SC5: Action | SD5: Animation | SE5: Action | SF5: Animation | SG5: Adventure | SH5: Drama | SI5: Animation | SJ5: Adventure | SK5: Animation | SL5: Animation | SM5: Romance | SN5: Animation | SO5: Comedy | SP5: Animation | SQ5: Animation | SR5: Science Fiction | SS5: Action | ST5: Mystery | SU5: Animation | SV5: Adventure | SW5: Adventure | SX5: Thriller | SY5: Comedy | SZ5: Animation | TA5: Comedy | TB5: Comedy | TC5: Horror | TD5: Animation | TE5: Animation | TF5: Adventure | TG5: Comedy | TH5: Science Fiction | TI5: Comedy | TJ5: Animation | TK5: Animation | TL5: Comedy | TM5: Adventure | TN5: Thriller | TO5: Comedy | TP5: Romantic Comedy | TQ5: Disaster | TR5: Animation | TS5: Family | TT5: Thriller | TU5: Comedy | TV5: Drama | TW5: Action | TX5: Animation | TY5: Animation | TZ5: Action | UA5: Comedy | UB5: Adventure | UC5: Animation | UD5: Comedy | UE5: Action | UF5: Comedy | UG5: Comedy | UH5: Crime | UI5: Horror | UJ5: Comedy | UK5: Thriller | UL5: Drama | UM5: Romance | UN5: Drama | UO5: Thriller | UP5: Animation | UQ5: Thriller | UR5: Family | US5: Thriller | UT5: Action | UU5: Drama | UV5: Comedy | UW5: Horror | UX5: Comedy | UY5: Animation | UZ5: Adventure | VA5: Thriller | VB5: Thriller | VC5: Comedy | VD5: Thriller | VE5: Comedy | VF5: Comedy | VG5: Romance | VH5: Comedy | VI5: Romance | VJ5: Action | VK5: Action | VL5: Comedy | VM5: Drama | VN5: Adventure | VO5: Comedy | VP5: Animation | VQ5: Biography | VR5: Drama | VS5: Comedy | VT5: Comedy | VU5: Comedy | VV5: Romance | VW5: Comedy | VX5: Comedy | VY5: Thriller | VZ5: Action | WA5: Comedy | WB5: Romance | WC5: Comedy | WD5: Comedy | WE5: Comedy | WF5: Action | WG5: War | WH5: Drama | WI5: Adventure | WJ5: Comedy | WK5: Action | WL5: Sport | WM5: Drama | WN5: Romance | WO5: Science Fiction | WP5: Adventure | WQ5: Adventure | WR5: Comedy | WS5: Action | WT5: Comedy | WU5: Drama | WV5: Comedy | WW5: Drama | WX5: Adventure | WY5: Drama | WZ5: Drama | XA5: Comedy | XB5: Thriller | XC5: Thriller | XD5: Drama | XE5: Comedy | XF5: Drama | XG5: Sport | XH5: Action | XI5: Horror | XJ5: Musical | XK5: Comedy | XL5: Comedy | XM5: Comedy | XN5: Comedy | XO5: Comedy | XP5: Action | XQ5: Comedy | XR5: Comedy | XS5: Comedy | XT5: Drama | XU5: Horror | XV5: Drama | XW5: War | XX5: Romantic Comedy | XY5: Comedy | XZ5: Family | YA5: Musical | YB5: Comedy | YC5: Action | YD5: Thriller | YE5: Horror | YF5: Drama | YG5: Comedy | YH5: Science Fiction | YI5: Drama | YJ5: Adventure | YK5: Romantic Comedy | YL5: Drama | YM5: Thriller | YN5: Horror | YO5: Comedy | YP5: Action | YQ5: War | YR5: Thriller | YS5: Drama | YT5: Crime | YU5: Drama | YV5: Comedy | YW5: Disaster | YX5: Comedy | YY5: Disaster | YZ5: Crime | ZA5: Disaster | ZB5: Comedy | ZC5: Crime | ZD5: Horror | ZE5: Drama | ZF5: Crime | ZG5: Animation | ZH5: Crime | ZI5: Disaster | ZJ5: Thriller | ZK5: Musical | ZL5: Musical | ZM5: Crime | ZN5: Thriller | ZO5: Romance | ZP5: Disaster | ZQ5: Biography | ZR5: Western | ZS5: Drama | ZT5: Drama | ZU5: Musical | ZV5: Comedy | ZW5: Comedy | ZX5: Crime | ZY5: Science Fiction | ZZ5: Comedy | AAA5: Animation | AAB5: Crime | AAC5: War | AAD5: Horror | AAE5: Sport | AAF5: Musical | AAG5: War | AAH5: Musical | AAI5: History | AAJ5: Western | AAK5: Comedy | AAL5: Animation | AAM5: Horror | AAN5: War | AAO5: History | AAP5: Drama | AAQ5: Musical | AAR5: History | AAS5: Animation | AAT5: History | AAU5: Horror | AAV5: Adventure | AAW5: War | AAX5: Comedy | AAY5: Drama | AAZ5: Animation | ABA5: Thriller | ABB5: Romantic Comedy | ABC5: Musical | ABD5: Adventure | ABE5: Thriller | ABF5: Drama | ABG5: Western | ABH5: Fantasy | ABI5: Drama | ABJ5: Musical | ABK5: Western | ABL5: Musical | ABM5: Musical | ABN5: Musical | ABO5: Animation | ABP5: Adventure | ABQ5: Drama | ABR5: Drama | ABS5: Western | ABT5: Animation | ABU5: Musical | ABV5: Musical | ABW5: Animation | ABX5: Drama | ABY5: Adventure | ABZ5: Thriller | ACA5: Animation | ACB5: Adventure | ACC5: Musical | ACD5: War | ACE5: War | ACF5: Drama | ACG5: Comedy | ACH5: Drama | ACI5: Romance | ACJ5: Fantasy | ACK5: Animation | ACL5: Drama | ACM5: Horror | ACN5: Horror | ACO5: War | ACP5: Comedy | ACQ5: Science Fiction | ACR5: Adventure | ACS5: Action | ACT5: Action | ACU5: Animation | ACV5: Animation | ACW5: Action | ACX5: Science Fiction | ACY5: Science Fiction | ACZ5: Action | ADA5: Animation | ADB5: Animation | ADC5: Adventure | ADD5: Action | ADE5: Animation | ADF5: Action | ADG5: Action | ADH5: Action | ADI5: Action | ADJ5: Comedy | ADK5: Adventure | ADL5: Adventure | ADM5: Adventure | ADN5: Drama | ADO5: Drama | ADP5: Drama | ADQ5: Crime | ADR5: Fantasy | ADS5: Comedy | ADT5: Comedy | ADU5: Biography | ADV5: Adventure | ADW5: Comedy | ADX5: Action | ADY5: Science Fiction | ADZ5: Action | AEA5: Martial Arts | AEB5: Adventure | AEC5: Action | AED5: Action | AEE5: Action | AEF5: Action | AEG5: Mystery | AEH5: Adventure | AEI5: Action | AEJ5: Action | AEK5: Action | AEL5: Science Fiction | AEM5: Martial Arts | AEN5: Action | AEO5: Action | AEP5: Action | AEQ5: Thriller | AER5: War | AES5: Disaster | AET5: Action | AEU5: Thriller | AEV5: Thriller | AEW5: Science Fiction | AEX5: Science Fiction | AEY5: Science Fiction | AEZ5: Adventure | AFA5: Biography | AFB5: Adventure | AFC5: Science Fiction | AFD5: Horror | AFE5: Crime | AFF5: Action | AFG5: Action | AFH5: Science Fiction | AFI5: Action | AFJ5: Science Fiction | AFK5: Horror | AFL5: Action | AFM5: Family | AFN5: Comedy | AFO5: Science Fiction | AFP5: Western | AFQ5: Action | AFR5: Science Fiction | AFS5: Action | AFT5: Action | AFU5: Action | AFV5: Fantasy | AFW5: Fantasy | AFX5: Fantasy | AFY5: Documentary | AFZ5: Action | AGA5: Drama | AGB5: Action | AGC5: Action | AGD5: Action | AGE5: Crime | AGF5: Action | AGG5: Action | AGH5: Science Fiction | AGI5: Action | AGJ5: Thriller | AGK5: Thriller | AGL5: War | AGM5: History | AGN5: Science Fiction | AGO5: Biography | AGP5: Comedy | AGQ5: Biography | AGR5: History | AGS5: Family | AGT5: Biography | AGU5: Drama | AGV5: Comedy | AGW5: Comedy | AGX5: Crime | AGY5: Science Fiction | AGZ5: Science Fiction | AHA5: Animation | AHB5: Science Fiction | AHC5: Action | AHD5: Action | AHE5: Martial Arts | AHF5: Science Fiction | AHG5: Martial Arts | AHH5: Crime | AHI5: War | AHJ5: Western | AHK5: Western | AHL5: Western | AHM5: Western | AHN5: Action | AHO5: War | AHP5: Western | AHQ5: War | AHR5: Thriller | AHS5: Thriller | AHT5: Drama | AHU5: Sport | AHV5: Biography | AHW5: Biography | AHX5: Biography | AHY5: Biography | AHZ5: Action | AIA5: Thriller | AIB5: Action | AIC5: Action | AID5: Action | AIE5: Fantasy | AIF5: Western | AIG5: Western | AIH5: Drama | AII5: Action | AIJ5: Crime | AIK5: Thriller | AIL5: Drama | AIM5: War | AIN5: Science Fiction | AIO5: Science Fiction | AIP5: Science Fiction | AIQ5: Science Fiction | AIR5: Science Fiction | AIS5: Comedy | AIT5: Comedy | AIU5: Romantic Comedy | AIV5: Comedy | AIW5: Crime | AIX5: Drama | AIY5: Crime | AIZ5: Musical | AJA5: Comedy | AJB5: Drama | AJC5: Drama | AJD5: Romance | AJE5: Drama | AJF5: Biography | AJG5: Thriller | AJH5: Comedy | AJI5: Fantasy | AJJ5: Animation | AJK5: Comedy | AJL5: Science Fiction | AJM5: Comedy | AJN5: Comedy | AJO5: Science Fiction | AJP5: Comedy | AJQ5: Thriller | AJR5: Animation | AJS5: Crime | AJT5: War | AJU5: Western | AJV5: Western | AJW5: Adventure | AJX5: Adventure | AJY5: Western | AJZ5: Western | AKA5: Thriller | AKB5: Crime | AKC5: War | AKD5: Adventure | AKE5: Action | AKF5: Action | AKG5: Thriller | AKH5: Drama | AKI5: Fantasy | AKJ5: Science Fiction | AKK5: Science Fiction | AKL5: Fantasy | AKM5: Comedy | AKN5: Action | AKO5: Action | AKP5: Action | AKQ5: Horror | AKR5: Thriller | AKS5: Thriller | AKT5: Action | AKU5: Animation | AKV5: Comedy | AKW5: Comedy | AKX5: Science Fiction | AKY5: Science Fiction | AKZ5: Biography | ALA5: Action | ALB5: Horror | ALC5: Action | ALD5: Action | ALE5: Sport | ALF5: Science Fiction | ALG5: Thriller | ALH5: War | ALI5: Thriller | ALJ5: Action | ALK5: Science Fiction | ALL5: Fantasy | ALM5: Thriller | ALN5: Adventure | ALO5: Adventure | ALP5: War | ALQ5: Crime | ALR5: Action | ALS5: Adventure | ALT5: Adventure | ALU5: Awful | ALV5: Crime | ALW5: Thriller | ALX5: Action | ALY5: Adventure | ALZ5: Comedy | AMA5: Drama | AMB5: Comedy | AMC5: Comedy | AMD5: Comedy | AME5: Action | AMF5: Drama | AMG5: Romance | AMH5: Drama | AMI5: Crime | AMJ5: Drama | AMK5: Comedy | AML5: Action | AMM5: Science Fiction | AMN5: Biography | AMO5: Thriller | AMP5: Science Fiction | AMQ5: Action | AMR5: Science Fiction | AMS5: Thriller | AMT5: Science Fiction | AMU5: Science Fiction | AMV5: Horror | AMW5: Comedy | AMX5: Action | AMY5: Action | AMZ5: Western | ANA5: Action | ANB5: Science Fiction | ANC5: Drama | AND5: Adventure | ANE5: Drama | ANF5: Comedy | ANG5: Western | ANH5: Western | ANI5: Horror | ANJ5: Horror | ANK5: Comedy | ANL5: Animation | ANM5: Drama | ANN5: Comedy | ANO5: Animation | ANP5: Animation | ANQ5: Action | ANR5: Comedy | ANS5: Animation | ANT5: Fantasy | ANU5: Fantasy | ANV5: Science Fiction | ANW5: History | ANX5: Adventure | ANY5: Western | ANZ5: Drama | AOA5: Drama | AOB5: Biography | AOC5: Crime | AOD5: Drama | AOE5: Drama | AOF5: Drama | AOG5: Comedy | AOH5: Drama | AOI5: Science Fiction | AOJ5: Thriller
A6: Director | B6: George Miller | C6: John Cornell | D6: Peter Faiman | E6: George Miller | F6: George Miller | G6: George Miller | H6: George Miller | I6: Fernando Meirelles | J6: Joel Zwick | K6: Bob Clark | L6: Zhang Yimou | M6: Ang Lee | N6: Zhang Yimou | O6: Stephen Chow | P6: Hark Tsui | Q6: Hark Tsui | R6: John Woo | S6: John Woo | T6: Nicolas Winding Refn | U6: Luc Besson | V6: Luc Besson | W6: Jean-Pierre Jeunet | X6: Chris Nahon | Y6: Louis Leterrier | Z6: Louis Leterrier | AA6: Louis Leterrier | AB6: Pierre Morel | AC6: Patrick Alessandrin | AD6: Pierre Morel | AE6: Pierre Morel | AF6: Jacques Audiard | AG6: Michael J. Bassett | AH6: McG | AI6: Oliver Hirschbiegel | AJ6: Wolfgang Peterson | AK6: Florian Henckel von Donnersmarck | AL6: Paul McGuigan | AM6: Wolfgang Peterson | AN6: Stanley Tong | AO6: Lo Wei | AP6: Lo Wei | AQ6: Bruce Lee | AR6: Robert Clouse | AS6: Robert Clouse | AT6: Stanley Tong | AU6: Hark Tsui | AV6: Peter Chan | AW6: Peter Chan | AX6: Hark Tsui | AY6: John Woo | AZ6: Wilson Yip | BA6: Wilson Yip | BB6: Wilson Yip | BC6: Woo-ping Yuen | BD6: Stephen Chow | BE6: Gareth Evans | BF6: Gareth Evans | BG6: Sergio Leone | BH6: Sergio Leone | BI6: Sergio Leone | BJ6: Sergio Leone | BK6: Akira Kurosawa | BL6: Akira Kurosawa | BM6: Akira Kurosawa | BN6: Richard Fleischer | BO6: Akira Kurosawa | BP6: Takashi Miike | BQ6: Takashi Miike | BR6: Kinji Fukasaku | BS6: Yojiro Takita | BT6: Yoji Yamada | BU6: Ishiro Honda | BV6: Ishiro Honda | BW6: Richard Fleischer | BX6: Peter Jackson | BY6: Peter Jackson | BZ6: Peter Jackson | CA6: Peter Jackson | CB6: Lee Tamahori | CC6: Peter Jackson | CD6: Peter Jackson | CE6: Peter Jackson | CF6: Joel Coen | CG6: Timur Bekmambetov | CH6: Timur Bekmambetov | CI6: Stephen Campanelli | CJ6: Neill Blomkamp | CK6: Niels Arden Oplev | CL6: Daniel Alfredson | CM6: Ingmar Bergman | CN6: Prachya Pinkaew | CO6: Tony Jaa | CP6: Prachya Pinkaew | CQ6: Prachya Pinkaew | CR6: David Yates | CS6: Mike Newell | CT6: Lee Tamahori | CU6: Michael Apted | CV6: Alfonso Cuaron | CW6: Chris Columbus | CX6: Roger Spottiswoode | CY6: Martin Campbell | CZ6: Chris Columbus | DA6: Martin Campbell | DB6: John Glen | DC6: John Glen | DD6: Lewis Gilbert | DE6: John Glen | DF6: Richard Attenborough | DG6: Larry Charles | DH6: Edgar Wright | DI6: Ang Lee | DJ6: Danny Boyle | DK6: Danny Boyle | DL6: Danny Boyle | DM6: Lewis Gilbert | DN6: Ken Hughes | DO6: Terence Young | DP6: Peter R. Hunt | DQ6: Guy Hamilton | DR6: Guy Hamilton | DS6: Guy Hamilton | DT6: Edgar Wright | DU6: Mike Newell | DV6: Terence Young | DW6: Terence Young | DX6: Danny Boyle | DY6: David Bowers | DZ6: Sam Mendes | EA6: David Yates | EB6: Tim Burton | EC6: David Yates | ED6: David Yates | EE6: Guy Ritchie | EF6: Phyllida Lloyd | EG6: Marc Forster | EH6: Andrew Adamson | EI6: Andrew Adamson | EJ6: Roger Michell | EK6: John Madden | EL6: Peter Cattaneo | EM6: Richard Lester | EN6: Hugh Hudson | EO6: Terry Gilliam | EP6: Blake Edwards | EQ6: Richard Attenborough | ER6: Jim Sharman | ES6: Blake Edwards | ET6: Stanley Kubrick | EU6: Robert Stevenson | EV6: Stanley Kubrick | EW6: Franco Zeffirelli | EX6: Carol Reed | EY6: David Lean | EZ6: Richard Lester | FA6: David Lean | FB6: J. Lee Thompson | FC6: David Lean | FD6: Richard Thorpe | FE6: John Huston | FF6: Sam Wood | FG6: Sam Mendes | FH6: Stanley Kubrick | FI6: Alfred Hitchcock | FJ6: Julien Duvivier | FK6: David Lean | FL6: Compton Bennett | FM6: David Lean | FN6: Laurence Olivier | FO6: Terry Gilliam | FP6: Terry Jones | FQ6: Desmond Davis | FR6: Shane Meadows | FS6: Shane Meadows | FT6: Steve Bendelack | FU6: Ben Wheatley | FV6: Ben Wheatley | FW6: Ben Wheatley | FX6: Ben Wheatley | FY6: Danny Boyle | FZ6: John Madden | GA6: John Madden | GB6: Jonathan English | GC6: Danny Boyle | GD6: Danny Boyle | GE6: Juan Carlos Fresnadillo | GF6: Danny Boyle | GG6: Danny Boyle | GH6: Matthew Vaughn | GI6: Matthew Vaughn | GJ6: Matthew Vaughn | GK6: Matthew Vaughn | GL6: Len Wiseman | GM6: Len Wiseman | GN6: Peter Hyams | GO6: Stanley Kubrick | GP6: Stanley Kubrick | GQ6: Stanley Kubrick | GR6: Stanley Kubrick | GS6: Sidney Lumet | GT6: Mike Hodges | GU6: Brian G. Hutton | GV6: Sam Peckinpah | GW6: Cy Endfield | GX6: Nicolas Winding Refn | GY6: Martin Scorsese | GZ6: Jim Henson | HA6: Edgar Wright | HB6: David Yates | HC6: Alex Garland | HD6: Joe Wright | HE6: Lasse Hallstrom | HF6: Anthony Minghella | HG6: Guy Ritchie | HH6: Guy Ritchie | HI6: Guy Ritchie | HJ6: Guy Ritchie | HK6: Ridley Scott | HL6: James Marsh | HM6: James Marsh | HN6: Tom Hooper | HO6: Justin Chadwick | HP6: Justin Chadwick | HQ6: Tom Hooper | HR6: Tom Hooper | HS6: Steve McQueen | HT6: Ron Howard | HU6: Kevin Macdonald | HV6: Kevin Macdonald | HW6: Neil Marshall | HX6: Don Chaffey | HY6: Don Chaffey | HZ6: Richard Lester | IA6: Steven Spielberg | IB6: Sam Raimi | IC6: Bryan Singer | ID6: James Cameron | IE6: Tom Shadyac | IF6: Kevin Reynolds | IG6: Michael Bay | IH6: Michael Bay | II6: Robert Zemeckis | IJ6: Steve Hickner | IK6: Gore Verbinski | IL6: Francis Lawrence | IM6: Brad Bird | IN6: Wolfgang Peterson | IO6: Christopher Nolan | IP6: Tim Burton | IQ6: Gore Verbinski | IR6: Richard Donner | IS6: Michael Bay | IT6: Barry Sonnenfeld | IU6: Sam Raimi | IV6: Sam Raimi | IW6: Rob Cohen | IX6: Hironobu Sakaguchi | IY6: Michael Mann | IZ6: Peter Weir | JA6: Steven Spielberg | JB6: Paul Greengrass | JC6: Lilly (Andy) Wachowski | JD6: Ron Howard | JE6: Roland Emmerich | JF6: Gore Verbinski | JG6: Edward Zwick | JH6: Wolfgang Peterson | JI6: J. J. Abrams | JJ6: John Woo | JK6: John Woo | JL6: George Lucas | JM6: Pete Docter | JN6: George Lucas | JO6: George Lucas | JP6: Lilly (Andy) Wachowski | JQ6: Steven Soderbergh | JR6: Len Wiseman | JS6: Frank Coraci | JT6: Ridley Scott | JU6: Doug Liman | JV6: Martin Scorsese | JW6: Michael Mann | JX6: Alex Proyas | JY6: Steven Spielberg | JZ6: James Cameron | KA6: Jean-Christophe Comar | KB6: Ridley Scott | KC6: Edward Zwick | KD6: Ridley Scott | KE6: James Cameron | KF6: Martin Scorsese | KG6: Ridley Scott | KH6: Brett Ratner | KI6: Brett Ratner | KJ6: Barry Sonnenfeld | KK6: Martin Scorsese | KL6: John McTiernan | KM6: Ron Howard | KN6: Paul Greengrass | KO6: John McTiernan | KP6: Robert Zemeckis | KQ6: Steven Soderbergh | KR6: Frank Coraci | KS6: Tom Shadyac | KT6: Brian De Palma | KU6: Mimi Leder | KV6: Sam Mendes | KW6: Ron Howard | KX6: Alfonso Cuaron | KY6: Steven Spielberg | KZ6: Roland Emmerich | LA6: Bryan Singer | LB6: Bryan Singer | LC6: Michael Bay | LD6: Francis Lawrence | LE6: M. Night Shyamalan | LF6: Adam McKay | LG6: David Silverman | LH6: Mel Gibson | LI6: Sam Mendes | LJ6: M. Night Shyamalan | LK6: Chris Miller | LL6: Andrew Adamson | LM6: James Cameron | LN6: Jonathan Frakes | LO6: Robert Zemeckis | LP6: Tim Burton | LQ6: Rob Cohen | LR6: Renny Harlin | LS6: Renny Harlin | LT6: Ron Howard | LU6: Steven Spielberg | LV6: David Fincher | LW6: Lilly (Andy) Wachowski | LX6: Paul Verhoeven | LY6: Renny Harlin | LZ6: Phillip Noyce | MA6: Brian De Palma | MB6: Peter Weir | MC6: Paul Anderson | MD6: Doug Liman | ME6: Guillermo del Toro | MF6: Todd Phillips | MG6: Joel Coen | MH6: Zack Snyder | MI6: Stuart Baird | MJ6: Richard Donner | MK6: Tony Scott | ML6: Tony Scott | MM6: Tony Scott | MN6: Tony Scott | MO6: Quentin Tarantino | MP6: David Fincher | MQ6: Tom Dey | MR6: Quentin Tarantino | MS6: Guillermo del Toro | MT6: Clint Eastwood | MU6: Martin Scorsese | MV6: Kevin Reynolds | MW6: Andrew Adamson | MX6: David Dobkin | MY6: Steven Spielberg | MZ6: Jonathan Frakes | NA6: Stephen Norrington | NB6: Phillip Noyce | NC6: Andrew Davis | ND6: Christopher Nolan | NE6: Michael Mann | NF6: Mel Gibson | NG6: David Dobkin | NH6: Robert Zemeckis | NI6: Robert Zemeckis | NJ6: Frank Miller | NK6: Joss Whedon | NL6: David Carson | NM6: Irvin Kershner | NN6: Robert Wise | NO6: Brett Ratner | NP6: Richard Donner | NQ6: Richard Marquand | NR6: David Cronenberg | NS6: Barry Sonnenfeld | NT6: Andrew Dominik | NU6: Clint Eastwood | NV6: David Fincher | NW6: John McTiernan | NX6: Ivan Reitman | NY6: William Shatner | NZ6: Steven Spielberg | OA6: Ridley Scott | OB6: John McTiernan | OC6: John Glen | OD6: Nicholas Meyer | OE6: Paul Michael Glaser | OF6: Kevin Costner | OG6: Ivan Reitman | OH6: Joel Coen | OI6: Martin Scorsese | OJ6: Mel Gibson | OK6: Brian De Palma | OL6: Steven Spielberg | OM6: Adam McKay | ON6: Brian De Palma | OO6: Leonard Nimoy | OP6: John Guillermin | OQ6: Irvin Kershner | OR6: Kurt Wimmer | OS6: Robert Rodriguez | OT6: Steven Spielberg | OU6: Robert Zemeckis | OV6: Kevin Costner | OW6: Leonard Nimoy | OX6: Martin Scorsese | OY6: James Cameron | OZ6: Clint Eastwood | PA6: Michael Mann | PB6: Sam Mendes | PC6: Richard Donner | PD6: Richard Donner | PE6: Ang Lee | PF6: Ang Lee | PG6: Ang Lee | PH6: Ivan Reitman | PI6: Clint Eastwood | PJ6: Nicholas Meyer | PK6: George Lucas | PL6: Steven Spielberg | PM6: Lewis Gilbert | PN6: Ridley Scott | PO6: Quentin Tarantino | PP6: Joel Coen | PQ6: George Clooney | PR6: Clint Eastwood | PS6: James Cameron | PT6: Michael Anderson | PU6: Bryan Singer | PV6: Christopher Nolan | PW6: Guy Hamilton | PX6: Quentin Tarantino | PY6: Merian C. Cooper | PZ6: Morgan Spurlock | QA6: Steven Spielberg | QB6: Michael Bay | QC6: James Gunn | QD6: Robert Stromberg | QE6: Bryan Singer | QF6: Anthony Russo | QG6: Francis Lawrence | QH6: Marc Webb | QI6: Matt Reeves | QJ6: Christopher Nolan | QK6: Chris Buck | QL6: Shane Black | QM6: Pierre Coffin | QN6: Francis Lawrence | QO6: Justin Lin | QP6: Dan Scanlon | QQ6: Alfonso Cuaron | QR6: Zack Snyder | QS6: Alan Taylor | QT6: Joss Whedon | QU6: Christopher Nolan | QV6: Mike Thurmeier | QW6: Bill Condon | QX6: Marc Webb | QY6: Eric Darnell | QZ6: Gary Ross | RA6: Barry Sonnenfeld | RB6: Michael Bay | RC6: Rob Marshall | RD6: Bill Condon | RE6: Brad Bird | RF6: Jennifer Yuh Nelson | RG6: Justin Lin | RH6: Todd Phillips | RI6: Raja Gosnell | RJ6: John Lasseter | RK6: Lee Unkrich | RL6: Christopher Nolan | RM6: Mike Mitchell | RN6: David Slade | RO6: Jon Favreau | RP6: Nathan Greno | RQ6: Pierre Coffin | RR6: Dean DeBlois | RS6: James Cameron | RT6: Carlos Saldanha | RU6: Michael Bay | RV6: Roland Emmerich | RW6: Pete Docter | RX6: Chris Weitz | RY6: Ron Howard | RZ6: Todd Phillips | SA6: Christopher Nolan | SB6: Mark Osborne | SC6: Peter Berg | SD6: Eric Darnell | SE6: Jon Favreau | SF6: Andrew Stanton | SG6: Jon Turteltaub | SH6: Ron Howard | SI6: Carlos Saldanha | SJ6: Shawn Levy | SK6: John Lasseter | SL6: Eric Darnell | SM6: Andy Tennant | SN6: Brad Bird | SO6: Jay Roach | SP6: Vicky Jenson | SQ6: Andrew Stanton | SR6: Jonathan Mostow | SS6: Michael Bay | ST6: M. Night Shyamalan | SU6: Carlos Saldanha | SV6: Stephen Sommers | SW6: Joe Johnston | SX6: Ridley Scott | SY6: Nancy Meyers | SZ6: Ralph Zondag | TA6: Ron Howard | TB6: Jay Roach | TC6: Robert Zemeckis | TD6: John Lasseter | TE6: Kevin Lima | TF6: Stephen Sommers | TG6: Jay Roach | TH6: Roland Emmerich | TI6: Peter Farrelly | TJ6: John Lasseter | TK6: Barry Cook | TL6: Betty Thomas | TM6: Steven Spielberg | TN6: Wolfgang Peterson | TO6: Tom Shadyac | TP6: P. J. Hogan | TQ6: Jan de Bont | TR6: Gary Trousdale | TS6: Stephen Herek | TT6: Ron Howard | TU6: Tom Shadyac | TV6: Cameron Crowe | TW6: Chuck Russell | TX6: John Lasseter | TY6: Mike Gabriel | TZ6: Joel Schumacher | UA6: Brad Silberling | UB6: Joe Johnston | UC6: Rob Minkoff | UD6: Chuck Russell | UE6: Jan de Bont | UF6: Brian Levant | UG6: Peter Farrelly | UH6: Mike Newell | UI6: Neil Jordan | UJ6: Chris Columbus | UK6: Sydney Pollack | UL6: Adrian Lyne | UM6: Nora Ephron | UN6: Jonathan Demme | UO6: Alan J. Pakula | UP6: Ron Clements | UQ6: Mick Jackson | UR6: Chris Columbus | US6: Paul Verhoeven | UT6: Tim Burton | UU6: Rob Reiner | UV6: Emile Ardolino | UW6: Francis Ford Coppola | UX6: Penelope Spheeris | UY6: Gary Trousdale | UZ6: Steven Spielberg | VA6: Jonathan Demme | VB6: Oliver Stone | VC6: Barry Sonnenfeld | VD6: Martin Scorsese | VE6: Jim Abrahams | VF6: Ron Underwood | VG6: Jerry Zucker | VH6: Chris Columbus | VI6: Garry Marshall | VJ6: Steve Barron | VK6: Tim Burton | VL6: Amy Heckerling | VM6: Peter Weir | VN6: Joe Johnston | VO6: Ivan Reitman | VP6: Ron Clements | VQ6: Oliver Stone | VR6: Barry Levinson | VS6: John Landis | VT6: Penny Marshall | VU6: David Zucker | VV6: Roger Donaldson | VW6: Tim Burton | VX6: Leonard Nimoy | VY6: Adrian Lyne | VZ6: Tony Scott | WA6: Barry Levinson | WB6: Norman Jewison | WC6: Herbert Ross | WD6: John Badham | WE6: George Miller | WF6: Tony Scott | WG6: Oliver Stone | WH6: John G. Avildsen | WI6: Michael Ritchie | WJ6: John Hughes | WK6: George P. Cosmatos | WL6: Sylvester Stallone | WM6: Steven Spielberg | WN6: Sydney Pollack | WO6: Ron Howard | WP6: Lewis Teague | WQ6: Richard Donner | WR6: John Landis | WS6: Martin Brest | WT6: Joe Dante | WU6: John G. Avildsen | WV6: Hugh Wilson | WW6: Herbert Ross | WX6: Robert Zemeckis | WY6: James L. Brooks | WZ6: Adrian Lyne | XA6: John Landis | XB6: John Badham | XC6: Clint Eastwood | XD6: Sylvester Stallone | XE6: Sydney Pollack | XF6: Taylor Hackford | XG6: Sylvester Stallone | XH6: Walter Hill | XI6: Tobe Hooper | XJ6: John Huston | XK6: Steve Gordon | XL6: Hal Needham | XM6: Colin Higgins | XN6: Sidney Poitier | XO6: Jim Abrahams | XP6: Buddy Van Horn | XQ6: Howard Zieff | XR6: Hal Needham | XS6: John Landis | XT6: Robert Benton | XU6: Stuart Rosenberg | XV6: Sylvester Stallone | XW6: Francis Ford Coppola | XX6: Blake Edwards | XY6: Carl Reiner | XZ6: James Frawley | YA6: Randal Kleiser | YB6: John Landis | YC6: James Fargo | YD6: Jeannot Szwarc | YE6: George A. Romero | YF6: Michael Cimino | YG6: Hal Needham | YH6: Steven Spielberg | YI6: John Badham | YJ6: Peter Yates | YK6: Woody Allen | YL6: John G. Avildsen | YM6: Alan J. Pakula | YN6: Richard Donner | YO6: Arthur Hiller | YP6: James Fargo | YQ6: Jack Smight | YR6: Steven Spielberg | YS6: Milos Forman | YT6: Sidney Lumet | YU6: Hal Ashby | YV6: Mel Brooks | YW6: John Guillermin | YX6: Mel Brooks | YY6: Mark Robson | YZ6: Francis Ford Coppola | ZA6: Jack Smight | ZB6: Robert Aldrich | ZC6: George Roy Hill | ZD6: William Friedkin | ZE6: George Lucas | ZF6: Franklin J. Schaffner | ZG6: Wolfgang Reitherman | ZH6: Francis Ford Coppola | ZI6: Ronald Neame | ZJ6: John Boorman | ZK6: Bob Fosse | ZL6: Norman Jewison | ZM6: William Friedkin | ZN6: Don Siegel | ZO6: Arthur Hiller | ZP6: George Seaton | ZQ6: Franklin J. Schaffner | ZR6: George Roy Hill | ZS6: John Schlesinger | ZT6: Dennis Hopper | ZU6: Joshua Logan | ZV6: Robert Stevenson | ZW6: Gene Saks | ZX6: Peter Yates | ZY6: Franklin J. Schaffner | ZZ6: Mike Nichols | AAA6: Wolfgang Reitherman | AAB6: Arthur Penn | AAC6: Robert Aldrich | AAD6: George A. Romero | AAE6: John Frankenheimer | AAF6: Robert Wise | AAG6: Mark Robson | AAH6: George Cukor | AAI6: Joseph L. Mankiewicz | AAJ6: John Ford | AAK6: Stanley Kramer | AAL6: Wolfgang Reitherman | AAM6: Alfred Hitchcock | AAN6: Ken Annakin | AAO6: Lewis Milestone | AAP6: Robert Mulligan | AAQ6: Robert Wise | AAR6: Anthony Mann | AAS6: Wolfgang Reitherman | AAT6: Stanley Kubrick | AAU6: Alfred Hitchcock | AAV6: Ken Annakin | AAW6: John Wayne | AAX6: Lewis Milestone | AAY6: William Wyler | AAZ6: Wolfgang Reitherman | ABA6: Alfred Hitchcock | ABB6: Billy Wilder | ABC6: Joshua Logan | ABD6: Richard Fleischer | ABE6: Alfred Hitchcock | ABF6: Charles Vidor | ABG6: John Sturges | ABH6: Cecil B. DeMille | ABI6: King Vidor | ABJ6: Walter Lang | ABK6: John Ford | ABL6: Charles Walters | ABM6: Fred Zinnemann | ABN6: Joseph L. Mankiewicz | ABO6: Clyde Geronimi | ABP6: Richard Fleischer | ABQ6: Henry Koster | ABR6: Fred Zinnemann | ABS6: George Stevens | ABT6: Clyde Geronimi | ABU6: Howard Hawks | ABV6: Gene Kelly | ABW6: Clyde Geronimi | ABX6: Elia Kazan | ABY6: John Huston | ABZ6: Alfred Hitchcock | ACA6: Clyde Geronimi | ACB6: Compton Bennett | ACC6: Charles Walters | ACD6: Allan Dwan | ACE6: Sam Wood | ACF6: Michael Curtiz | ACG6: Charlie Chaplin | ACH6: John Ford | ACI6: Victor Fleming | ACJ6: Victor Fleming | ACK6: David Hand | ACL6: Clarence Brown | ACM6: James Whale | ACN6: Tod Browning | ACO6: Lewis Milestone | ACP6: Charlie Chaplin | ACQ6: J. J. Abrams | ACR6: Colin Trevorrow | ACS6: James Wan | ACT6: Joss Whedon | ACU6: Pierre Coffin | ACV6: Pete Docter | ACW6: Christopher McQuarrie | ACX6: Francis Lawrence | ACY6: Ridley Scott | ACZ6: Anthony Russo | ADA6: Andrew Stanton | ADB6: Byron Howard | ADC6: Jon Favreau | ADD6: Zack Snyder | ADE6: Chris Renaud | ADF6: Tim Miller | ADG6: David Ayer | ADH6: Bryan Singer | ADI6: Scott Derrickson | ADJ6: Nancy Meyers | ADK6: Michael Curtiz | ADL6: Michael Curtiz | ADM6: Michael Curtiz | ADN6: Frank Lloyd | ADO6: John Huston | ADP6: Orson Welles | ADQ6: William A. Wellman | ADR6: Frank Capra | ADS6: Frank Capra | ADT6: George Seaton | ADU6: Victor Fleming | ADV6: George Sidney | ADW6: Hal Needham | ADX6: Andrzej Bartkowiak | ADY6: James Wong | ADZ6: Andrzej Bartkowiak | AEA6: Rob Minkoff | AEB6: Rob Cohen | AEC6: Sylvester Stallone | AED6: Simon West | AEE6: Patrick Hughes | AEF6: Louis Leterrier | AEG6: Louis Leterrier | AEH6: Louis Leterrier | AEI6: John Woo | AEJ6: John Woo | AEK6: John Woo | AEL6: John Woo | AEM6: Woo-ping Yuen | AEN6: Carl Rinsch | AEO6: Kenneth Branagh | AEP6: Peter Berg | AEQ6: Peter Berg | AER6: Peter Berg | AES6: Peter Berg | AET6: Justin Lin | AEU6: Pierre Morel | AEV6: Jean-Francois Richet | AEW6: Neill Blomkamp | AEX6: Neill Blomkamp | AEY6: Andrew Stanton | AEZ6: Brian Helgeland | AFA6: Danny Boyle | AFB6: Ang Lee | AFC6: Alan Taylor | AFD6: Henry Hobson | AFE6: David Ayer | AFF6: Mikael Hafstrom | AFG6: Kim Jee-woon | AFH6: McG | AFI6: Andrew Davis | AFJ6: Roger Spottiswoode | AFK6: Peter Hyams | AFL6: Joel Schumacher | AFM6: Brian Levant | AFN6: Ivan Reitman | AFO6: Len Wiseman | AFP6: Joel Coen | AFQ6: Walter Hill | AFR6: John McTiernan | AFS6: John Irvin | AFT6: Mark L. Lester | AFU6: Brett Ratner | AFV6: Richard Fleischer | AFW6: John Milius | AFX6: Marcus Nispel | AFY6: George Butler | AFZ6: McG | AGA6: McG | AGB6: Matthew Vaughn | AGC6: McG | AGD6: McG | AGE6: Sergio Leone | AGF6: Patrick Tatopoulos | AGG6: Mans Marlind | AGH6: Roland Emmerich | AGI6: Andrew Davis | AGJ6: Steven Spielberg | AGK6: Steven Spielberg | AGL6: Steven Spielberg | AGM6: Steven Spielberg | AGN6: Steven Spielberg | AGO6: Steven Spielberg | AGP6: Steven Spielberg | AGQ6: Steven Spielberg | AGR6: Timur Bekmambetov | AGS6: Steven Spielberg | AGT6: Angelina Jolie | AGU6: Joel Coen | AGV6: Joel Coen | AGW6: Joel Coen | AGX6: Joel Coen | AGY6: Howard McCain | AGZ6: Peter Hyams | AHA6: Jennifer Yuh Nelson | AHB6: Roland Emmerich | AHC6: Sheldon Lettich | AHD6: Deran Sarafian | AHE6: Mark DiSalle | AHF6: Albert Pyun | AHG6: Newt Arnold | AHH6: Antoine Fuqua | AHI6: Stanley Kubrick | AHJ6: John Huston | AHK6: John Huston | AHL6: Clint Eastwood | AHM6: Ted Post | AHN6: Don Siegel | AHO6: Brian G. Hutton | AHP6: Clint Eastwood | AHQ6: Clint Eastwood | AHR6: Buddy Van Horn | AHS6: Clint Eastwood | AHT6: Clint Eastwood | AHU6: Clint Eastwood | AHV6: Clint Eastwood | AHW6: Clint Eastwood | AHX6: Clint Eastwood | AHY6: Clint Eastwood | AHZ6: David S. Goyer | AIA6: Stuart Baird | AIB6: John Badham | AIC6: Marco Brambilla | AID6: Kevin Hooks | AIE6: Rob Reiner | AIF6: Walter Hill | AIG6: Sam Peckinpah | AIH6: Tony Kaye | AII6: Sam Peckinpah | AIJ6: Sam Peckinpah | AIK6: Sam Peckinpah | AIL6: Stanley Kramer | AIM6: John Sturges | AIN6: Justin Lin | AIO6: J. J. Abrams | AIP6: J. J. Abrams | AIQ6: Paul Verhoeven | AIR6: Jose Padilha | AIS6: Kevin Smith | AIT6: Kevin Smith | AIU6: Kevin Smith | AIV6: Kevin Smith | AIW6: Nicolas Winding Refn | AIX6: Martin Scorsese | AIY6: Martin Scorsese | AIZ6: Martin Scorsese | AJA6: Martin Scorsese | AJB6: Martin Scorsese | AJC6: Martin Scorsese | AJD6: Martin Scorsese | AJE6: Martin Scorsese | AJF6: Martin Scorsese | AJG6: Martin Scorsese | AJH6: Ben Stiller | AJI6: Ron Howard | AJJ6: George Miller | AJK6: Ben Stiller | AJL6: David Lynch | AJM6: Shane Black | AJN6: Shane Black | AJO6: Roland Emmerich | AJP6: Paul Feig | AJQ6: Paul Greengrass | AJR6: Conrad Vernon | AJS6: Quentin Tarantino | AJT6: Quentin Tarantino | AJU6: Quentin Tarantino | AJV6: Quentin Tarantino | AJW6: Stephen Herek | AJX6: Peter Hewitt | AJY6: John Sturges | AJZ6: Antoine Fuqua | AKA6: Antoine Fuqua | AKB6: Antoine Fuqua | AKC6: Antoine Fuqua | AKD6: Antoine Fuqua | AKE6: Antoine Fuqua | AKF6: Antoine Fuqua | AKG6: Antoine Fuqua | AKH6: Antoine Fuqua | AKI6: Tim Burton | AKJ6: Tim Burton | AKK6: Tim Burton | AKL6: Tim Burton | AKM6: Tim Burton | AKN6: Zack Snyder | AKO6: Zack Snyder | AKP6: Zack Snyder | AKQ6: Zack Snyder | AKR6: Edward Zwick | AKS6: Christopher McQuarrie | AKT6: Christopher McQuarrie | AKU6: Ron Clements | AKV6: Terry Zwigoff | AKW6: Mark Waters | AKX6: Gareth Edwards | AKY6: Morten Tyldum | AKZ6: Morten Tyldum | ALA6: Gareth Edwards | ALB6: Kathryn Bigelow | ALC6: Kathryn Bigelow | ALD6: Ericson Core | ALE6: Ericson Core | ALF6: Kathryn Bigelow | ALG6: Kathryn Bigelow | ALH6: Kathryn Bigelow | ALI6: Kathryn Bigelow | ALJ6: Guy Ritchie | ALK6: Ridley Scott | ALL6: Ridley Scott | ALM6: Ridley Scott | ALN6: Ridley Scott | ALO6: Ridley Scott | ALP6: Ridley Scott | ALQ6: Ridley Scott | ALR6: Ridley Scott | ALS6: Ridley Scott | ALT6: Ridley Scott | ALU6: Catherine Hardwicke | ALV6: Niels Arden Oplev | ALW6: David Fincher | ALX6: Chad Stahelski | ALY6: Alejandro G. Inarritu | ALZ6: Alejandro G. Inarritu | AMA6: Alejandro G. Inarritu | AMB6: Seth MacFarlane | AMC6: Seth MacFarlane | AMD6: Seth MacFarlane | AME6: Tommy Wirkola | AMF6: Paul Thomas Anderson | AMG6: Paul Thomas Anderson | AMH6: Paul Thomas Anderson | AMI6: Paul Thomas Anderson | AMJ6: Paul Thomas Anderson | AMK6: Joe Dante | AML6: Jonathan Hensleigh | AMM6: Rian Johnson | AMN6: Steve McQueen | AMO6: Denis Villeneuve | AMP6: Jon Favreau | AMQ6: James Mangold | AMR6: Lana (Larry) Wachowski | AMS6: Denis Villeneuve | AMT6: Doug Liman | AMU6: George Nolfi | AMV6: Joe Johnston | AMW6: Mike Nichols | AMX6: Robert Rodriguez | AMY6: Peyton Reed | AMZ6: James Mangold | ANA6: James Mangold | ANB6: Steven Soderbergh | ANC6: Steven Soderbergh | AND6: Stephen Herek | ANE6: Stephen Herek | ANF6: Stephen Herek | ANG6: Christopher Cain | ANH6: Geoff Murphy | ANI6: Joel Schumacher | ANJ6: Joel Schumacher | ANK6: Phil Lord | ANL6: Phil Lord | ANM6: Anatole Litvak | ANN6: Akiva Schaffer | ANO6: Cody Cameron | ANP6: Phil Lord | ANQ6: Michael Bay | ANR6: Phil Lord | ANS6: Mike Thurmeier | ANT6: Don Chaffey | ANU6: David Lowery | ANV6: Richard Fleischer | ANW6: Joseph L. Mankiewicz | ANX6: J. Lee Thompson | ANY6: George Stevens | ANZ6: Nicholas Ray | AOA6: Elia Kazan | AOB6: Elia Kazan | AOC6: Elia Kazan | AOD6: George Stevens | AOE6: George Stevens | AOF6: George Stevens | AOG6: George Stevens | AOH6: Cecil B. DeMille | AOI6: Wolfgang Peterson | AOJ6: Wolfgang Peterson
A7: Studio | B7: Village Roadshow Pictures | C7: Paramount Pictures | D7: Rimfire Films | E7: Kennedy Miller | F7: Kennedy Miller | G7: Kennedy Miller | H7: Kennedy Miller | I7: O2 Filmes | J7: Gold Circle Films | K7: Astral Media | L7: Beijing New Picture Film Co. | M7: EDKO Films | N7: EDKO Films | O7: China Film Group | P7: Film Workshop | Q7: Film Workshop | R7: China Film Group | S7: China Film Group | T7: Gaumont | U7: Gaumont | V7: Gaumont | W7: UGC | X7: StudioCanal | Y7: EuropaCorp | Z7: EuropaCorp | AA7: EuropaCorp | AB7: EuropaCorp | AC7: EuropaCorp | AD7: EuropaCorp | AE7: EuropaCorp | AF7: Why Not Productions | AG7: Davis Entertainment | AH7: EuropaCorp | AI7: Newmarket Capital Group | AJ7: Bavaria Film | AK7: Bayerischer Rundfunk | AL7: Metro-Goldwyn-Mayer | AM7: Bavaria Film | AN7: Golden Harvest | AO7: Golden Harvest | AP7: Golden Harvest | AQ7: Golden Harvest | AR7: Golden Harvest | AS7: Warner Bros. Pictures | AT7: Golden Harvest | AU7: Golden Harvest | AV7: China Film Group | AW7: We Pictures | AX7: Film Workshop | AY7: Golden Princess Film Production Limited | AZ7: China Film Group | BA7: China Film Group | BB7: Dreams Salon Entertainment | BC7: Golden Harvest | BD7: China Film Group | BE7: PT. Merantau Films | BF7: PT. Merantau Films | BG7: Constantin Film | BH7: Constantin Film | BI7: Constantin Film | BJ7: Paramount Pictures | BK7: Toho Company | BL7: Toho Company | BM7: Greenwich Film Productions | BN7: 20th Century Fox | BO7: Daiei Film | BP7: Omega Project | BQ7: Toho Company | BR7: AM Associates | BS7: TV Tokyo | BT7: Eisei Gekijo | BU7: Toho Company | BV7: Toho Company | BW7: Dino De Laurentiis Corporation | BX7: WingNut Films | BY7: WingNut Films | BZ7: WingNut Films | CA7: WingNut Films | CB7: Communicado Productions | CC7: New Line Cinema | CD7: WingNut Films | CE7: WingNut Films | CF7: Miramax Films | CG7: Channel One Russia | CH7: Channel One Russia | CI7: Azari Media | CJ7: WingNut Films | CK7: Yellow Bird | CL7: Yellow Bird | CM7: Svensk Filmindustri | CN7: Baa-Ram-Ewe | CO7: Sahamongkol Film International | CP7: Baa-Ram-Ewe | CQ7: Baa-Ram-Ewe | CR7: Heyday Films | CS7: Heyday Films | CT7: Eon Productions | CU7: Eon Productions | CV7: Heyday Films | CW7: Heyday Films | CX7: Eon Productions | CY7: Eon Productions | CZ7: Heyday Films | DA7: Eon Productions | DB7: Eon Productions | DC7: Eon Productions | DD7: Eon Productions | DE7: Eon Productions | DF7: Goldcrest Films | DG7: Dune Entertainment | DH7: Big Talk Productions | DI7: Columbia Pictures | DJ7: British Film Council | DK7: 20th Century Fox | DL7: Channel Four Films | DM7: Eon Productions | DN7: Columbia Pictures | DO7: Eon Productions | DP7: Eon Productions | DQ7: Eon Productions | DR7: Eon Productions | DS7: Eon Productions | DT7: Big Talk Productions | DU7: Channel Four Films | DV7: Eon Productions | DW7: Eon Productions | DX7: DNA Films | DY7: Aardman Animations | DZ7: Eon Productions | EA7: Heyday Films | EB7: Walt Disney Pictures | EC7: Heyday Films | ED7: Heyday Films | EE7: Silver Pictures | EF7: Playtone Entertainment | EG7: Eon Productions | EH7: Walt Disney Pictures | EI7: Walden Media | EJ7: Polygram Filmed Entertainment | EK7: The Bedford Falls Company | EL7: Channel Four Films | EM7: Dovemead | EN7: Goldcrest Films | EO7: Handmade Films | EP7: Sellers-Edwards Productions | EQ7: Joseph E. Levine Productions | ER7: 20th Century Fox | ES7: United Artists | ET7: Hawk Films | EU7: Walt Disney Pictures | EV7: Stanley Kubrick Productions | EW7: Dino De Laurentiis Corporation | EX7: Columbia Pictures | EY7: Metro-Goldwyn-Mayer | EZ7: United Artists | FA7: Horizon Pictures | FB7: Columbia Pictures | FC7: Horizon Pictures | FD7: Metro-Goldwyn-Mayer | FE7: Romulus Films | FF7: Metro-Goldwyn-Mayer | FG7: Eon Productions | FH7: Seven Arts Productions | FI7: Gaumont | FJ7: London Film Productions | FK7: Cineguild | FL7: Ortus Films | FM7: Cineguild | FN7: Two Cities Films | FO7: Python (Monty) Pictures | FP7: Python (Monty) Pictures | FQ7: Metro-Goldwyn-Mayer | FR7: FilmFour Productions | FS7: FilmFour Productions | FT7: FilmFour Productions | FU7: Baby Cow Productions | FV7: FilmFour Productions | FW7: FilmFour Productions | FX7: FilmFour Productions | FY7: FilmFour Productions | FZ7: Blueprint Pictures | GA7: Blueprint Pictures | GB7: Mythic International Entertainment | GC7: FilmFour Productions | GD7: Channel Four Films | GE7: DNA Films | GF7: FilmFour Productions | GG7: Pathe | GH7: Shangri-La Entertainment | GI7: Plan B Entertainment | GJ7: Marv Films | GK7: Marv Films | GL7: Lakeshore Entertainment | GM7: Lakeshore Entertainment | GN7: The Ladd Company | GO7: Stanley Kubrick Productions | GP7: Stanley Kubrick Productions | GQ7: Hawk Films | GR7: Hawk Films | GS7: EMI Films | GT7: Dino De Laurentiis Corporation | GU7: Metro-Goldwyn-Mayer | GV7: EMI Films | GW7: Paramount Pictures | GX7: Vertigo Films | GY7: Paramount Pictures | GZ7: Henson Associates | HA7: Big Talk Productions | HB7: Heyday Films | HC7: FilmFour Productions | HD7: StudioCanal | HE7: Miramax Films | HF7: Miramax Films | HG7: Handmade Films | HH7: Columbia Pictures | HI7: Warner Bros. Pictures | HJ7: Village Roadshow Pictures | HK7: Scott Free Productions | HL7: Universal Pictures | HM7: BBC Films | HN7: UK Film Council | HO7: BBC Films | HP7: Pathe | HQ7: UK Film Council | HR7: UK Film Council | HS7: FilmFour Productions | HT7: Imagine Entertainment | HU7: FilmFour Productions | HV7: FilmFour Productions | HW7: UK Film Council | HX7: Columbia Pictures | HY7: Hammer Film Productions | HZ7: Dovemead | IA7: Amblin Entertainment | IB7: Marvel Entertainment | IC7: Legendary Pictures | ID7: 20th Century Fox | IE7: Spyglass Entertainment | IF7: Gordon Company | IG7: Touchstone Pictures | IH7: di Bonaventura Pictures | II7: Shangri-La Entertainment | IJ7: Dreamworks | IK7: Walt Disney Pictures | IL7: Village Roadshow Pictures | IM7: Walt Disney Pictures | IN7: Helena Productions | IO7: Legendary Pictures | IP7: Village Roadshow Pictures | IQ7: Walt Disney Pictures | IR7: Silver Pictures | IS7: Touchstone Pictures | IT7: Amblin Entertainment | IU7: Marvel Entertainment | IV7: Marvel Entertainment | IW7: Original Film | IX7: Square Pictures | IY7: Universal Pictures | IZ7: 20th Century Fox | JA7: Amblin Entertainment | JB7: The Kennedy Marshall Company | JC7: Village Roadshow Pictures | JD7: Imagine Entertainment | JE7: Centropolis Entertainment | JF7: Walt Disney Pictures | JG7: Radar Pictures | JH7: Warner Bros. Pictures | JI7: Cruise Wagner Productions | JJ7: Cruise Wagner Productions | JK7: Lion Rock Productions | JL7: Lucasfilm | JM7: Pixar Animation Studios | JN7: Lucasfilm | JO7: Lucasfilm | JP7: Village Roadshow Pictures | JQ7: Jerry Weintraub Productions | JR7: Cheyenne Enterprises | JS7: Walden Media | JT7: Scott Free Productions | JU7: Regency Enterprises | JV7: Forward Pass | JW7: Peters Entertainment | JX7: Davis Entertainment | JY7: Amblin Entertainment | JZ7: Carolco Pictures | KA7: Village Roadshow Pictures | KB7: Imagine Entertainment | KC7: The Bedford Falls Company | KD7: Scott Free Productions | KE7: Lightstorm Entertainment | KF7: Touchstone Pictures | KG7: Revolution Studios | KH7: Roger Birnbaum Productions | KI7: New Line Cinema | KJ7: Amblin Entertainment | KK7: Warner Bros. Pictures | KL7: Cinergi Pictures | KM7: Imagine Entertainment | KN7: The Kennedy Marshall Company | KO7: Columbia Pictures | KP7: ImageMovers | KQ7: Jerry Weintraub Productions | KR7: Revolution Studios | KS7: Spyglass Entertainment | KT7: Cruise Wagner Productions | KU7: Dreamworks | KV7: The Zanuck Company | KW7: Imagine Entertainment | KX7: Strike Entertainment | KY7: Amblin Entertainment | KZ7: Centropolis Entertainment | LA7: 20th Century Fox | LB7: 20th Century Fox | LC7: Hollywood Pictures | LD7: Village Roadshow Pictures | LE7: Touchstone Pictures | LF7: Apatow Productions | LG7: Gracie Films | LH7: Icon Productions | LI7: Universal Pictures | LJ7: Touchstone Pictures | LK7: Dreamworks | LL7: Dreamworks | LM7: Lightstorm Entertainment | LN7: Paramount Pictures | LO7: Touchstone Pictures | LP7: Mandalay Pictures | LQ7: Revolution Studios | LR7: Silver Pictures | LS7: New Line Cinema | LT7: Imagine Entertainment | LU7: Amblin Entertainment | LV7: Fox 2000 Pictures | LW7: Village Roadshow Pictures | LX7: Carolco Pictures | LY7: Carolco Pictures | LZ7: Paramount Pictures | MA7: Millennium Films | MB7: Scott Rudin Productions | MC7: Paramount Pictures | MD7: The Kennedy Marshall Company | ME7: Revolution Studios | MF7: Weed Road Pictures | MG7: Imagine Entertainment | MH7: Legendary Pictures | MI7: Paramount Pictures | MJ7: Dovemead | MK7: Hollywood Pictures | ML7: Touchstone Pictures | MM7: Regency Enterprises | MN7: Touchstone Pictures | MO7: A Band Apart | MP7: Brandywine Productions | MQ7: Touchstone Pictures | MR7: A Band Apart | MS7: New Line Cinema | MT7: Paramount Pictures | MU7: Universal Pictures | MV7: Morgan Creek Productions | MW7: Pacific Data Images | MX7: Touchstone Pictures | MY7: Lucasfilm | MZ7: Paramount Pictures | NA7: New Line Cinema | NB7: Paramount Pictures | NC7: Warner Bros. Pictures | ND7: Touchstone Pictures | NE7: Morgan Creek Productions | NF7: Touchstone Pictures | NG7: Tapestry Films | NH7: Amblin Entertainment | NI7: Amblin Entertainment | NJ7: Dimension Films | NK7: Universal Pictures | NL7: Paramount Pictures | NM7: Taliafilm | NN7: Paramount Pictures | NO7: Roger Birnbaum Productions | NP7: Silver Pictures | NQ7: Lucasfilm | NR7: New Line Cinema | NS7: Jersey Films | NT7: Virtual Studios | NU7: Lakeshore Entertainment | NV7: New Line Cinema | NW7: Mace Neufeld Productions | NX7: Black Rhino | NY7: Paramount Pictures | NZ7: Lucasfilm | OA7: The Ladd Company | OB7: Silver Pictures | OC7: Eon Productions | OD7: Paramount Pictures | OE7: Republic Pictures | OF7: Touchstone Pictures | OG7: Imagine Entertainment | OH7: Touchstone Pictures | OI7: Warner Bros. Pictures | OJ7: Icon Productions | OK7: Paramount Pictures | OL7: Amblin Entertainment | OM7: Apatow Productions | ON7: Universal Pictures | OO7: Paramount Pictures | OP7: Dino De Laurentiis Corporation | OQ7: Lucasfilm | OR7: Dimension Films | OS7: Dimension Films | OT7: Lucasfilm | OU7: Amblin Entertainment | OV7: Tig Productions | OW7: Paramount Pictures | OX7: United Artists | OY7: Brandywine Productions | OZ7: The Malpaso Company | PA7: Paramount Pictures | PB7: Jinks/Cohen Company | PC7: Silver Pictures | PD7: Silver Pictures | PE7: River Road Entertainment | PF7: Universal Pictures | PG7: Universal Pictures | PH7: Universal Pictures | PI7: Dreamworks | PJ7: Paramount Pictures | PK7: Lucasfilm | PL7: Amblin Entertainment | PM7: Eon Productions | PN7: Brandywine Productions | PO7: A Band Apart | PP7: Polygram Filmed Entertainment | PQ7: 2929 Entertainment | PR7: The Malpaso Company | PS7: Hemdale | PT7: United Artists | PU7: Bad Hat Harry Productions | PV7: Summit Entertainment | PW7: Eon Productions | PX7: Live Entertainment | PY7: RKO Radio Pictures | PZ7: The Con | QA7: Lucasfilm | QB7: di Bonaventura Pictures | QC7: Marvel Entertainment | QD7: Walt Disney Pictures | QE7: Marvel Entertainment | QF7: Marvel Entertainment | QG7: Color Force | QH7: Marvel Entertainment | QI7: Chernin Entertainment | QJ7: Legendary Pictures | QK7: Walt Disney Pictures | QL7: Marvel Entertainment | QM7: Illumination Entertainment | QN7: Color Force | QO7: Original Film | QP7: Pixar Animation Studios | QQ7: Heyday Films | QR7: Legendary Pictures | QS7: Marvel Entertainment | QT7: Marvel Entertainment | QU7: Legendary Pictures | QV7: 20th Century Fox | QW7: Summit Entertainment | QX7: Marvel Entertainment | QY7: Dreamworks | QZ7: Color Force | RA7: Amblin Entertainment | RB7: di Bonaventura Pictures | RC7: Walt Disney Pictures | RD7: Temple Hill Entertainment | RE7: Bad Robot Productions | RF7: Dreamworks | RG7: Original Film | RH7: Legendary Pictures | RI7: Sony Pictures | RJ7: Pixar Animation Studios | RK7: Pixar Animation Studios | RL7: Legendary Pictures | RM7: Dreamworks | RN7: Temple Hill Entertainment | RO7: Marvel Entertainment | RP7: Walt Disney Pictures | RQ7: Illumination Entertainment | RR7: Dreamworks | RS7: Lightstorm Entertainment | RT7: 20th Century Fox | RU7: di Bonaventura Pictures | RV7: Centropolis Entertainment | RW7: Pixar Animation Studios | RX7: Temple Hill Entertainment | RY7: Imagine Entertainment | RZ7: Legendary Pictures | SA7: Legendary Pictures | SB7: Dreamworks | SC7: Relativity Media | SD7: Dreamworks | SE7: Marvel Entertainment | SF7: Pixar Animation Studios | SG7: Jerry Bruckheimer Films | SH7: Imagine Entertainment | SI7: 20th Century Fox | SJ7: Dune Entertainment | SK7: Pixar Animation Studios | SL7: Dreamworks | SM7: Overbrook Entertainment | SN7: Pixar Animation Studios | SO7: Tribeca Productions | SP7: Dreamworks | SQ7: Pixar Animation Studios | SR7: Intermedia | SS7: Jerry Bruckheimer Films | ST7: Touchstone Pictures | SU7: 20th Century Fox | SV7: Alphaville Films | SW7: Amblin Entertainment | SX7: Dino De Laurentiis Corporation | SY7: Icon Productions | SZ7: Walt Disney Pictures | TA7: Imagine Entertainment | TB7: Tribeca Productions | TC7: ImageMovers | TD7: Pixar Animation Studios | TE7: Walt Disney Pictures | TF7: Alphaville Films | TG7: Eric's Boy | TH7: Centropolis Entertainment | TI7: 20th Century Fox | TJ7: Pixar Animation Studios | TK7: Walt Disney Pictures | TL7: Davis Entertainment | TM7: Amblin Entertainment | TN7: Touchstone Pictures | TO7: Imagine Entertainment | TP7: Zucker Brothers Productions | TQ7: Amblin Entertainment | TR7: Walt Disney Pictures | TS7: Walt Disney Pictures | TT7: Touchstone Pictures | TU7: Imagine Entertainment | TV7: Gracie Films | TW7: Kopelson Entertainment | TX7: Pixar Animation Studios | TY7: Walt Disney Pictures | TZ7: Polygram Filmed Entertainment | UA7: Amblin Entertainment | UB7: Interscope Communications | UC7: Walt Disney Pictures | UD7: Dark Horse Entertainment | UE7: Mark Gordon Productions | UF7: Amblin Entertainment | UG7: Motion Picture Corporation of America | UH7: Channel Four Films | UI7: Geffen Pictures | UJ7: Blue Wolf Productions | UK7: Davis Entertainment | UL7: Paramount Pictures | UM7: TriStar Pictures | UN7: TriStar Pictures | UO7: Warner Bros. Pictures | UP7: Walt Disney Pictures | UQ7: Tig Productions | UR7: Hughes Entertainment | US7: Carolco Pictures | UT7: Polygram Filmed Entertainment | UU7: Castle Rock Entertainment | UV7: Touchstone Pictures | UW7: Columbia Pictures | UX7: Paramount Pictures | UY7: Walt Disney Pictures | UZ7: Amblin Entertainment | VA7: Strong Heart/Demme Production | VB7: Regency Enterprises | VC7: Orion Pictures | VD7: Amblin Entertainment | VE7: 20th Century Fox | VF7: Castle Rock Entertainment | VG7: Paramount Pictures | VH7: Hughes Entertainment | VI7: Touchstone Pictures | VJ7: Golden Harvest | VK7: Polygram Filmed Entertainment | VL7: TriStar Pictures | VM7: Touchstone Pictures | VN7: Walt Disney Pictures | VO7: Columbia Pictures | VP7: Walt Disney Pictures | VQ7: Universal Pictures | VR7: United Artists | VS7: Eddie Murphy Productions | VT7: Gracie Films | VU7: Paramount Pictures | VV7: Touchstone Pictures | VW7: Geffen Pictures | VX7: Touchstone Pictures | VY7: Paramount Pictures | VZ7: Paramount Pictures | WA7: Touchstone Pictures | WB7: Metro-Goldwyn-Mayer | WC7: Rastar | WD7: Touchstone Pictures | WE7: Kennedy Miller | WF7: Paramount Pictures | WG7: Hemdale | WH7: Columbia Pictures | WI7: Eddie Murphy Productions | WJ7: Paramount Pictures | WK7: Carolco Pictures | WL7: United Artists | WM7: Amblin Entertainment | WN7: Mirage Studios | WO7: 20th Century Fox | WP7: 20th Century Fox | WQ7: Amblin Entertainment | WR7: Warner Bros. Pictures | WS7: Eddie Murphy Productions | WT7: Amblin Entertainment | WU7: Columbia Pictures | WV7: The Ladd Company | WW7: Paramount Pictures | WX7: 20th Century Fox | WY7: Paramount Pictures | WZ7: Polygram Filmed Entertainment | XA7: Eddie Murphy Productions | XB7: United Artists | XC7: Warner Bros. Pictures | XD7: Paramount Pictures | XE7: Mirage Studios | XF7: Lorimar Productions | XG7: United Artists | XH7: Paramount Pictures | XI7: Metro-Goldwyn-Mayer | XJ7: Rastar | XK7: Orion Pictures | XL7: Golden Harvest | XM7: 20th Century Fox | XN7: Columbia Pictures | XO7: Paramount Pictures | XP7: The Malpaso Company | XQ7: Warner Bros. Pictures | XR7: Rastar | XS7: Universal Pictures | XT7: Columbia Pictures | XU7: Dino De Laurentiis Corporation | XV7: United Artists | XW7: Zoetrope Studios | XX7: Orion Pictures | XY7: Universal Pictures | XZ7: Henson Associates | YA7: Paramount Pictures | YB7: Universal Pictures | YC7: The Malpaso Company | YD7: Universal Pictures | YE7: Laurel Group | YF7: EMI Films | YG7: Rastar | YH7: EMI Films | YI7: Paramount Pictures | YJ7: EMI Films | YK7: United Artists | YL7: United Artists | YM7: Warner Bros. Pictures | YN7: 20th Century Fox | YO7: 20th Century Fox | YP7: Warner Bros. Pictures | YQ7: Universal Pictures | YR7: Universal Pictures | YS7: United Artists | YT7: Warner Bros. Pictures | YU7: Columbia Pictures | YV7: Warner Bros. Pictures | YW7: 20th Century Fox | YX7: 20th Century Fox | YY7: Universal Pictures | YZ7: Paramount Pictures | ZA7: Universal Pictures | ZB7: Paramount Pictures | ZC7: Universal Pictures | ZD7: Warner Bros. Pictures | ZE7: Lucasfilm | ZF7: Columbia Pictures | ZG7: Walt Disney Pictures | ZH7: Paramount Pictures | ZI7: 20th Century Fox | ZJ7: Warner Bros. Pictures | ZK7: Allied Artists | ZL7: The Mirisch Production Company | ZM7: 20th Century Fox | ZN7: The Malpaso Company | ZO7: Paramount Pictures | ZP7: Universal Pictures | ZQ7: 20th Century Fox | ZR7: 20th Century Fox | ZS7: United Artists | ZT7: Columbia Pictures | ZU7: The Malpaso Company | ZV7: Walt Disney Pictures | ZW7: Paramount Pictures | ZX7: Warner Bros. Pictures | ZY7: 20th Century Fox | ZZ7: United Artists | AAA7: Walt Disney Pictures | AAB7: Warner Bros. Pictures | AAC7: Metro-Goldwyn-Mayer | AAD7: Laurel Group | AAE7: Metro-Goldwyn-Mayer | AAF7: 20th Century Fox | AAG7: 20th Century Fox | AAH7: Warner Bros. Pictures | AAI7: 20th Century Fox | AAJ7: Metro-Goldwyn-Mayer | AAK7: United Artists | AAL7: Walt Disney Pictures | AAM7: Alfred J. Hitchcock Productions | AAN7: 20th Century Fox | AAO7: Metro-Goldwyn-Mayer | AAP7: Universal Pictures | AAQ7: The Mirisch Production Company | AAR7: Samuel Bronston Productions | AAS7: Walt Disney Pictures | AAT7: Bryna Productions | AAU7: Shamley Productions | AAV7: Walt Disney Pictures | AAW7: United Artists | AAX7: Warner Bros. Pictures | AAY7: Metro-Goldwyn-Mayer | AAZ7: Walt Disney Pictures | ABA7: Metro-Goldwyn-Mayer | ABB7: The Mirisch Production Company | ABC7: 20th Century Fox | ABD7: United Artists | ABE7: Paramount Pictures | ABF7: Selznick International Pictures | ABG7: Paramount Pictures | ABH7: Motion Picture Corporation of America | ABI7: Dino De Laurentiis Corporation | ABJ7: 20th Century Fox | ABK7: Warner Bros. Pictures | ABL7: Bing Crosby Productions | ABM7: RKO Radio Pictures | ABN7: Metro-Goldwyn-Mayer | ABO7: Walt Disney Pictures | ABP7: Walt Disney Pictures | ABQ7: 20th Century Fox | ABR7: Columbia Pictures | ABS7: Paramount Pictures | ABT7: Walt Disney Pictures | ABU7: 20th Century Fox | ABV7: Metro-Goldwyn-Mayer | ABW7: Walt Disney Pictures | ABX7: Warner Bros. Pictures | ABY7: Horizon Pictures | ABZ7: Transatlantic Pictures | ACA7: Walt Disney Pictures | ACB7: Metro-Goldwyn-Mayer | ACC7: Metro-Goldwyn-Mayer | ACD7: Republic Pictures | ACE7: Paramount Pictures | ACF7: Warner Bros. Pictures | ACG7: Charles Chaplin Film Corporation | ACH7: 20th Century Fox | ACI7: Selznick International Pictures | ACJ7: Metro-Goldwyn-Mayer | ACK7: Walt Disney Pictures | ACL7: Metro-Goldwyn-Mayer | ACM7: Universal Pictures | ACN7: Universal Pictures | ACO7: Universal Pictures | ACP7: Charles Chaplin Film Corporation | ACQ7: Lucasfilm | ACR7: Amblin Entertainment | ACS7: Original Film | ACT7: Marvel Entertainment | ACU7: Illumination Entertainment | ACV7: Pixar Animation Studios | ACW7: Cruise Wagner Productions | ACX7: Color Force | ACY7: Scott Free Productions | ACZ7: Marvel Entertainment | ADA7: Pixar Animation Studios | ADB7: Walt Disney Pictures | ADC7: Walt Disney Pictures | ADD7: DC Entertainment | ADE7: Illumination Entertainment | ADF7: Marvel Entertainment | ADG7: DC Entertainment | ADH7: Marvel Entertainment | ADI7: Marvel Entertainment | ADJ7: Walt Disney Pictures | ADK7: Cosmopolitan Productions | ADL7: Warner Bros. Pictures | ADM7: Warner Bros. Pictures | ADN7: Metro-Goldwyn-Mayer | ADO7: Seven Arts Productions | ADP7: Mercury Productions | ADQ7: Warner Bros. Pictures | ADR7: Liberty Films | ADS7: Columbia Pictures | ADT7: 20th Century Fox | ADU7: Sierra Pictures | ADV7: Metro-Goldwyn-Mayer | ADW7: Golden Harvest | ADX7: Silver Pictures | ADY7: Revolution Studios | ADZ7: Silver Pictures | AEA7: Relativity Media | AEB7: Relativity Media | AEC7: Millennium Films | AED7: Millennium Films | AEE7: Millennium Films | AEF7: Marvel Entertainment | AEG7: Summit Entertainment | AEH7: Legendary Pictures | AEI7: Alphaville Films | AEJ7: 20th Century Fox | AEK7: Paramount Pictures | AEL7: Lion Rock Productions | AEM7: China Film Group | AEN7: Moving Picture Company | AEO7: Marvel Entertainment | AEP7: Hasbro Studios | AEQ7: Relativity Media | AER7: Weed Road Pictures | AES7: di Bonaventura Pictures | AET7: Relativity Media | AEU7: Silver Pictures | AEV7: Rogue Pictures | AEW7: TriStar Pictures | AEX7: Columbia Pictures | AEY7: Walt Disney Pictures | AEZ7: Columbia Pictures | AFA7: Legendary Pictures | AFB7: Fox 2000 Pictures | AFC7: Paramount Pictures | AFD7: Lionsgate | AFE7: Open Road Films | AFF7: Summit Entertainment | AFG7: di Bonaventura Pictures | AFH7: Columbia Pictures | AFI7: Warner Bros. Pictures | AFJ7: Columbia Pictures | AFK7: Beacon Pictures | AFL7: Polygram Filmed Entertainment | AFM7: 20th Century Fox | AFN7: Universal Pictures | AFO7: Relativity Media | AFP7: Paramount Pictures | AFQ7: Carolco Pictures | AFR7: Silver Pictures | AFS7: Dino De Laurentiis Corporation | AFT7: Silver Pictures | AFU7: Marvel Entertainment | AFV7: Dino De Laurentiis Corporation | AFW7: Dino De Laurentiis Corporation | AFX7: Millennium Films | AFY7: White Mountain Films | AFZ7: Dune Entertainment | AGA7: Legendary Pictures | AGB7: Marvel Entertainment | AGC7: Columbia Pictures | AGD7: Columbia Pictures | AGE7: The Ladd Company | AGF7: Lakeshore Entertainment | AGG7: Lakeshore Entertainment | AGH7: StudioCanal | AGI7: Regency Enterprises | AGJ7: Dreamworks | AGK7: Universal Pictures | AGL7: Amblin Entertainment | AGM7: Dreamworks | AGN7: Amblin Entertainment | AGO7: Amblin Entertainment | AGP7: Amblin Entertainment | AGQ7: Amblin Entertainment | AGR7: Tim Burton Productions | AGS7: Walt Disney Pictures | AGT7: Legendary Pictures | AGU7: StudioCanal | AGV7: Touchstone Pictures | AGW7: Polygram Filmed Entertainment | AGX7: 20th Century Fox | AGY7: Virtual Studios | AGZ7: Dark Horse Entertainment | AHA7: Dreamworks | AHB7: Carolco Pictures | AHC7: Columbia Pictures | AHD7: Pathe | AHE7: Kings Road Entertainment | AHF7: The Cannon Group | AHG7: The Cannon Group | AHH7: Millennium Films | AHI7: Bryna Productions | AHJ7: Warner Bros. Pictures | AHK7: United Artists | AHL7: The Malpaso Company | AHM7: The Malpaso Company | AHN7: The Malpaso Company | AHO7: Metro-Goldwyn-Mayer | AHP7: The Malpaso Company | AHQ7: The Malpaso Company | AHR7: The Malpaso Company | AHS7: The Malpaso Company | AHT7: The Malpaso Company | AHU7: The Malpaso Company | AHV7: Village Roadshow Pictures | AHW7: Village Roadshow Pictures | AHX7: Imagine Entertainment | AHY7: Imagine Entertainment | AHZ7: Marvel Entertainment | AIA7: Kopelson Entertainment | AIB7: Paramount Pictures | AIC7: Silver Pictures | AID7: Warner Bros. Pictures | AIE7: Act III Communications | AIF7: United Artists | AIG7: Seven Arts Productions | AIH7: New Line Cinema | AII7: EMI Films | AIJ7: First Artists | AIK7: ABC Pictures | AIL7: United Artists | AIM7: The Mirisch Production Company | AIN7: Bad Robot Productions | AIO7: Bad Robot Productions | AIP7: Bad Robot Productions | AIQ7: Orion Pictures | AIR7: Metro-Goldwyn-Mayer | AIS7: View Askew Productions | AIT7: View Askew Productions | AIU7: View Askew Productions | AIV7: View Askew Productions | AIW7: FilmDistrict | AIX7: Columbia Pictures | AIY7: Warner Bros. Pictures | AIZ7: United Artists | AJA7: Embassy International | AJB7: Touchstone Pictures | AJC7: Universal Pictures | AJD7: Columbia Pictures | AJE7: Paramount Pictures | AJF7: Paramount Pictures | AJG7: Paramount Pictures | AJH7: Village Roadshow Pictures | AJI7: Lucasfilm | AJJ7: Village Roadshow Pictures | AJK7: Paramount Pictures | AJL7: Dino De Laurentiis Corporation | AJM7: Silver Pictures | AJN7: Silver Pictures | AJO7: Centropolis Entertainment | AJP7: Village Roadshow Pictures | AJQ7: The Kennedy Marshall Company | AJR7: Columbia Pictures | AJS7: A Band Apart | AJT7: A Band Apart | AJU7: Columbia Pictures | AJV7: Double Feature Films | AJW7: Interscope Communications | AJX7: Interscope Communications | AJY7: The Mirisch Production Company | AJZ7: Village Roadshow Pictures | AKA7: Columbia Pictures | AKB7: Village Roadshow Pictures | AKC7: Revolution Studios | AKD7: Touchstone Pictures | AKE7: di Bonaventura Pictures | AKF7: Millennium Films | AKG7: Village Roadshow Pictures | AKH7: Fuqua Films | AKI7: Tim Burton Productions | AKJ7: Tim Burton Productions | AKK7: The Zanuck Company | AKL7: The Zanuck Company | AKM7: Village Roadshow Pictures | AKN7: Legendary Pictures | AKO7: Legendary Pictures | AKP7: Legendary Pictures | AKQ7: Strike Entertainment | AKR7: Paramount Pictures | AKS7: Paramount Pictures | AKT7: Artisan Entertainment | AKU7: Walt Disney Pictures | AKV7: Dimension Films | AKW7: Miramax Films | AKX7: Lucasfilm | AKY7: Village Roadshow Pictures | AKZ7: Black Bear Pictures | ALA7: Legendary Pictures | ALB7: Dino De Laurentiis Corporation | ALC7: 20th Century Fox | ALD7: Summit Entertainment | ALE7: Walt Disney Pictures | ALF7: Lightstorm Entertainment | ALG7: Intermedia | ALH7: Summit Entertainment | ALI7: Columbia Pictures | ALJ7: Davis Entertainment | ALK7: Scott Free Productions | ALL7: Embassy International | ALM7: Paramount Pictures | ALN7: Pathe | ALO7: Paramount Pictures | ALP7: Scott Free Productions | ALQ7: Scott Free Productions | ALR7: Scott Free Productions | ALS7: Scott Free Productions | ALT7: Scott Free Productions | ALU7: Temple Hill Entertainment | ALV7: Original Film | ALW7: Scott Rudin Productions | ALX7: Summit Entertainment | ALY7: Regency Enterprises | ALZ7: Regency Enterprises | AMA7: This Is That | AMB7: Universal Pictures | AMC7: Universal Pictures | AMD7: Universal Pictures | AME7: Paramount Pictures | AMF7: Miramax Films | AMG7: New Line Cinema | AMH7: The Weinstein Company | AMI7: Warner Bros. Pictures | AMJ7: New Line Cinema | AMK7: Amblin Entertainment | AML7: Marvel Entertainment | AMM7: TriStar Pictures | AMN7: Summit Entertainment | AMO7: Warner Bros. Pictures | AMP7: Dreamworks | AMQ7: Regency Enterprises | AMR7: Village Roadshow Pictures | AMS7: Lionsgate | AMT7: Village Roadshow Pictures | AMU7: Universal Pictures | AMV7: Relativity Media | AMW7: Relativity Media | AMX7: Dimension Films | AMY7: Marvel Entertainment | AMZ7: Relativity Media | ANA7: Marvel Entertainment | ANB7: Lightstorm Entertainment | ANC7: Warner Bros. Pictures | AND7: Walt Disney Pictures | ANE7: Polygram Filmed Entertainment | ANF7: Walt Disney Pictures | ANG7: Morgan Creek Productions | ANH7: Morgan Creek Productions | ANI7: Warner Bros. Pictures | ANJ7: Columbia Pictures | ANK7: Relativity Media | ANL7: Sony Pictures | ANM7: 20th Century Fox | ANN7: Paramount Pictures | ANO7: Sony Pictures | ANP7: Village Roadshow Pictures | ANQ7: Jerry Bruckheimer Films | ANR7: Original Film | ANS7: 20th Century Fox | ANT7: Walt Disney Pictures | ANU7: Walt Disney Pictures | ANV7: 20th Century Fox | ANW7: Metro-Goldwyn-Mayer | ANX7: Cannon Productions | ANY7: Warner Bros. Pictures | ANZ7: Warner Bros. Pictures | AOA7: 20th Century Fox | AOB7: 20th Century Fox | AOC7: Horizon Pictures | AOD7: 20th Century Fox | AOE7: United Artists | AOF7: Paramount Pictures | AOG7: Columbia Pictures | AOH7: Paramount Pictures | AOI7: Kings Road Entertainment | AOJ7: Castle Rock Entertainment
A8: Country | B8: Australia | C8: Australia | D8: Australia | E8: Australia | F8: Australia | G8: Australia | H8: Australia | I8: Brazil | J8: Canada | K8: Canada | L8: China | M8: China | N8: China | O8: China | P8: China | Q8: China | R8: China | S8: China | T8: Denmark | U8: France | V8: France | W8: France | X8: France | Y8: France | Z8: France | AA8: France | AB8: France | AC8: France | AD8: France | AE8: France | AF8: France | AG8: France | AH8: France | AI8: Germany | AJ8: Germany | AK8: Germany | AL8: Germany | AM8: Germany | AN8: Hong Kong | AO8: Hong Kong | AP8: Hong Kong | AQ8: Hong Kong | AR8: Hong Kong | AS8: Hong Kong | AT8: Hong Kong | AU8: Hong Kong | AV8: Hong Kong | AW8: Hong Kong | AX8: Hong Kong | AY8: Hong Kong | AZ8: Hong Kong | BA8: Hong Kong | BB8: Hong Kong | BC8: Hong Kong | BD8: Hong Kong | BE8: Indonesia | BF8: Indonesia | BG8: Italy | BH8: Italy | BI8: Italy | BJ8: Italy | BK8: Japan | BL8: Japan | BM8: Japan | BN8: Japan | BO8: Japan | BP8: Japan | BQ8: Japan | BR8: Japan | BS8: Japan | BT8: Japan | BU8: Japan | BV8: Japan | BW8: Netherlands | BX8: New Zealand | BY8: New Zealand | BZ8: New Zealand | CA8: New Zealand | CB8: New Zealand | CC8: New Zealand | CD8: New Zealand | CE8: New Zealand | CF8: NULL | CG8: Russia | CH8: Russia | CI8: South Africa | CJ8: South Africa | CK8: Sweden | CL8: Sweden | CM8: Sweden | CN8: Thailand | CO8: Thailand | CP8: Thailand | CQ8: Thailand | CR8: United Kingdom | CS8: United Kingdom | CT8: United Kingdom | CU8: United Kingdom | CV8: United Kingdom | CW8: United Kingdom | CX8: United Kingdom | CY8: United Kingdom | CZ8: United Kingdom | DA8: United Kingdom | DB8: United Kingdom | DC8: United Kingdom | DD8: United Kingdom | DE8: United Kingdom | DF8: United Kingdom | DG8: United Kingdom | DH8: United Kingdom | DI8: United Kingdom | DJ8: United Kingdom | DK8: United Kingdom | DL8: United Kingdom | DM8: United Kingdom | DN8: United Kingdom | DO8: United Kingdom | DP8: United Kingdom | DQ8: United Kingdom | DR8: United Kingdom | DS8: United Kingdom | DT8: United Kingdom | DU8: United Kingdom | DV8: United Kingdom | DW8: United Kingdom | DX8: United Kingdom | DY8: United Kingdom | DZ8: United Kingdom | EA8: United Kingdom | EB8: United Kingdom | EC8: United Kingdom | ED8: United Kingdom | EE8: United Kingdom | EF8: United Kingdom | EG8: United Kingdom | EH8: United Kingdom | EI8: United Kingdom | EJ8: United Kingdom | EK8: United Kingdom | EL8: United Kingdom | EM8: United Kingdom | EN8: United Kingdom | EO8: United Kingdom | EP8: United Kingdom | EQ8: United Kingdom | ER8: United Kingdom | ES8: United Kingdom | ET8: United Kingdom | EU8: United Kingdom | EV8: United Kingdom | EW8: United Kingdom | EX8: United Kingdom | EY8: United Kingdom | EZ8: United Kingdom | FA8: United Kingdom | FB8: United Kingdom | FC8: United Kingdom | FD8: United Kingdom | FE8: United Kingdom | FF8: United Kingdom | FG8: United Kingdom | FH8: United Kingdom | FI8: United Kingdom | FJ8: United Kingdom | FK8: United Kingdom | FL8: United Kingdom | FM8: United Kingdom | FN8: United Kingdom | FO8: United Kingdom | FP8: United Kingdom | FQ8: United Kingdom | FR8: United Kingdom | FS8: United Kingdom | FT8: United Kingdom | FU8: United Kingdom | FV8: United Kingdom | FW8: United Kingdom | FX8: United Kingdom | FY8: United Kingdom | FZ8: United Kingdom | GA8: United Kingdom | GB8: United Kingdom | GC8: United Kingdom | GD8: United Kingdom | GE8: United Kingdom | GF8: United Kingdom | GG8: United Kingdom | GH8: United Kingdom | GI8: United Kingdom | GJ8: United Kingdom | GK8: United Kingdom | GL8: United Kingdom | GM8: United Kingdom | GN8: United Kingdom | GO8: United Kingdom | GP8: United Kingdom | GQ8: United Kingdom | GR8: United Kingdom | GS8: United Kingdom | GT8: United Kingdom | GU8: United Kingdom | GV8: United Kingdom | GW8: United Kingdom | GX8: United Kingdom | GY8: United Kingdom | GZ8: United Kingdom | HA8: United Kingdom | HB8: United Kingdom | HC8: United Kingdom | HD8: United Kingdom | HE8: United Kingdom | HF8: United Kingdom | HG8: United Kingdom | HH8: United Kingdom | HI8: United Kingdom | HJ8: United Kingdom | HK8: United Kingdom | HL8: United Kingdom | HM8: United Kingdom | HN8: United Kingdom | HO8: United Kingdom | HP8: United Kingdom | HQ8: United Kingdom | HR8: United Kingdom | HS8: United Kingdom | HT8: United Kingdom | HU8: United Kingdom | HV8: United Kingdom | HW8: United Kingdom | HX8: United Kingdom | HY8: United Kingdom | HZ8: United Kingdom | IA8: United States | IB8: United States | IC8: United States | ID8: United States | IE8: United States | IF8: United States | IG8: United States | IH8: United States | II8: United States | IJ8: United States | IK8: United States | IL8: United States | IM8: United States | IN8: United States | IO8: United States | IP8: United States | IQ8: United States | IR8: United States | IS8: United States | IT8: United States | IU8: United States | IV8: United States | IW8: United States | IX8: United States | IY8: United States | IZ8: United States | JA8: United States | JB8: United States | JC8: United States | JD8: United States | JE8: United States | JF8: United States | JG8: United States | JH8: United States | JI8: United States | JJ8: United States | JK8: United States | JL8: United States | JM8: United States | JN8: United States | JO8: United States | JP8: United States | JQ8: United States | JR8: United States | JS8: United States | JT8: United States | JU8: United States | JV8: United States | JW8: United States | JX8: United States | JY8: United States | JZ8: United States | KA8: United States | KB8: United States | KC8: United States | KD8: United States | KE8: United States | KF8: United States | KG8: United States | KH8: United States | KI8: United States | KJ8: United States | KK8: United States | KL8: United States | KM8: United States | KN8: United States | KO8: United States | KP8: United States | KQ8: United States | KR8: United States | KS8: United States | KT8: United States | KU8: United States | KV8: United States | KW8: United States | KX8: United States | KY8: United States | KZ8: United States | LA8: United States | LB8: United States | LC8: United States | LD8: United States | LE8: United States | LF8: United States | LG8: United States | LH8: United States | LI8: United States | LJ8: United States | LK8: United States | LL8: United States | LM8: United States | LN8: United States | LO8: United States | LP8: United States | LQ8: United States | LR8: United States | LS8: United States | LT8: United States | LU8: United States | LV8: United States | LW8: United States | LX8: United States | LY8: United States | LZ8: United States | MA8: United States | MB8: United States | MC8: United States | MD8: United States | ME8: United States | MF8: United States | MG8: United States | MH8: United States | MI8: United States | MJ8: United States | MK8: United States | ML8: United States | MM8: United States | MN8: United States | MO8: United States | MP8: United States | MQ8: United States | MR8: United States | MS8: United States | MT8: United States | MU8: United States | MV8: United States | MW8: United States | MX8: United States | MY8: United States | MZ8: United States | NA8: United States | NB8: United States | NC8: United States | ND8: United States | NE8: United States | NF8: United States | NG8: United States | NH8: United States | NI8: United States | NJ8: United States | NK8: United States | NL8: United States | NM8: United States | NN8: United States | NO8: United States | NP8: United States | NQ8: United States | NR8: United States | NS8: United States | NT8: United States | NU8: United States | NV8: United States | NW8: United States | NX8: United States | NY8: United States | NZ8: United States | OA8: United States | OB8: United States | OC8: United States | OD8: United States | OE8: United States | OF8: United States | OG8: United States | OH8: United States | OI8: United States | OJ8: United States | OK8: United States | OL8: United States | OM8: United States | ON8: United States | OO8: United States | OP8: United States | OQ8: United States | OR8: United States | OS8: United States | OT8: United States | OU8: United States | OV8: United States | OW8: United States | OX8: United States | OY8: United States | OZ8: United States | PA8: United States | PB8: United States | PC8: United States | PD8: United States | PE8: United States | PF8: United States | PG8: United States | PH8: United States | PI8: United States | PJ8: United States | PK8: United States | PL8: United States | PM8: United States | PN8: United States | PO8: United States | PP8: United States | PQ8: United States | PR8: United States | PS8: United States | PT8: United States | PU8: United States | PV8: United States | PW8: United States | PX8: United States | PY8: United States | PZ8: United States | QA8: United States | QB8: United States | QC8: United States | QD8: United States | QE8: United States | QF8: United States | QG8: United States | QH8: United States | QI8: United States | QJ8: United States | QK8: United States | QL8: United States | QM8: United States | QN8: United States | QO8: United States | QP8: United States | QQ8: United States | QR8: United States | QS8: United States | QT8: United States | QU8: United States | QV8: United States | QW8: United States | QX8: United States | QY8: United States | QZ8: United States | RA8: United States | RB8: United States | RC8: United States | RD8: United States | RE8: United States | RF8: United States | RG8: United States | RH8: United States | RI8: United States | RJ8: United States | RK8: United States | RL8: United States | RM8: United States | RN8: United States | RO8: United States | RP8: United States | RQ8: United States | RR8: United States | RS8: United States | RT8: United States | RU8: United States | RV8: United States | RW8: United States | RX8: United States | RY8: United States | RZ8: United States | SA8: United States | SB8: United States | SC8: United States | SD8: United States | SE8: United States | SF8: United States | SG8: United States | SH8: United States | SI8: United States | SJ8: United States | SK8: United States | SL8: United States | SM8: United States | SN8: United States | SO8: United States | SP8: United States | SQ8: United States | SR8: United States | SS8: United States | ST8: United States | SU8: United States | SV8: United States | SW8: United States | SX8: United States | SY8: United States | SZ8: United States | TA8: United States | TB8: United States | TC8: United States | TD8: United States | TE8: United States | TF8: United States | TG8: United States | TH8: United States | TI8: United States | TJ8: United States | TK8: United States | TL8: United States | TM8: United States | TN8: United States | TO8: United States | TP8: United States | TQ8: United States | TR8: United States | TS8: United States | TT8: United States | TU8: United States | TV8: United States | TW8: United States | TX8: United States | TY8: United States | TZ8: United States | UA8: United States | UB8: United States | UC8: United States | UD8: United States | UE8: United States | UF8: United States | UG8: United States | UH8: United States | UI8: United States | UJ8: United States | UK8: United States | UL8: United States | UM8: United States | UN8: United States | UO8: United States | UP8: United States | UQ8: United States | UR8: United States | US8: United States | UT8: United States | UU8: United States | UV8: United States | UW8: United States | UX8: United States | UY8: United States | UZ8: United States | VA8: United States | VB8: United States | VC8: United States | VD8: United States | VE8: United States | VF8: United States | VG8: United States | VH8: United States | VI8: United States | VJ8: United States | VK8: United States | VL8: United States | VM8: United States | VN8: United States | VO8: United States | VP8: United States | VQ8: United States | VR8: United States | VS8: United States | VT8: United States | VU8: United States | VV8: United States | VW8: United States | VX8: United States | VY8: United States | VZ8: United States | WA8: United States | WB8: United States | WC8: United States | WD8: United States | WE8: United States | WF8: United States | WG8: United States | WH8: United States | WI8: United States | WJ8: United States | WK8: United States | WL8: United States | WM8: United States | WN8: United States | WO8: United States | WP8: United States | WQ8: United States | WR8: United States | WS8: United States | WT8: United States | WU8: United States | WV8: United States | WW8: United States | WX8: United States | WY8: United States | WZ8: United States | XA8: United States | XB8: United States | XC8: United States | XD8: United States | XE8: United States | XF8: United States | XG8: United States | XH8: United States | XI8: United States | XJ8: United States | XK8: United States | XL8: United States | XM8: United States | XN8: United States | XO8: United States | XP8: United States | XQ8: United States | XR8: United States | XS8: United States | XT8: United States | XU8: United States | XV8: United States | XW8: United States | XX8: United States | XY8: United States | XZ8: United States | YA8: United States | YB8: United States | YC8: United States | YD8: United States | YE8: United States | YF8: United States | YG8: United States | YH8: United States | YI8: United States | YJ8: United States | YK8: United States | YL8: United States | YM8: United States | YN8: United States | YO8: United States | YP8: United States | YQ8: United States | YR8: United States | YS8: United States | YT8: United States | YU8: United States | YV8: United States | YW8: United States | YX8: United States | YY8: United States | YZ8: United States | ZA8: United States | ZB8: United States | ZC8: United States | ZD8: United States | ZE8: United States | ZF8: United States | ZG8: United States | ZH8: United States | ZI8: United States | ZJ8: United States | ZK8: United States | ZL8: United States | ZM8: United States | ZN8: United States | ZO8: United States | ZP8: United States | ZQ8: United States | ZR8: United States | ZS8: United States | ZT8: United States | ZU8: United States | ZV8: United States | ZW8: United States | ZX8: United States | ZY8: United States | ZZ8: United States | AAA8: United States | AAB8: United States | AAC8: United States | AAD8: United States | AAE8: United States | AAF8: United States | AAG8: United States | AAH8: United States | AAI8: United States | AAJ8: United States | AAK8: United States | AAL8: United States | AAM8: United States | AAN8: United States | AAO8: United States | AAP8: United States | AAQ8: United States | AAR8: United States | AAS8: United States | AAT8: United States | AAU8: United States | AAV8: United States | AAW8: United States | AAX8: United States | AAY8: United States | AAZ8: United States | ABA8: United States | ABB8: United States | ABC8: United States | ABD8: United States | ABE8: United States | ABF8: United States | ABG8: United States | ABH8: United States | ABI8: United States | ABJ8: United States | ABK8: United States | ABL8: United States | ABM8: United States | ABN8: United States | ABO8: United States | ABP8: United States | ABQ8: United States | ABR8: United States | ABS8: United States | ABT8: United States | ABU8: United States | ABV8: United States | ABW8: United States | ABX8: United States | ABY8: United States | ABZ8: United States | ACA8: United States | ACB8: United States | ACC8: United States | ACD8: United States | ACE8: United States | ACF8: United States | ACG8: United States | ACH8: United States | ACI8: United States | ACJ8: United States | ACK8: United States | ACL8: United States | ACM8: United States | ACN8: United States | ACO8: United States | ACP8: United States | ACQ8: United States | ACR8: United States | ACS8: United States | ACT8: United States | ACU8: United States | ACV8: United States | ACW8: United States | ACX8: United States | ACY8: United States | ACZ8: United States | ADA8: United States | ADB8: United States | ADC8: United States | ADD8: United States | ADE8: United States | ADF8: United States | ADG8: United States | ADH8: United States | ADI8: United States | ADJ8: United States | ADK8: United States | ADL8: United States | ADM8: United States | ADN8: United States | ADO8: United States | ADP8: United States | ADQ8: United States | ADR8: United States | ADS8: United States | ADT8: United States | ADU8: United States | ADV8: United States | ADW8: United States | ADX8: United States | ADY8: United States | ADZ8: United States | AEA8: United States | AEB8: United States | AEC8: United States | AED8: United States | AEE8: United States | AEF8: United States | AEG8: United States | AEH8: United States | AEI8: United States | AEJ8: United States | AEK8: United States | AEL8: United States | AEM8: United States | AEN8: United States | AEO8: United States | AEP8: United States | AEQ8: United States | AER8: United States | AES8: United States | AET8: United States | AEU8: United States | AEV8: United States | AEW8: United States | AEX8: United States | AEY8: United States | AEZ8: United States | AFA8: United States | AFB8: United States | AFC8: United States | AFD8: United States | AFE8: United States | AFF8: United States | AFG8: United States | AFH8: United States | AFI8: United States | AFJ8: United States | AFK8: United States | AFL8: United States | AFM8: United States | AFN8: United States | AFO8: United States | AFP8: United States | AFQ8: United States | AFR8: United States | AFS8: United States | AFT8: United States | AFU8: United States | AFV8: United States | AFW8: United States | AFX8: United States | AFY8: United States | AFZ8: United States | AGA8: United States | AGB8: United States | AGC8: United States | AGD8: United States | AGE8: United States | AGF8: United States | AGG8: United States | AGH8: United States | AGI8: United States | AGJ8: United States | AGK8: United States | AGL8: United States | AGM8: United States | AGN8: United States | AGO8: United States | AGP8: United States | AGQ8: United States | AGR8: United States | AGS8: United States | AGT8: United States | AGU8: United States | AGV8: United States | AGW8: United States | AGX8: United States | AGY8: United States | AGZ8: United States | AHA8: United States | AHB8: United States | AHC8: United States | AHD8: United States | AHE8: United States | AHF8: United States | AHG8: United States | AHH8: United States | AHI8: United States | AHJ8: United States | AHK8: United States | AHL8: United States | AHM8: United States | AHN8: United States | AHO8: United States | AHP8: United States | AHQ8: United States | AHR8: United States | AHS8: United States | AHT8: United States | AHU8: United States | AHV8: United States | AHW8: United States | AHX8: United States | AHY8: United States | AHZ8: United States | AIA8: United States | AIB8: United States | AIC8: United States | AID8: United States | AIE8: United States | AIF8: United States | AIG8: United States | AIH8: United States | AII8: United States | AIJ8: United States | AIK8: United States | AIL8: United States | AIM8: United States | AIN8: United States | AIO8: United States | AIP8: United States | AIQ8: United States | AIR8: United States | AIS8: United States | AIT8: United States | AIU8: United States | AIV8: United States | AIW8: United States | AIX8: United States | AIY8: United States | AIZ8: United States | AJA8: United States | AJB8: United States | AJC8: United States | AJD8: United States | AJE8: United States | AJF8: United States | AJG8: United States | AJH8: United States | AJI8: United States | AJJ8: United States | AJK8: United States | AJL8: United States | AJM8: United States | AJN8: United States | AJO8: United States | AJP8: United States | AJQ8: United States | AJR8: United States | AJS8: United States | AJT8: United States | AJU8: United States | AJV8: United States | AJW8: United States | AJX8: United States | AJY8: United States | AJZ8: United States | AKA8: United States | AKB8: United States | AKC8: United States | AKD8: United States | AKE8: United States | AKF8: United States | AKG8: United States | AKH8: United States | AKI8: United States | AKJ8: United States | AKK8: United States | AKL8: United States | AKM8: United States | AKN8: United States | AKO8: United States | AKP8: United States | AKQ8: United States | AKR8: United States | AKS8: United States | AKT8: United States | AKU8: United States | AKV8: United States | AKW8: United States | AKX8: United States | AKY8: United States | AKZ8: United States | ALA8: United States | ALB8: United States | ALC8: United States | ALD8: United States | ALE8: United States | ALF8: United States | ALG8: United States | ALH8: United States | ALI8: United States | ALJ8: United States | ALK8: United States | ALL8: United States | ALM8: United States | ALN8: United States | ALO8: United States | ALP8: United States | ALQ8: United States | ALR8: United States | ALS8: United States | ALT8: United States | ALU8: United States | ALV8: United States | ALW8: United States | ALX8: United States | ALY8: United States | ALZ8: United States | AMA8: United States | AMB8: United States | AMC8: United States | AMD8: United States | AME8: United States | AMF8: United States | AMG8: United States | AMH8: United States | AMI8: United States | AMJ8: United States | AMK8: United States | AML8: United States | AMM8: United States | AMN8: United States | AMO8: United States | AMP8: United States | AMQ8: United States | AMR8: United States | AMS8: United States | AMT8: United States | AMU8: United States | AMV8: United States | AMW8: United States | AMX8: United States | AMY8: United States | AMZ8: United States | ANA8: United States | ANB8: United States | ANC8: United States | AND8: United States | ANE8: United States | ANF8: United States | ANG8: United States | ANH8: United States | ANI8: United States | ANJ8: United States | ANK8: United States | ANL8: United States | ANM8: United States | ANN8: United States | ANO8: United States | ANP8: United States | ANQ8: United States | ANR8: United States | ANS8: United States | ANT8: United States | ANU8: United States | ANV8: United States | ANW8: United States | ANX8: United States | ANY8: United States | ANZ8: United States | AOA8: United States | AOB8: United States | AOC8: United States | AOD8: United States | AOE8: United States | AOF8: United States | AOG8: United States | AOH8: United States | AOI8: United States | AOJ8: United States
